Workbook

Sheet 账单封面
C3: 客户对账单
C5: 947270-FB4-M20260430
D7: 客户代码： | E7: L65EXQC | G7: 客户名称： | H7: SINOWELL TRADING LIMITED
D8: 服务类别： | E8: FB4 | G8: 销售组织： | H8: GFN-总部商务中心
D9: 结算方式： | E9: 月结 | G9: 结算组织： | H9: 4PX DIGITAL PARCEL EXPRESS CO., LIMITED
D10: 结算日： | E10: 2026.05.25 | G10: 账单期间： | H10: 2026.04.01-2026.04.30
C12: 币种维度：
C13: 币种 | D13: 本期消费(-)
C14: EUR | D14: 77457.89 | E14: 0.8501 | F14: =D14/E14
C15: GBP | D15: 14518.28 | E15: 0.7307 | F15: =D15/E15
C16: USD | D16: 5140.96 | E16: 1 | F16: =D16/E16
C17: AUD | D17: 73695.73 | E17: 1.3701 | F17: =D17/E17
C18: CAD | D18: 45484.32 | E18: 1.3508 | F18: =D18/E18
F19: =SUM(F14:F18)
C20: 仓库维度：
C21: 仓库 | F21: 单量 | G21: 币种 | H21: 账单金额 | J21: 含代收代付税费 | L21: 可开票金额
C22: 德国法兰克福2仓 | F22: 98 | G22: EUR | H22: 127.44 | J22: 0 | L22: 127.44
C23: 德国法兰克福1仓 | F23: 7 | G23: EUR | H23: 39.2 | J23: 0 | L23: 39.2
C24: 德国法兰克福2仓 | F24: 8300 | G24: EUR | H24: 42334.58 | J24: 0 | L24: 42334.58
C25: 德国曼海姆1仓 | F25: 3088 | G25: EUR | H25: 15203.1 | J25: 0 | L25: 15203.1
C26: 德国法兰克福2仓 | E26: 请您查收，实际汇率还是按照收汇日当天的汇率~ | F26: 8 | G26: EUR | H26: 5277.99 | J26: 0 | L26: 5277.99
C27: 德国曼海姆1仓 | E27: 入库订单 | F27: 1 | G27: EUR | H27: 7.82 | J27: 0 | L27: 7.82
C28: 德国法兰克福2仓 | E28: 退件订单 | F28: 204 | G28: EUR | H28: 823.49 | J28: 0 | L28: 823.49
C29: 德国曼海姆1仓 | E29: 退件订单 | F29: 33 | G29: EUR | H29: 97.5 | J29: 0 | L29: 97.5
C30: 德国法兰克福2仓 | E30: 仓租 | F30: - | G30: EUR | H30: 10727.21 | J30: 0 | L30: 10727.21
C31: 德国曼海姆1仓 | E31: 仓租 | F31: - | G31: EUR | H31: 2819.56 | J31: 0 | L31: 2819.56
C32: 英国莱斯特1仓 | E32: 增值服务 | F32: 23 | G32: GBP | H32: 26.32 | J32: 0 | L32: 26.32
C33: 英国路腾1仓 | E33: 增值服务 | F33: 1 | G33: GBP | H33: 4.4 | J33: 0 | L33: 4.4
C34: 英国莱斯特1仓 | E34: 出库订单 | F34: 18 | G34: GBP | H34: 52.44 | J34: 0 | L34: 52.44
C35: 英国路腾1仓 | E35: 出库订单 | F35: 2642 | G35: GBP | H35: 6258.91 | J35: 0 | L35: 6258.91
C36: 英国路腾1仓 | E36: 入库订单 | F36: 3 | G36: GBP | H36: 995.7 | J36: 0 | L36: 995.7
C37: 英国莱斯特1仓 | E37: 退件订单 | F37: 36 | G37: GBP | H37: 189.34 | J37: 0 | L37: 189.34
C38: 英国莱斯特1仓 | E38: 仓租 | F38: - | G38: GBP | H38: 54.46 | J38: 0 | L38: 54.46
C39: 英国路腾1仓 | E39: 仓租 | F39: - | G39: GBP | H39: 6936.71 | J39: 0 | L39: 6936.71
C40: 美国休斯顿1仓 | E40: 出库订单 | F40: 7 | G40: USD | H40: 131.02 | J40: 0 | L40: 131.02
C41: 美西洛杉矶3仓 | E41: 出库订单 | F41: 24 | G41: USD | H41: 318.74 | J41: 0 | L41: 318.74
C42: 美东新泽西2仓 | E42: 出库订单 | F42: 201 | G42: USD | H42: 2727.15 | J42: 0 | L42: 2727.15
C43: 澳大利亚悉尼2仓 | E43: 入库订单 | F43: 2 | G43: USD | H43: 0 | J43: 0 | L43: 0
C44: 加拿大温哥华1仓 | E44: 入库订单 | F44: 1 | G44: USD | H44: 0 | J44: 0 | L44: 0
C45: 德国法兰克福2仓 | E45: 入库订单 | F45: 4 | G45: USD | H45: 0 | J45: 0 | L45: 0
C46: 德国曼海姆1仓 | E46: 入库订单 | F46: 1 | G46: USD | H46: 0 | J46: 0 | L46: 0
C47: 英国路腾1仓 | E47: 入库订单 | F47: 2 | G47: USD | H47: 0 | J47: 0 | L47: 0
C48: 美国休斯顿1仓 | E48: 仓租 | F48: - | G48: USD | H48: 132.19 | J48: 0 | L48: 132.19
C49: 美西洛杉矶3仓 | E49: 仓租 | F49: - | G49: USD | H49: 161.37 | J49: 0 | L49: 161.37
C50: 美东新泽西2仓 | E50: 仓租 | F50: - | G50: USD | H50: 1670.49 | J50: 0 | L50: 1670.49
C51: 澳大利亚悉尼1仓 | E51: 增值服务 | F51: 12 | G51: AUD | H51: 17.36 | J51: 0 | L51: 17.36
C52: 澳大利亚悉尼1仓 | E52: 出库订单 | F52: 32 | G52: AUD | H52: 818.58 | J52: 0 | L52: 818.58
C53: 澳大利亚悉尼2仓 | E53: 出库订单 | F53: 2918 | G53: AUD | H53: 67117.73 | J53: 0 | L53: 67117.73
C54: 澳大利亚悉尼2仓 | E54: 入库订单 | F54: 3 | G54: AUD | H54: 2619.14 | J54: 0 | L54: 2619.14
C55: 澳大利亚悉尼1仓 | E55: 退件订单 | F55: 14 | G55: AUD | H55: 128.27 | J55: 0 | L55: 128.27
C56: 澳大利亚悉尼2仓 | E56: 退件订单 | F56: 4 | G56: AUD | H56: 18.9 | J56: 0 | L56: 18.9
C57: 澳大利亚悉尼1仓 | E57: 仓租 | F57: - | G57: AUD | H57: 0 | J57: 0 | L57: 0
C58: 澳大利亚悉尼2仓 | E58: 仓租 | F58: - | G58: AUD | H58: 2975.75 | J58: 0 | L58: 2975.75
C59: 加拿大温哥华1仓 | E59: 增值服务 | F59: 3 | G59: CAD | H59: 12.88 | J59: 0 | L59: 12.88
C60: 加拿大温哥华1仓 | E60: 出库订单 | F60: 776 | G60: CAD | H60: 42482.55 | J60: 0 | L60: 42482.55
C61: 加拿大温哥华1仓 | E61: 入库订单 | F61: 1 | G61: CAD | H61: 688.02 | J61: 0 | L61: 688.02
C62: 加拿大温哥华1仓 | E62: 退件订单 | F62: 21 | G62: CAD | H62: 156.89 | J62: 0 | L62: 156.89
C63: 加拿大温哥华1仓 | E63: 仓租 | F63: - | G63: CAD | H63: 2143.98 | J63: 0 | L63: 2143.98
C66: 温馨提示：
C67: 1、根据税务机关发布的有关政策，要求付款主体、开票主体和签约主体为同一个法律主体，请贵司按合同签约主体对应的账单币种进行支付；
C68: 2、计算公式：期初结余=上期期末结余；本期充值=本期充值金额+申请调账调入-申请调账调出；本期赔偿=本期产生的赔偿金额；本期调退=本期产生的调退金额；本期消费=本期产生的计费订单-本期取消的计费订单；
C69: 3、当【期初结余】为负数时，则为上期期末欠费结转本期期初；当【本期充值】为负数时，则为本期发生退款或余额调整；当【本期消费】为负数时，则为本期消费有发生调退；当【期末结余】为负数时，则为本期应付金额；
C70: 4、代收代付税费是我司为您提供服务过程中产生需缴纳的税费，由于代缴的税款不属于我司提供的国际货代服务，开具包含代缴税金的发票与实际经营业务不相符，因此系统开票时将剔除税费金额，即可开票金额=账单金额-含代收代付税费。若您与我司签约主体为国内主体，根据法律要求会涉及税费。如下为税费费用项：代收VAT押金，关税，申报值5%关税，申报值20%关税，申报值25%关税，申报值30%关税，DUTIES TAXES PAID，IMPORT EXPORT DUTIES，仓储关税，预收关税，进口关税，预收关税KG费，预收关税操作费，退预收关税，税费，预收税金，关税CFIA，关税OGD，海关关税，VAT税，IMPORT EXPORT TAXES，出口退税，单独退税自VAT，非出口退税，代收VAT税，Customs Duty，消费税，地方消费税，增值税，申报值110%关税，代扣代缴增值税等，将不予开票。
C71: 5、请贵司收到账单后在合同约定的“核对期”内进行核对反馈，若对此账单有异议，请联系我司客服或销售人员反馈；若在“核对期”内未有任何反馈，则视为认可此账单，请在结算日前安排支付，逾期未支付系统会自动锁定账户，影响您的货物正常中转。

Sheet 充值退款
A1: 类型 | B1: 入账方式 | C1: 币种 | D1: 金额 | E1: 发生时间 | F1: 交易单据号 | G1: 业务单号 | H1: SKU | I1: SKU数量 | J1: 备注 | K1: SKU英文 | L1: SKU中文 | M1: 客户单号
A2: 充值 | B2: 赔偿 | C2: EUR | D2: 87.33 | E2: 46128.393 | F2: REPA:FB420260407004794:-1 | G2: OC9472702511300291 | J2: 业务单号：OC9472702511300291，尾程问题-轨迹无更新 | M2: 165112024892878992
A3: 充值 | B3: 赔偿 | C3: GBP | D3: 34.99 | E3: 46115.697 | F3: REPA:FB420260402003294:-1 | G3: AJIGBLONA2604020000927 | H3: VSF-AWD4X2-UK | I3: 1 | J3: 业务单号：AJIGBLONA2604020000927，库内问题-遗失 | K3: VIVOSUN AeroWave D4, 4” Grow Tent Clip Fan with Detachable Hook
A4: 充值 | B4: 赔偿 | C4: USD | D4: 9.99 | E4: 46114.575 | F4: REPA:FB420260331000590:-1 | G4: OC9472702602130043 | H4: CFPB-4 | I4: 1 | J4: 业务单号：OC9472702602130043，尾程问题-未上网 | K4: 4 Inch Prefilter for 4" Carbon Filter, Black | L4: 截断款黑色滤芯棉4寸 | M4: 103668522868932608
A5: 充值 | B5: 赔偿 | C5: USD | D5: 13.99 | E5: 46115.696 | F5: REPA:FB420260319011994:-1 | G5: AJIUSNJCB2603190000124 | H5: DWC-0001 | I5: 1 | J5: 业务单号：AJIUSNJCB2603190000124，库内问题-遗失 | K5: DWC Hydroponics Grow System (1 Bucket + Top Drip Kit)
A6: 充值 | B6: 赔偿 | C6: USD | D6: 31.98 | E6: 46115.697 | F6: REPA:FB420260402009389:-1 | G6: AJIUSNJCB2604020000085 | H6: VC-0003 | I6: 2 | J6: 业务单号：AJIUSNJCB2604020000085，库内问题-遗失 | K6: 2Pcs 8" Grow Tent Vent Covers | L6: 8-Inch防尘罩 两个装
A7: 充值 | B7: 赔偿 | C7: USD | D7: 15.99 | E7: 46115.697 | F7: REPA:FB420260402009390:-1 | G7: AJIUSNJCB2604020000086 | H7: VC-0003 | I7: 1 | J7: 业务单号：AJIUSNJCB2604020000086，库内问题-遗失 | K7: 2Pcs 8" Grow Tent Vent Covers | L7: 8-Inch防尘罩 两个装
A8: 充值 | B8: 赔偿 | C8: USD | D8: 39.99 | E8: 46128.395 | F8: REPA:FB420260414003451:-1 | G8: OC9472702603110367 | J8: 业务单号：OC9472702603110367，尾程问题-破损 | M8: 167509242370690461
A9: 充值 | B9: 赔偿 | C9: USD | D9: 17.99 | E9: 46128.397 | F9: REPA:FB420260410000006:-1 | G9: AJIGBLONA2604100000411 | H9: 306109-48C-UK | I9: 1 | J9: 业务单号：AJIGBLONA2604100000411，库内问题-遗失 | K9: VIVOSUN Dryer Vent Hose, 4 inch Aluminum Foil Ducting
A10: 退款 | B10: 赔偿撤销 | C10: USD | D10: -65.99 | E10: 46131.743 | F10: REPA:FB420251010011956:-1 | G10: PAYCN2510100080 | J10: 货已找回并盘盈，需撤销整单货值赔偿 AJIUSNJCB2603240000051
A11: 充值 | B11: 线上 | C11: USD | D11: 175893.45 | E11: 46132.462 | F11: 10010126042065972559
A12: 充值 | B12: 赔偿 | C12: USD | D12: 100 | E12: 46134.493 | F12: REPA:FB420260420004723:-1 | G12: OC9472702603260229 | H12: VSAW200-E42A-UK | I12: 1 | J12: 业务单号：OC9472702603260229，尾程问题-未上网 | K12: AeroLight Wing 200W + E42A | M12: 167855671212031246
A13: 充值 | B13: 赔偿 | C13: USD | D13: 10.99 | E13: 46136.473 | F13: REPA:FB420260420004990:-1 | G13: AJIGBLONA2604200000067 | H13: VC-0002-UK | I13: 1 | J13: 业务单号：AJIGBLONA2604200000067，库内问题-遗失 | K13: 6-Inch防尘罩 两个装 | L13: 6-Inch防尘罩 两个装
A14: 充值 | B14: 赔偿 | C14: USD | D14: 19.99 | E14: 46138.68 | F14: REPA:FB420260422002611:-1 | G14: AJIDEFRAB2604220000014 | H14: VS-TLGG-XL | I14: 1 | J14: 业务单号：AJIDEFRAB2604220000014，库内问题-遗失 | K14: Vivosun Tshirt 2025 Size XL | L14: VS LGGT恤 欧版 XL码
A15: 充值 | B15: 赔偿 | C15: USD | D15: 39.98 | E15: 46138.68 | F15: REPA:FB420260422002621:-1 | G15: AJIDEFRAB2604220000013 | H15: VS-TLGG-XL | I15: 2 | J15: 业务单号：AJIDEFRAB2604220000013，库内问题-遗失 | K15: Vivosun Tshirt 2025 Size XL | L15: VS LGGT恤 欧版 XL码
A16: 充值 | B16: 赔偿 | C16: USD | D16: 100 | E16: 46141.725 | F16: REPA:FB420260427011373:-1 | G16: OC9472702512100008 | H16: VSAW200-E42A-UK | I16: 1 | J16: 业务单号：OC9472702512100008，尾程问题-未上网 | K16: AeroLight Wing 200W + E42A | M16: 165399001454647445
A17: 充值 | B17: 赔偿 | C17: USD | D17: 15.99 | E17: 46141.725 | F17: REPA:FB420260427011383:-1 | G17: OC9472702511160209 | H17: GH-E25-EU | I17: 1 | J17: 业务单号：OC9472702511160209，尾程问题-未上网 | K17: E25控制器-单品包装 | L17: E25控制器-单品包装 | M17: 164834625302991365

Sheet 入库订单
A1: 业务单号 | B1: 客户单号 | C1: 服务类别 | D1: 服务产品 | E1: 下单子账号 | F1: 计费时间 | G1: 计费重 | H1: 实重 | I1: SKU | J1: SKU数量 | K1: 费用类型 | L1: 费用名称 | M1: 币种 | N1: 计费金额 | O1: 优惠金额 | P1: 应收金额 | Q1: 含代收代付税费 | R1: 可开票金额 | S1: 计费单位 | T1: 计费数量 | U1: 计费地点 | V1: 计算公式 | W1: 数字公式 | X1: 报价单编号 | Y1: 优惠券信息 | Z1: 服务商单号 | AA1: 目的地国家 | AB1: 起运地邮编 | AC1: 目的地邮编 | AD1: 起运分区 | AE1: 目的分区 | AF1: 分区名称 | AG1: 有红冲单 | AH1: 划拨单号 | AI1: 是否跨月重计 | AJ1: 备注 | AK1: SKU英文 | AL1: SKU中文 | AM1: 关联入库单号
A2: IC947270260117132 | B2: SW202601150004DE | C2: FB4 | D2: 入库操作费-DE | E2: 947270 | F2: 2026-03-31 17:38:38 | G2: 0 | H2: 10762.26 | I2: VSF-AWA6G2X2-EU | J2: 240 | K2: 入库操作费 | L2: 海外仓查验费 | M2: EUR | N2: 2.75 | O2: 0 | P2: 2.75 | Q2: 0 | R2: 2.75 | U2: 德国法兰克福2仓 | X2: 入库操作费-F230DE-250327（公布价）-3 | AA2: DE | AB2: 65462C | AC2: 65462C | AD2: PZ_国际 | AE2: DEFRAB德国法兰克福2仓 | AK2: 2-Pack AeroWave A6 Gen2 Grow Tent Clip Fan | AL2: 入门款AC电机夹扇A6 Gen2 欧版 两只装
A3: IC947270260117132 | B3: SW202601150004DE | C3: FB4 | D3: 入库操作费-DE | E3: 947270 | F3: 2026-03-31 17:38:38 | G3: 0 | H3: 10762.26 | K3: 入库操作费 | L3: 入库卸货费 | M3: EUR | N3: 348.6 | O3: 0 | P3: 348.6 | Q3: 0 | R3: 348.6 | S3: mums.measurement_info.code.CBM | T3: 67.03768 | U3: 德国法兰克福2仓 | X3: 入库操作费-F230DE-250327（公布价）-3 | AA3: DE | AB3: 65462C | AC3: 65462C | AD3: PZ_国际 | AE3: DEFRAB德国法兰克福2仓
A4: IC947270260117132 | B4: SW202601150004DE | C4: FB4 | D4: 入库操作费-DE | E4: 947270 | F4: 2026-03-31 17:38:38 | G4: 0 | H4: 10762.26 | I4: VSE-ALC08-EU | J4: 180 | K4: 入库操作费 | L4: 入库操作费 | M4: EUR | N4: 432 | O4: 0 | P4: 370.8 | Q4: 0 | R4: 370.8 | S4: 个 | T4: 25.778 | U4: 德国法兰克福2仓 | X4: 入库操作费-F230DE-250327（公布价）-3 | AA4: DE | AB4: 65462C | AC4: 65462C | AD4: PZ_国际 | AE4: DEFRAB德国法兰克福2仓 | AK4: AeroLush Air Conditioner - 8000 BTU - European Standard | AL4: AeroLush 空调_8000BTU_欧规
A5: IC947270260117132 | B5: SW202601150004DE | C5: FB4 | D5: 入库操作费-DE | E5: 947270 | F5: 2026-03-31 17:38:38 | G5: 0 | H5: 10762.26 | I5: VSE-ASH05-EU | J5: 240 | K5: 入库操作费 | L5: 入库操作费 | M5: EUR | N5: 72 | O5: 0 | P5: 62.4 | Q5: 0 | R5: 62.4 | S5: 个 | T5: 1.954 | U5: 德国法兰克福2仓 | X5: 入库操作费-F230DE-250327（公布价）-3 | AA5: DE | AB5: 65462C | AC5: 65462C | AD5: PZ_国际 | AE5: DEFRAB德国法兰克福2仓 | AK5: AeroStream Humidificateur pour plantes 5 l | AL5: AeroStream 5L智能Wi-Fi加湿器（SGS，单核雾化片）-欧版
A6: IC947270260117132 | B6: SW202601150004DE | C6: FB4 | D6: 入库操作费-DE | E6: 947270 | F6: 2026-03-31 17:38:38 | G6: 0 | H6: 10762.26 | I6: VSE-ADD12-EU | J6: 240 | K6: 入库操作费 | L6: 入库操作费 | M6: EUR | N6: 348 | O6: 0 | P6: 300 | Q6: 0 | R6: 300 | S6: 个 | T6: 12.5 | U6: 德国法兰克福2仓 | X6: 入库操作费-F230DE-250327（公布价）-3 | AA6: DE | AB6: 65462C | AC6: 65462C | AD6: PZ_国际 | AE6: DEFRAB德国法兰克福2仓 | AK6: Desumidificador AeroDrain D12 | AL6: AeroDrain WiFi除湿机_12L_欧版
A7: IC947270260117132 | B7: SW202601150004DE | C7: FB4 | D7: 入库操作费-DE | E7: 947270 | F7: 2026-03-31 17:38:38 | G7: 0 | H7: 10762.26 | I7: VG-Y18B-EU | J7: 50 | K7: 入库操作费 | L7: 入库操作费 | M7: EUR | N7: 120 | O7: 0 | P7: 103 | Q7: 0 | R7: 103 | S7: 个 | T7: 23.55 | U7: 德国法兰克福2仓 | X7: 入库操作费-F230DE-250327（公布价）-3 | AA7: DE | AB7: 65462C | AC7: 65462C | AD7: PZ_国际 | AE7: DEFRAB德国法兰克福2仓 | AK7: 欧版 VGrow 智能种植箱 | AL7: 欧版 VGrow 智能种植箱
A8: IC947270260117132 | B8: SW202601150004DE | C8: FB4 | D8: 入库操作费-DE | E8: 947270 | F8: 2026-03-31 17:38:38 | G8: 0 | H8: 10762.26 | I8: 306146-0412-EU | J8: 300 | K8: 入库操作费 | L8: 入库操作费 | M8: EUR | N8: 90 | O8: 0 | P8: 78 | Q8: 0 | R8: 78 | S8: 个 | T8: 2.826 | U8: 德国法兰克福2仓 | X8: 入库操作费-F230DE-250327（公布价）-3 | AA8: DE | AB8: 65462C | AC8: 65462C | AD8: PZ_国际 | AE8: DEFRAB德国法兰克福2仓 | AK8: VIVOSUN钢印滤芯 黑色4" | AL8: VIVOSUN钢印滤芯 黑色4"
A9: IC947270260117132 | B9: SW202601150004DE | C9: FB4 | D9: 入库操作费-DE | E9: 947270 | F9: 2026-03-31 17:38:38 | G9: 0 | H9: 10762.26 | I9: VSF-AWA6G2X2-EU | J9: 240 | K9: 入库操作费 | L9: 入库操作费 | M9: EUR | N9: 72 | O9: 0 | P9: 62.4 | Q9: 0 | R9: 62.4 | S9: 个 | T9: 2.838 | U9: 德国法兰克福2仓 | X9: 入库操作费-F230DE-250327（公布价）-3 | AA9: DE | AB9: 65462C | AC9: 65462C | AD9: PZ_国际 | AE9: DEFRAB德国法兰克福2仓 | AK9: 2-Pack AeroWave A6 Gen2 Grow Tent Clip Fan | AL9: 入门款AC电机夹扇A6 Gen2 欧版 两只装
A10: IC947270260117143 | B10: SW202601150003DE | C10: FB4 | D10: 入库操作费-DE | E10: 947270 | F10: 2026-03-31 15:23:58 | G10: 0 | H10: 9259.808 | I10: VSF-AWA6G2-EU | J10: 240 | K10: 入库操作费 | L10: 海外仓查验费 | M10: EUR | N10: 2.75 | O10: 0 | P10: 2.75 | Q10: 0 | R10: 2.75 | U10: 德国法兰克福2仓 | X10: 入库操作费-F230DE-250327（公布价）-3 | AA10: DE | AB10: 65462C | AC10: 65462C | AD10: PZ_国际 | AE10: DEFRAB德国法兰克福2仓 | AK10: Aerowave A6 Gen2 Grow Tent Clip Fan | AL10: 入门款AC电机夹扇A6 Gen2 欧版
A11: IC947270260117143 | B11: SW202601150003DE | C11: FB4 | D11: 入库操作费-DE | E11: 947270 | F11: 2026-03-31 15:23:58 | G11: 0 | H11: 9259.808 | K11: 入库操作费 | L11: 入库卸货费 | M11: EUR | N11: 317.89 | O11: 0 | P11: 317.89 | Q11: 0 | R11: 317.89 | S11: mums.measurement_info.code.CBM | T11: 61.13187 | U11: 德国法兰克福2仓 | X11: 入库操作费-F230DE-250327（公布价）-3 | AA11: DE | AB11: 65462C | AC11: 65462C | AD11: PZ_国际 | AE11: DEFRAB德国法兰克福2仓
A12: IC947270260117143 | B12: SW202601150003DE | C12: FB4 | D12: 入库操作费-DE | E12: 947270 | F12: 2026-03-31 15:23:58 | G12: 0 | H12: 9259.808 | I12: VSL-LRUC100-EU | J12: 96 | K12: 入库操作费 | L12: 入库操作费 | M12: EUR | N12: 28.8 | O12: 0 | P12: 24.96 | Q12: 0 | R12: 24.96 | S12: 个 | T12: 2.9 | U12: 德国法兰克福2仓 | X12: 入库操作费-F230DE-250327（公布价）-3 | AA12: DE | AB12: 65462C | AC12: 65462C | AD12: PZ_国际 | AE12: DEFRAB德国法兰克福2仓 | AK12: Supplemental light LumaRay-under canopy 100W-EU | AL12: Supplemental light LumaRay-under canopy 100W-EU
A13: IC947270260117143 | B13: SW202601150003DE | C13: FB4 | D13: 入库操作费-DE | E13: 947270 | F13: 2026-03-31 15:23:58 | G13: 0 | H13: 9259.808 | I13: VG-Y18B-EU | J13: 25 | K13: 入库操作费 | L13: 入库操作费 | M13: EUR | N13: 60 | O13: 0 | P13: 51.5 | Q13: 0 | R13: 51.5 | S13: 个 | T13: 23.55 | U13: 德国法兰克福2仓 | X13: 入库操作费-F230DE-250327（公布价）-3 | AA13: DE | AB13: 65462C | AC13: 65462C | AD13: PZ_国际 | AE13: DEFRAB德国法兰克福2仓 | AK13: 欧版 VGrow 智能种植箱 | AL13: 欧版 VGrow 智能种植箱
A14: IC947270260117143 | B14: SW202601150003DE | C14: FB4 | D14: 入库操作费-DE | E14: 947270 | F14: 2026-03-31 15:23:58 | G14: 0 | H14: 9259.808 | I14: VSVC-AZT6E42AP-EU | J14: 25 | K14: 入库操作费 | L14: 入库操作费 | M14: EUR | N14: 23.5 | O14: 0 | P14: 20.25 | Q14: 0 | R14: 20.25 | S14: 个 | T14: 10 | U14: 德国法兰克福2仓 | X14: 入库操作费-F230DE-250327（公布价）-3 | AA14: DE | AB14: 65462C | AC14: 65462C | AD14: PZ_国际 | AE14: DEFRAB德国法兰克福2仓 | AK14: Smart Air Filtration Kit Pro 6″ | AL14: AeroZesh T6 金属底座风机 6寸 + GrowHub E42A+控制器+黑色滤芯6寸+黑色风管6寸8ft 欧版
A15: IC947270260117143 | B15: SW202601150003DE | C15: FB4 | D15: 入库操作费-DE | E15: 947270 | F15: 2026-03-31 15:23:58 | G15: 0 | H15: 9259.808 | I15: VSF-AWD4X2-EU | J15: 432 | K15: 入库操作费 | L15: 入库操作费 | M15: EUR | N15: 116.64 | O15: 0 | P15: 99.36 | Q15: 0 | R15: 99.36 | S15: 个 | T15: 0.61 | U15: 德国法兰克福2仓 | X15: 入库操作费-F230DE-250327（公布价）-3 | AA15: DE | AB15: 65462C | AC15: 65462C | AD15: PZ_国际 | AE15: DEFRAB德国法兰克福2仓 | AK15: AeroWave D4, 4” Grow Tent Clip Fan with Detachable Hook
A16: IC947270260117143 | B16: SW202601150003DE | C16: FB4 | D16: 入库操作费-DE | E16: 947270 | F16: 2026-03-31 15:23:58 | G16: 0 | H16: 9259.808 | I16: VSE-ATW70-EU | J16: 72 | K16: 入库操作费 | L16: 入库操作费 | M16: EUR | N16: 34.56 | O16: 0 | P16: 29.52 | Q16: 0 | R16: 29.52 | S16: 个 | T16: 3.216 | U16: 德国法兰克福2仓 | X16: 入库操作费-F230DE-250327（公布价）-3 | AA16: DE | AB16: 65462C | AC16: 65462C | AD16: PZ_国际 | AE16: DEFRAB德国法兰克福2仓 | AK16: AeroFlux Heater 70w | AL16: AeroFlux Heater 70w
A17: IC947270260117143 | B17: SW202601150003DE | C17: FB4 | D17: 入库操作费-DE | E17: 947270 | F17: 2026-03-31 15:23:58 | G17: 0 | H17: 9259.808 | I17: VSF-AWA6G2-EU | J17: 240 | K17: 入库操作费 | L17: 入库操作费 | M17: EUR | N17: 72 | O17: 0 | P17: 62.4 | Q17: 0 | R17: 62.4 | S17: 个 | T17: 1.468 | U17: 德国法兰克福2仓 | X17: 入库操作费-F230DE-250327（公布价）-3 | AA17: DE | AB17: 65462C | AC17: 65462C | AD17: PZ_国际 | AE17: DEFRAB德国法兰克福2仓 | AK17: Aerowave A6 Gen2 Grow Tent Clip Fan | AL17: 入门款AC电机夹扇A6 Gen2 欧版
A18: IC947270260117143 | B18: SW202601150003DE | C18: FB4 | D18: 入库操作费-DE | E18: 947270 | F18: 2026-03-31 15:23:58 | G18: 0 | H18: 9259.808 | I18: VSVC-AZG4E42AP-EU | J18: 36 | K18: 入库操作费 | L18: 入库操作费 | M18: EUR | N18: 33.84 | O18: 0 | P18: 29.16 | Q18: 0 | R18: 29.16 | S18: 个 | T18: 7 | U18: 德国法兰克福2仓 | X18: 入库操作费-F230DE-250327（公布价）-3 | AA18: DE | AB18: 65462C | AC18: 65462C | AD18: PZ_国际 | AE18: DEFRAB德国法兰克福2仓 | AK18: Smart Air Filtration PRO G4 Kit 4" | AL18: AeroZesh G4 金属底座风机 4寸 + GrowHub E42A+控制器+黑色滤芯4寸+黑色风管4寸8ft 欧版
A19: IC947270260117143 | B19: SW202601150003DE | C19: FB4 | D19: 入库操作费-DE | E19: 947270 | F19: 2026-03-31 15:23:58 | G19: 0 | H19: 9259.808 | I19: VSF-AWE6-G2-EU | J19: 336 | K19: 入库操作费 | L19: 入库操作费 | M19: EUR | N19: 100.8 | O19: 0 | P19: 87.36 | Q19: 0 | R19: 87.36 | S19: 个 | T19: 1.1 | U19: 德国法兰克福2仓 | X19: 入库操作费-F230DE-250327（公布价）-3 | AA19: DE | AB19: 65462C | AC19: 65462C | AD19: PZ_国际 | AE19: DEFRAB德国法兰克福2仓 | AK19: AeroWave E6 Grow Tent Fan 6”
A20: IC947270260117143 | B20: SW202601150003DE | C20: FB4 | D20: 入库操作费-DE | E20: 947270 | F20: 2026-03-31 15:23:58 | G20: 0 | H20: 9259.808 | I20: 304113-52-EU | J20: 32 | K20: 入库操作费 | L20: 入库操作费 | M20: EUR | N20: 46.4 | O20: 0 | P20: 40 | Q20: 0 | R20: 40 | S20: 个 | T20: 11.821 | U20: 德国法兰克福2仓 | X20: 入库操作费-F230DE-250327（公布价）-3 | AA20: DE | AB20: 65462C | AC20: 65462C | AD20: PZ_国际 | AE20: DEFRAB德国法兰克福2仓 | AK20: 52帐篷-60"x32"x80"/150*80*200cm 16mm管径 | AL20: 52帐篷-60"x32"x80"/150*80*200cm 16mm管径
A21: IC947270260117143 | B21: SW202601150003DE | C21: FB4 | D21: 入库操作费-DE | E21: 947270 | F21: 2026-03-31 15:23:58 | G21: 0 | H21: 9259.808 | I21: E331903J-EU | J21: 36 | K21: 入库操作费 | L21: 入库操作费 | M21: EUR | N21: 33.84 | O21: 0 | P21: 29.16 | Q21: 0 | R21: 29.16 | S21: 个 | T21: 6.262 | U21: 德国法兰克福2仓 | X21: 入库操作费-F230DE-250327（公布价）-3 | AA21: DE | AB21: 65462C | AC21: 65462C | AD21: PZ_国际 | AE21: DEFRAB德国法兰克福2仓 | AK21: E331903J || New lawn mower 16" (with orange flower trimmer) | AL21: E331903J||新款 割草机16"（带橘色花枝剪）
A22: IC947270260117143 | B22: SW202601150003DE | C22: FB4 | D22: 入库操作费-DE | E22: 947270 | F22: 2026-03-31 15:23:58 | G22: 0 | H22: 9259.808 | I22: VSK-GIYS336-EU | J22: 20 | K22: 入库操作费 | L22: 入库操作费 | M22: EUR | N22: 48 | O22: 0 | P22: 41.2 | Q22: 0 | R22: 41.2 | S22: 个 | T22: 23 | U22: 德国法兰克福2仓 | X22: 入库操作费-F230DE-250327（公布价）-3 | AA22: DE | AB22: 65462C | AC22: 65462C | AD22: PZ_国际 | AE22: DEFRAB德国法兰克福2仓 | AK22: Smart Grow Tent Kit GIY-SE-33 3x3, 3-Plant Complete System | AL22: GIY SGS智能标准款帐篷套装S336欧版
A23: IC947270260117143 | B23: SW202601150003DE | C23: FB4 | D23: 入库操作费-DE | E23: 947270 | F23: 2026-03-31 15:23:58 | G23: 0 | H23: 9259.808 | I23: VSE-ASH05-EU | J23: 120 | K23: 入库操作费 | L23: 入库操作费 | M23: EUR | N23: 36 | O23: 0 | P23: 31.2 | Q23: 0 | R23: 31.2 | S23: 个 | T23: 1.954 | U23: 德国法兰克福2仓 | X23: 入库操作费-F230DE-250327（公布价）-3 | AA23: DE | AB23: 65462C | AC23: 65462C | AD23: PZ_国际 | AE23: DEFRAB德国法兰克福2仓 | AK23: AeroStream Humidificateur pour plantes 5 l | AL23: AeroStream 5L智能Wi-Fi加湿器（SGS，单核雾化片）-欧版
A24: IC947270260117143 | B24: SW202601150003DE | C24: FB4 | D24: 入库操作费-DE | E24: 947270 | F24: 2026-03-31 15:23:58 | G24: 0 | H24: 9259.808 | I24: VSE-ASH09-EU | J24: 168 | K24: 入库操作费 | L24: 入库操作费 | M24: EUR | N24: 80.64 | O24: 0 | P24: 68.88 | Q24: 0 | R24: 68.88 | S24: 个 | T24: 3.346 | U24: 德国法兰克福2仓 | X24: 入库操作费-F230DE-250327（公布价）-3 | AA24: DE | AB24: 65462C | AC24: 65462C | AD24: PZ_国际 | AE24: DEFRAB德国法兰克福2仓 | AK24: AeroStream - Humidificador para plantas (9 L) | AL24: AeroStream 9L智能Wi-Fi加湿器（SGS，单核雾化片）-欧版
A25: IC947270260117143 | B25: SW202601150003DE | C25: FB4 | D25: 入库操作费-DE | E25: 947270 | F25: 2026-03-31 15:23:58 | G25: 0 | H25: 9259.808 | I25: VSI-FFSW6-4-EU | J25: 120 | K25: 入库操作费 | L25: 入库操作费 | M25: EUR | N25: 57.6 | O25: 0 | P25: 49.2 | Q25: 0 | R25: 49.2 | S25: 个 | T25: 4.72 | U25: 德国法兰克福2仓 | X25: 入库操作费-F230DE-250327（公布价）-3 | AA25: DE | AB25: 65462C | AC25: 65462C | AD25: PZ_国际 | AE25: DEFRAB德国法兰克福2仓 | AK25: 4-Pack FlexFeed Self-Watering Irrigation Pot
A26: IC947270260117143 | B26: SW202601150003DE | C26: FB4 | D26: 入库操作费-DE | E26: 947270 | F26: 2026-03-31 15:23:58 | G26: 0 | H26: 9259.808 | I26: VST-SP2-GL-EU | J26: 200 | K26: 入库操作费 | L26: 入库操作费 | M26: EUR | N26: 60 | O26: 0 | P26: 52 | Q26: 0 | R26: 52 | S26: 个 | T26: 2.014 | U26: 德国法兰克福2仓 | X26: 入库操作费-F230DE-250327（公布价）-3 | AA26: DE | AB26: 65462C | AC26: 65462C | AD26: PZ_国际 | AE26: DEFRAB德国法兰克福2仓 | AK26: Grow Tent High CFM Kit 100-150cm | AL26: 帐篷伸缩支撑杆100-150cm
A27: IC947270260117143 | B27: SW202601150003DE | C27: FB4 | D27: 入库操作费-DE | E27: 947270 | F27: 2026-03-31 15:23:58 | G27: 0 | H27: 9259.808 | I27: VSFL6450-EU | J27: 15 | K27: 入库操作费 | L27: 入库操作费 | M27: EUR | N27: 14.1 | O27: 0 | P27: 12.15 | Q27: 0 | R27: 12.15 | S27: 个 | T27: 10 | U27: 德国法兰克福2仓 | X27: 入库操作费-F230DE-250327（公布价）-3 | AA27: DE | AB27: 65462C | AC27: 65462C | AD27: PZ_国际 | AE27: DEFRAB德国法兰克福2仓 | AK27: LED Grow Light
A28: IC947270260117143 | B28: SW202601150003DE | C28: FB4 | D28: 入库操作费-DE | E28: 947270 | F28: 2026-03-31 15:23:58 | G28: 0 | H28: 9259.808 | I28: VSEX-HID1-ST-EU | J28: 88 | K28: 入库操作费 | L28: 入库操作费 | M28: EUR | N28: 42.24 | O28: 0 | P28: 36.08 | Q28: 0 | R28: 36.08 | S28: 个 | T28: 3.812 | U28: 德国法兰克福2仓 | X28: 入库操作费-F230DE-250327（公布价）-3 | AA28: DE | AB28: 65462C | AC28: 65462C | AD28: PZ_国际 | AE28: DEFRAB德国法兰克福2仓 | AK28: Herbal Decarboxylation and Infusion Machine | AL28: S4508B 黄油机套装-欧版
A29: IC947270260117143 | B29: SW202601150003DE | C29: FB4 | D29: 入库操作费-DE | E29: 947270 | F29: 2026-03-31 15:23:58 | G29: 0 | H29: 9259.808 | I29: VSE-ADD12-EU | J29: 50 | K29: 入库操作费 | L29: 入库操作费 | M29: EUR | N29: 72.5 | O29: 0 | P29: 62.5 | Q29: 0 | R29: 62.5 | S29: 个 | T29: 12.5 | U29: 德国法兰克福2仓 | X29: 入库操作费-F230DE-250327（公布价）-3 | AA29: DE | AB29: 65462C | AC29: 65462C | AD29: PZ_国际 | AE29: DEFRAB德国法兰克福2仓 | AK29: Desumidificador AeroDrain D12 | AL29: AeroDrain WiFi除湿机_12L_欧版
A30: IC947270260117143 | B30: SW202601150003DE | C30: FB4 | D30: 入库操作费-DE | E30: 947270 | F30: 2026-03-31 15:23:58 | G30: 0 | H30: 9259.808 | I30: VSK-GIYS448-EU | J30: 18 | K30: 入库操作费 | L30: 入库操作费 | M30: EUR | N30: 55.08 | O30: 0 | P30: 47.34 | Q30: 0 | R30: 47.34 | S30: 个 | T30: 33 | U30: 德国法兰克福2仓 | X30: 入库操作费-F230DE-250327（公布价）-3 | AA30: DE | AB30: 65462C | AC30: 65462C | AD30: PZ_国际 | AE30: DEFRAB德国法兰克福2仓 | AK30: Smart Grow Tent Kit GIY-SE-44 4x4, 4-Plant Complete System | AL30: GIY SGS智能标准款帐篷套装S448欧版
A31: IC947270260117143 | B31: SW202601150003DE | C31: FB4 | D31: 入库操作费-DE | E31: 947270 | F31: 2026-03-31 15:23:58 | G31: 0 | H31: 9259.808 | I31: VSI-VGDWC15-EU | J31: 60 | K31: 入库操作费 | L31: 入库操作费 | M31: EUR | N31: 28.8 | O31: 0 | P31: 24.6 | Q31: 0 | R31: 24.6 | S31: 个 | T31: 5 | U31: 德国法兰克福2仓 | X31: 入库操作费-F230DE-250327（公布价）-3 | AA31: DE | AB31: 65462C | AC31: 65462C | AD31: PZ_国际 | AE31: DEFRAB德国法兰克福2仓 | AK31: VGrow DWC Hydroponics Growing System Kit for VGrow Smart Grow Box | AL31: VGrow DWC水培套装 4加仑
A32: IC947270260117143 | B32: SW202601150003DE | C32: FB4 | D32: 入库操作费-DE | E32: 947270 | F32: 2026-03-31 15:23:58 | G32: 0 | H32: 9259.808 | I32: SST-1-0001-EU | J32: 120 | K32: 入库操作费 | L32: 入库操作费 | M32: EUR | N32: 36 | O32: 0 | P32: 31.2 | Q32: 0 | R32: 31.2 | S32: 个 | T32: 1.13 | U32: 德国法兰克福2仓 | X32: 入库操作费-F230DE-250327（公布价）-3 | AA32: DE | AB32: 65462C | AC32: 65462C | AD32: PZ_国际 | AE32: DEFRAB德国法兰克福2仓 | AK32: 1-Pack 40-Cell Seed Starter Trays with 1 Set of LED Lights and 10"x20.75" Seedling Heat Mat | AL32: 欧规 40孔育苗盘1套装+LED灯条1套+加热垫1套
A33: IC947270260117143 | B33: SW202601150003DE | C33: FB4 | D33: 入库操作费-DE | E33: 947270 | F33: 2026-03-31 15:23:58 | G33: 0 | H33: 9259.808 | I33: E331904J-EU | J33: 30 | K33: 入库操作费 | L33: 入库操作费 | M33: EUR | N33: 28.2 | O33: 0 | P33: 24.3 | Q33: 0 | R33: 24.3 | S33: 个 | T33: 7.25 | U33: 德国法兰克福2仓 | X33: 入库操作费-F230DE-250327（公布价）-3 | AA33: DE | AB33: 65462C | AC33: 65462C | AD33: PZ_国际 | AE33: DEFRAB德国法兰克福2仓 | AK33: E331904J || New lawn mower 19" (with orange flower trimmer) | AL33: E331904J||新款 割草机19"（带橘色花枝剪）
A34: IC947270260117143 | B34: SW202601150003DE | C34: FB4 | D34: 入库操作费-DE | E34: 947270 | F34: 2026-03-31 15:23:58 | G34: 0 | H34: 9259.808 | I34: 304113-P426-EU | J34: 40 | K34: 入库操作费 | L34: 入库操作费 | M34: EUR | N34: 58 | O34: 0 | P34: 50 | Q34: 0 | R34: 50 | S34: 个 | T34: 15 | U34: 德国法兰克福2仓 | X34: 入库操作费-F230DE-250327（公布价）-3 | AA34: DE | AB34: 65462C | AC34: 65462C | AD34: PZ_国际 | AE34: DEFRAB德国法兰克福2仓 | AK34: P426 48"×24"×72" PRO Grow Tent | AL34: P426 Pro款42帐篷-48"x24"x72"/120*60*180cm 22mm管径
A35: IC947270260117143 | B35: SW202601150003DE | C35: FB4 | D35: 入库操作费-DE | E35: 947270 | F35: 2026-03-31 15:23:58 | G35: 0 | H35: 9259.808 | I35: 304113-P448-EU | J35: 20 | K35: 入库操作费 | L35: 入库操作费 | M35: EUR | N35: 38.6 | O35: 0 | P35: 33.2 | Q35: 0 | R35: 33.2 | S35: 个 | T35: 20 | U35: 德国法兰克福2仓 | X35: 入库操作费-F230DE-250327（公布价）-3 | AA35: DE | AB35: 65462C | AC35: 65462C | AD35: PZ_国际 | AE35: DEFRAB德国法兰克福2仓 | AK35: P448 48"×48"×80" PRO Grow Tent | AL35: P448 Pro款44帐篷-48"x48"x80"/120*120*200cm 22mm管径
A36: IC947270260117143 | B36: SW202601150003DE | C36: FB4 | D36: 入库操作费-DE | E36: 947270 | F36: 2026-03-31 15:23:58 | G36: 0 | H36: 9259.808 | I36: VSVC-AZT4E42AP-EU | J36: 45 | K36: 入库操作费 | L36: 入库操作费 | M36: EUR | N36: 42.3 | O36: 0 | P36: 36.45 | Q36: 0 | R36: 36.45 | S36: 个 | T36: 6.5 | U36: 德国法兰克福2仓 | X36: 入库操作费-F230DE-250327（公布价）-3 | AA36: DE | AB36: 65462C | AC36: 65462C | AD36: PZ_国际 | AE36: DEFRAB德国法兰克福2仓 | AK36: Smart Air Filtration PRO T4 Kit 4" | AL36: AeroZesh T4 金属底座风机 4寸 + GrowHub E42A+控制器+黑色滤芯4寸+黑色风管4寸8ft 欧版
A37: IC947270260117143 | B37: SW202601150003DE | C37: FB4 | D37: 入库操作费-DE | E37: 947270 | F37: 2026-03-31 15:23:58 | G37: 0 | H37: 9259.808 | I37: 304113-P558-EU | J37: 12 | K37: 入库操作费 | L37: 入库操作费 | M37: EUR | N37: 28.8 | O37: 0 | P37: 24.72 | Q37: 0 | R37: 24.72 | S37: 个 | T37: 24 | U37: 德国法兰克福2仓 | X37: 入库操作费-F230DE-250327（公布价）-3 | AA37: DE | AB37: 65462C | AC37: 65462C | AD37: PZ_国际 | AE37: DEFRAB德国法兰克福2仓 | AK37: P558 60"×60"×80" PRO Grow Tent | AL37: P558 Pro款55帐篷-60"x60"x80"/150*150*200cm 22mm管径
A38: IC947270260117155 | B38: SW202601150006DE | C38: FB4 | D38: 入库操作费-DE | E38: 947270 | F38: 2026-04-15 20:24:26 | G38: 0 | H38: 8440.56 | I38: VSL-LL100X2-EU,VSV-IFP4C-EU,VSV-IFP6C-EU | J38: 20,160,48 | K38: 入库操作费 | L38: 海外仓查验费 | M38: EUR | N38: 8.25 | O38: 0 | P38: 8.25 | Q38: 0 | R38: 8.25 | U38: 德国法兰克福2仓 | X38: 入库操作费-F230DE_260410（公布价)-2 | AA38: DE | AB38: 65462C | AC38: 65462C | AD38: PZ_国际 | AE38: DEFRAB德国法兰克福2仓 | AG38: 是 | AK38: Lumalight Grow Light 100Wx2,Plastic exhaust fan with adjustable speed 4 inch,Plastic exhaust fan with adjustable speed 6 inch | AL38: VS-lumalight-量子版2025-100W-两只装-EU,P4 塑料抽风扇调速款单品-欧标,P6 塑料抽风扇调速款单品-欧标
A39: IC947270260117155 | B39: SW202601150006DE | C39: FB4 | D39: 入库操作费-DE | E39: 947270 | F39: 2026-04-15 20:24:26 | G39: 0 | H39: 8440.56 | K39: 入库操作费 | L39: 入库卸货费 | M39: EUR | N39: 0 | O39: 0 | P39: 0 | Q39: 0 | R39: 0 | S39: mums.measurement_info.code.CBM | T39: 45.18257 | U39: 德国法兰克福2仓 | X39: 入库操作费-F230DE_260410（公布价)-2 | AA39: DE | AB39: 65462C | AC39: 65462C | AD39: PZ_国际 | AE39: DEFRAB德国法兰克福2仓 | AG39: 是
A40: IC947270260117155 | B40: SW202601150006DE | C40: FB4 | D40: 入库操作费-DE | E40: 947270 | F40: 2026-04-15 20:24:26 | G40: 0 | H40: 8440.56 | I40: 330101CNJ-EU | J40: 120 | K40: 入库操作费 | L40: 入库操作费 | M40: EUR | N40: 33.6 | O40: 0 | P40: 28.8 | Q40: 0 | R40: 28.8 | S40: 个 | T40: 0.85 | U40: 德国法兰克福2仓 | X40: 入库操作费-F230DE_260410（公布价)-2 | AA40: DE | AB40: 65462C | AC40: 65462C | AD40: PZ_国际 | AE40: DEFRAB德国法兰克福2仓 | AG40: 是 | AK40: 10"x 20.75" Seedling Heat Mat and Digital Thermostat Combo Set | AL40: 欧规 恒温器+育苗垫组合10*20
A41: IC947270260117155 | B41: SW202601150006DE | C41: FB4 | D41: 入库操作费-DE | E41: 947270 | F41: 2026-04-15 20:24:26 | G41: 0 | H41: 8440.56 | I41: VSL-LRUC100-EU | J41: 92 | K41: 入库操作费 | L41: 入库操作费 | M41: EUR | N41: 30.36 | O41: 0 | P41: 25.76 | Q41: 0 | R41: 25.76 | S41: 个 | T41: 2.9 | U41: 德国法兰克福2仓 | X41: 入库操作费-F230DE_260410（公布价)-2 | AA41: DE | AB41: 65462C | AC41: 65462C | AD41: PZ_国际 | AE41: DEFRAB德国法兰克福2仓 | AG41: 是 | AK41: Supplemental light LumaRay-under canopy 100W-EU | AL41: Supplemental light LumaRay-under canopy 100W-EU
A42: IC947270260117155 | B42: SW202601150006DE | C42: FB4 | D42: 入库操作费-DE | E42: 947270 | F42: 2026-04-15 20:24:26 | G42: 0 | H42: 8440.56 | I42: VSV-AZG6-EU | J42: 12 | K42: 入库操作费 | L42: 入库操作费 | M42: EUR | N42: 6 | O42: 0 | P42: 5.16 | Q42: 0 | R42: 5.16 | S42: 个 | T42: 3.318 | U42: 德国法兰克福2仓 | X42: 入库操作费-F230DE_260410（公布价)-2 | AA42: DE | AB42: 65462C | AC42: 65462C | AD42: PZ_国际 | AE42: DEFRAB德国法兰克福2仓 | AG42: 是 | AK42: AeroZesh G6金属风机6寸+线控 | AL42: AeroZesh G6金属风机6寸+线控
A43: IC947270260117155 | B43: SW202601150006DE | C43: FB4 | D43: 入库操作费-DE | E43: 947270 | F43: 2026-04-15 20:24:26 | G43: 0 | H43: 8440.56 | I43: VSVC-AZT6E42AP-EU | J43: 12 | K43: 入库操作费 | L43: 入库操作费 | M43: EUR | N43: 11.28 | O43: 0 | P43: 9.72 | Q43: 0 | R43: 9.72 | S43: 个 | T43: 10 | U43: 德国法兰克福2仓 | X43: 入库操作费-F230DE_260410（公布价)-2 | AA43: DE | AB43: 65462C | AC43: 65462C | AD43: PZ_国际 | AE43: DEFRAB德国法兰克福2仓 | AG43: 是 | AK43: Smart Air Filtration Kit Pro 6″ | AL43: AeroZesh T6 金属底座风机 6寸 + GrowHub E42A+控制器+黑色滤芯6寸+黑色风管6寸8ft 欧版
A44: IC947270260117155 | B44: SW202601150006DE | C44: FB4 | D44: 入库操作费-DE | E44: 947270 | F44: 2026-04-15 20:24:26 | G44: 0 | H44: 8440.56 | I44: VSL-LL100X2-EU | J44: 20 | K44: 入库操作费 | L44: 入库操作费 | M44: EUR | N44: 18.8 | O44: 0 | P44: 16.2 | Q44: 0 | R44: 16.2 | S44: 个 | T44: 5.522 | U44: 德国法兰克福2仓 | X44: 入库操作费-F230DE_260410（公布价)-2 | AA44: DE | AB44: 65462C | AC44: 65462C | AD44: PZ_国际 | AE44: DEFRAB德国法兰克福2仓 | AG44: 是 | AK44: Lumalight Grow Light 100Wx2 | AL44: VS-lumalight-量子版2025-100W-两只装-EU
A45: IC947270260117155 | B45: SW202601150006DE | C45: FB4 | D45: 入库操作费-DE | E45: 947270 | F45: 2026-04-15 20:24:26 | G45: 0 | H45: 8440.56 | I45: VSVC-AZT4-EU | J45: 10 | K45: 入库操作费 | L45: 入库操作费 | M45: EUR | N45: 9.4 | O45: 0 | P45: 8.1 | Q45: 0 | R45: 8.1 | S45: 个 | T45: 6.005 | U45: 德国法兰克福2仓 | X45: 入库操作费-F230DE_260410（公布价)-2 | AA45: DE | AB45: 65462C | AC45: 65462C | AD45: PZ_国际 | AE45: DEFRAB德国法兰克福2仓 | AG45: 是 | AK45: Smart Air Filtration T4 Kit 4"
A46: IC947270260117155 | B46: SW202601150006DE | C46: FB4 | D46: 入库操作费-DE | E46: 947270 | F46: 2026-04-15 20:24:26 | G46: 0 | H46: 8440.56 | I46: VSE-UH075-EU | J46: 0 | K46: 入库操作费 | L46: 入库操作费 | M46: EUR | N46: 0 | O46: 0 | P46: 0 | Q46: 0 | R46: 0 | S46: 个 | T46: 0 | U46: 德国法兰克福2仓 | X46: 入库操作费-F230DE_260410（公布价)-2 | AA46: DE | AB46: 65462C | AC46: 65462C | AD46: PZ_国际 | AE46: DEFRAB德国法兰克福2仓 | AG46: 是 | AK46: USB Humidifier 750ML
A47: IC947270260117155 | B47: SW202601150006DE | C47: FB4 | D47: 入库操作费-DE | E47: 947270 | F47: 2026-04-15 20:24:26 | G47: 0 | H47: 8440.56 | I47: 311001-5X5-EU | J47: 220 | K47: 入库操作费 | L47: 入库操作费 | M47: EUR | N47: 61.6 | O47: 0 | P47: 52.8 | Q47: 0 | R47: 52.8 | S47: 个 | T47: 0.65 | U47: 德国法兰克福2仓 | X47: 入库操作费-F230DE_260410（公布价)-2 | AA47: DE | AB47: 65462C | AC47: 65462C | AD47: PZ_国际 | AE47: DEFRAB德国法兰克福2仓 | AG47: 是 | AK47: 5 gallon Grow Bags | AL47: 5加仑黑色种植袋 5个一卖
A48: IC947270260117155 | B48: SW202601150006DE | C48: FB4 | D48: 入库操作费-DE | E48: 947270 | F48: 2026-04-15 20:24:26 | G48: 0 | H48: 8440.56 | I48: VSVC-AZG6-EU | J48: 17 | K48: 入库操作费 | L48: 入库操作费 | M48: EUR | N48: 15.98 | O48: 0 | P48: 13.77 | Q48: 0 | R48: 13.77 | S48: 个 | T48: 9 | U48: 德国法兰克福2仓 | X48: 入库操作费-F230DE_260410（公布价)-2 | AA48: DE | AB48: 65462C | AC48: 65462C | AD48: PZ_国际 | AE48: DEFRAB德国法兰克福2仓 | AG48: 是 | AK48: Smart Air Filtration G6 Kit 6"
A49: IC947270260117155 | B49: SW202601150006DE | C49: FB4 | D49: 入库操作费-DE | E49: 947270 | F49: 2026-04-15 20:24:26 | G49: 0 | H49: 8440.56 | I49: VGS-CF10-2-EU | J49: 60 | K49: 入库操作费 | L49: 入库操作费 | M49: EUR | N49: 13.8 | O49: 0 | P49: 12 | Q49: 0 | R49: 12 | S49: 个 | T49: 0.34 | U49: 德国法兰克福2仓 | X49: 入库操作费-F230DE_260410（公布价)-2 | AA49: DE | AB49: 65462C | AC49: 65462C | AD49: PZ_国际 | AE49: DEFRAB德国法兰克福2仓 | AG49: 是 | AK49: Filter Replacement | AL49: Y18 替换滤芯 2只装
A50: IC947270260117155 | B50: SW202601150006DE | C50: FB4 | D50: 入库操作费-DE | E50: 947270 | F50: 2026-04-15 20:24:26 | G50: 0 | H50: 8440.56 | I50: VSV-AZT6E42AP-EU | J50: 30 | K50: 入库操作费 | L50: 入库操作费 | M50: EUR | N50: 15 | O50: 0 | P50: 12.9 | Q50: 0 | R50: 12.9 | S50: 个 | T50: 3.215 | U50: 德国法兰克福2仓 | X50: 入库操作费-F230DE_260410（公布价)-2 | AA50: DE | AB50: 65462C | AC50: 65462C | AD50: PZ_国际 | AE50: DEFRAB德国法兰克福2仓 | AG50: 是 | AK50: AeroZesh T6 金属底座风机 6寸 + GrowHub E42A+控制器 欧版 | AL50: AeroZesh T6 金属底座风机 6寸 + GrowHub E42A+控制器 欧版
A51: IC947270260117155 | B51: SW202601150006DE | C51: FB4 | D51: 入库操作费-DE | E51: 947270 | F51: 2026-04-15 20:24:26 | G51: 0 | H51: 8440.56 | I51: VSL-LL150-EU | J51: 65 | K51: 入库操作费 | L51: 入库操作费 | M51: EUR | N51: 32.5 | O51: 0 | P51: 27.95 | Q51: 0 | R51: 27.95 | S51: 个 | T51: 3.981 | U51: 德国法兰克福2仓 | X51: 入库操作费-F230DE_260410（公布价)-2 | AA51: DE | AB51: 65462C | AC51: 65462C | AD51: PZ_国际 | AE51: DEFRAB德国法兰克福2仓 | AG51: 是 | AK51: Vivosun Lumalight LED Grow Light 150W | AL51: VS-lumalight-量子版2025-150W-EU
A52: IC947270260117155 | B52: SW202601150006DE | C52: FB4 | D52: 入库操作费-DE | E52: 947270 | F52: 2026-04-15 20:24:26 | G52: 0 | H52: 8440.56 | I52: VSVC-AZT8E42AP-EU | J52: 2 | K52: 入库操作费 | L52: 入库操作费 | M52: EUR | N52: 3.86 | O52: 0 | P52: 3.32 | Q52: 0 | R52: 3.32 | S52: 个 | T52: 16.5 | U52: 德国法兰克福2仓 | X52: 入库操作费-F230DE_260410（公布价)-2 | AA52: DE | AB52: 65462C | AC52: 65462C | AD52: PZ_国际 | AE52: DEFRAB德国法兰克福2仓 | AG52: 是 | AK52: Smart Air Filtration PRO T8 Kit 8" | AL52: AeroZesh T8 金属底座风机 8寸 + GrowHub E42A+控制器+黑色滤芯8寸+黑色风管8寸25ft 欧版
A53: IC947270260117155 | B53: SW202601150006DE | C53: FB4 | D53: 入库操作费-DE | E53: 947270 | F53: 2026-04-15 20:24:26 | G53: 0 | H53: 8440.56 | I53: LH-001-EU | J53: 200 | K53: 入库操作费 | L53: 入库操作费 | M53: EUR | N53: 46 | O53: 0 | P53: 40 | Q53: 0 | R53: 40 | S53: 个 | T53: 0.16 | U53: 德国法兰克福2仓 | X53: 入库操作费-F230DE_260410（公布价)-2 | AA53: DE | AB53: 65462C | AC53: 65462C | AD53: PZ_国际 | AE53: DEFRAB德国法兰克福2仓 | AG53: 是 | AK53: 1-Pair 1/8 Inch Adjustable Grow Light Hanger, Heavy Duty Rope Hanger with Reinforced Metal Gears, 8Ft
A54: IC947270260117155 | B54: SW202601150006DE | C54: FB4 | D54: 入库操作费-DE | E54: 947270 | F54: 2026-04-15 20:24:26 | G54: 0 | H54: 8440.56 | I54: HDR006-EU | J54: 40 | K54: 入库操作费 | L54: 入库操作费 | M54: EUR | N54: 11.2 | O54: 0 | P54: 9.6 | Q54: 0 | R54: 9.6 | S54: 个 | T54: 0.94 | U54: 德国法兰克福2仓 | X54: 入库操作费-F230DE_260410（公布价)-2 | AA54: DE | AB54: 65462C | AC54: 65462C | AD54: PZ_国际 | AE54: DEFRAB德国法兰克福2仓 | AG54: 是 | AK54: 6-Layer Mesh Drying Rack | AL54: 六层草药晾晒网
A55: IC947270260117155 | B55: SW202601150006DE | C55: FB4 | D55: 入库操作费-DE | E55: 947270 | F55: 2026-04-15 20:24:26 | G55: 0 | H55: 8440.56 | I55: VSEX-CGM-BL-EU | J55: 50 | K55: 入库操作费 | L55: 入库操作费 | M55: EUR | N55: 16.5 | O55: 0 | P55: 14 | Q55: 0 | R55: 14 | S55: 个 | T55: 1.362 | U55: 德国法兰克福2仓 | X55: 入库操作费-F230DE_260410（公布价)-2 | AA55: DE | AB55: 65462C | AC55: 65462C | AD55: PZ_国际 | AE55: DEFRAB德国法兰克福2仓 | AG55: 是 | AK55: Vivosun Gummy Machine | AL55: 糖果机套装 欧规
A56: IC947270260117155 | B56: SW202601150006DE | C56: FB4 | D56: 入库操作费-DE | E56: 947270 | F56: 2026-04-15 20:24:26 | G56: 0 | H56: 8440.56 | I56: VSC-GCC4-EU | J56: 648 | K56: 入库操作费 | L56: 入库操作费 | M56: EUR | N56: 149.04 | O56: 0 | P56: 129.6 | Q56: 0 | R56: 129.6 | S56: 个 | T56: 0.262 | U56: 德国法兰克福2仓 | X56: 入库操作费-F230DE_260410（公布价)-2 | AA56: DE | AB56: 65462C | AC56: 65462C | AD56: PZ_国际 | AE56: DEFRAB德国法兰克福2仓 | AG56: 是 | AK56: GrowCam C4 | AL56: GrowCam 摄像头 400W 2K-欧版
A57: IC947270260117155 | B57: SW202601150006DE | C57: FB4 | D57: 入库操作费-DE | E57: 947270 | F57: 2026-04-15 20:24:26 | G57: 0 | H57: 8440.56 | I57: VSVC-AZG8E42AP-EU | J57: 10 | K57: 入库操作费 | L57: 入库操作费 | M57: EUR | N57: 19.3 | O57: 0 | P57: 16.6 | Q57: 0 | R57: 16.6 | S57: 个 | T57: 15.5 | U57: 德国法兰克福2仓 | X57: 入库操作费-F230DE_260410（公布价)-2 | AA57: DE | AB57: 65462C | AC57: 65462C | AD57: PZ_国际 | AE57: DEFRAB德国法兰克福2仓 | AG57: 是 | AK57: Smart Air Filtration PRO G8 Kit 8" | AL57: AeroZesh G8 金属底座风机 8寸 + GrowHub E42A+控制器+黑色滤芯8寸+黑色风管8寸25ft 欧版
A58: IC947270260117155 | B58: SW202601150006DE | C58: FB4 | D58: 入库操作费-DE | E58: 947270 | F58: 2026-04-15 20:24:26 | G58: 0 | H58: 8440.56 | I58: 306146-0820-EU | J58: 10 | K58: 入库操作费 | L58: 入库操作费 | M58: EUR | N58: 9.4 | O58: 0 | P58: 8.1 | Q58: 0 | R58: 8.1 | S58: 个 | T58: 7.51 | U58: 德国法兰克福2仓 | X58: 入库操作费-F230DE_260410（公布价)-2 | AA58: DE | AB58: 65462C | AC58: 65462C | AD58: PZ_国际 | AE58: DEFRAB德国法兰克福2仓 | AG58: 是 | AK58: 8-Inch Air Carbon Filter for Odor Control, black | AL58: VIVOSUN钢印滤芯 黑色8寸
A59: IC947270260117155 | B59: SW202601150006DE | C59: FB4 | D59: 入库操作费-DE | E59: 947270 | F59: 2026-04-15 20:24:26 | G59: 0 | H59: 8440.56 | I59: VSV-AZG8E42AP-EU | J59: 4 | K59: 入库操作费 | L59: 入库操作费 | M59: EUR | N59: 2 | O59: 0 | P59: 1.72 | Q59: 0 | R59: 1.72 | S59: 个 | T59: 4.792 | U59: 德国法兰克福2仓 | X59: 入库操作费-F230DE_260410（公布价)-2 | AA59: DE | AB59: 65462C | AC59: 65462C | AD59: PZ_国际 | AE59: DEFRAB德国法兰克福2仓 | AG59: 是 | AK59: VSV-AZG8E42AP-EU||AeroZesh G8 金属底座风机 8寸 + GrowHub E42A+控制器 欧版 | AL59: AeroZesh G8 金属底座风机 8寸 + GrowHub E42A+控制器 欧版
A60: IC947270260117155 | B60: SW202601150006DE | C60: FB4 | D60: 入库操作费-DE | E60: 947270 | F60: 2026-04-15 20:24:26 | G60: 0 | H60: 8440.56 | I60: TN-44-EU | J60: 12 | K60: 入库操作费 | L60: 入库操作费 | M60: EUR | N60: 2.76 | O60: 0 | P60: 2.4 | Q60: 0 | R60: 2.4 | S60: 个 | T60: 0.2 | U60: 德国法兰克福2仓 | X60: 入库操作费-F230DE_260410（公布价)-2 | AA60: DE | AB60: 65462C | AC60: 65462C | AD60: PZ_国际 | AE60: DEFRAB德国法兰克福2仓 | AG60: 是 | AK60: 4 x 4Ft. Elastic Trellis Netting | AL60: 弹力爬藤网 4*4FT(网格尺寸：10*10cm)
A61: IC947270260117155 | B61: SW202601150006DE | C61: FB4 | D61: 入库操作费-DE | E61: 947270 | F61: 2026-04-15 20:24:26 | G61: 0 | H61: 8440.56 | I61: VSV-IFP4C-EU | J61: 160 | K61: 入库操作费 | L61: 入库操作费 | M61: EUR | N61: 44.8 | O61: 0 | P61: 38.4 | Q61: 0 | R61: 38.4 | S61: 个 | T61: 0.506 | U61: 德国法兰克福2仓 | X61: 入库操作费-F230DE_260410（公布价)-2 | AA61: DE | AB61: 65462C | AC61: 65462C | AD61: PZ_国际 | AE61: DEFRAB德国法兰克福2仓 | AG61: 是 | AK61: Plastic exhaust fan with adjustable speed 4 inch | AL61: P4 塑料抽风扇调速款单品-欧标
A62: IC947270260117155 | B62: SW202601150006DE | C62: FB4 | D62: 入库操作费-DE | E62: 947270 | F62: 2026-04-15 20:24:26 | G62: 0 | H62: 8440.56 | I62: VSV-AZT6-EU | J62: 8 | K62: 入库操作费 | L62: 入库操作费 | M62: EUR | N62: 2.64 | O62: 0 | P62: 2.24 | Q62: 0 | R62: 2.24 | S62: 个 | T62: 2.776 | U62: 德国法兰克福2仓 | X62: 入库操作费-F230DE_260410（公布价)-2 | AA62: DE | AB62: 65462C | AC62: 65462C | AD62: PZ_国际 | AE62: DEFRAB德国法兰克福2仓 | AG62: 是 | AK62: AeroZesh T6金属支架风机6寸+线控 | AL62: AeroZesh T6金属支架风机6寸+线控
A63: IC947270260117155 | B63: SW202601150006DE | C63: FB4 | D63: 入库操作费-DE | E63: 947270 | F63: 2026-04-15 20:24:26 | G63: 0 | H63: 8440.56 | I63: TN-55-EU | J63: 20 | K63: 入库操作费 | L63: 入库操作费 | M63: EUR | N63: 4.6 | O63: 0 | P63: 4 | Q63: 0 | R63: 4 | S63: 个 | T63: 0.27 | U63: 德国法兰克福2仓 | X63: 入库操作费-F230DE_260410（公布价)-2 | AA63: DE | AB63: 65462C | AC63: 65462C | AD63: PZ_国际 | AE63: DEFRAB德国法兰克福2仓 | AG63: 是 | AK63: 5 x 5Ft. Elastic Trellis Netting | AL63: 弹力爬藤网 5*5FT(网格尺寸：10*10cm)
A64: IC947270260117155 | B64: SW202601150006DE | C64: FB4 | D64: 入库操作费-DE | E64: 947270 | F64: 2026-04-15 20:24:26 | G64: 0 | H64: 8440.56 | I64: VSK-GIYS336-EU | J64: 4 | K64: 入库操作费 | L64: 入库操作费 | M64: EUR | N64: 9.6 | O64: 0 | P64: 8.24 | Q64: 0 | R64: 8.24 | S64: 个 | T64: 23 | U64: 德国法兰克福2仓 | X64: 入库操作费-F230DE_260410（公布价)-2 | AA64: DE | AB64: 65462C | AC64: 65462C | AD64: PZ_国际 | AE64: DEFRAB德国法兰克福2仓 | AG64: 是 | AK64: Smart Grow Tent Kit GIY-SE-33 3x3, 3-Plant Complete System | AL64: GIY SGS智能标准款帐篷套装S336欧版
A65: IC947270260117155 | B65: SW202601150006DE | C65: FB4 | D65: 入库操作费-DE | E65: 947270 | F65: 2026-04-15 20:24:26 | G65: 0 | H65: 8440.56 | I65: VSL-LL100-EU | J65: 84 | K65: 入库操作费 | L65: 入库操作费 | M65: EUR | N65: 27.72 | O65: 0 | P65: 23.52 | Q65: 0 | R65: 23.52 | S65: 个 | T65: 2.997 | U65: 德国法兰克福2仓 | X65: 入库操作费-F230DE_260410（公布价)-2 | AA65: DE | AB65: 65462C | AC65: 65462C | AD65: PZ_国际 | AE65: DEFRAB德国法兰克福2仓 | AG65: 是 | AK65: VS lumalight LED Grow Light Board 100W | AL65: VS-lumalight-量子版2025-100W-EU
... A67: IC947270260117155 | B67: SW202601150006DE | C67: FB4 | D67: 入库操作费-DE | E67: 947270 | F67: 2026-04-15 20:24:26 | G67: 0 | H67: 8440.56 | I67: VSV-AZG4E42AP-EU | J67: 8 | K67: 入库操作费 | L67: 入库操作费 | M67: EUR | N67: 2.64 | O67: 0 | P67: 2.24 | Q67: 0 | R67: 2.24 | S67: 个 | T67: 2.859 | U67: 德国法兰克福2仓 | X67: 入库操作费-F230DE_260410（公布价)-2 | AA67: DE | AB67: 65462C | AC67: 65462C | AD67: PZ_国际 | AE67: DEFRAB德国法兰克福2仓 | AG67: 是 | AK67: AeroZesh G4 Inline fan + GrowHub E42A+ | AL67: AeroZesh G4 金属底座风机 4寸 + GrowHub E42A+控制器 欧版
A68: IC947270260117155 | B68: SW202601150006DE | C68: FB4 | D68: 入库操作费-DE | E68: 947270 | F68: 2026-04-15 20:24:26 | G68: 0 | H68: 8440.56 | I68: 332572-EU | J68: 30 | K68: 入库操作费 | L68: 入库操作费 | M68: EUR | N68: 8.4 | O68: 0 | P68: 7.2 | Q68: 0 | R68: 7.2 | S68: 个 | T68: 0.89 | U68: 德国法兰克福2仓 | X68: 入库操作费-F230DE_260410（公布价)-2 | AA68: DE | AB68: 65462C | AC68: 65462C | AD68: PZ_国际 | AE68: DEFRAB德国法兰克福2仓 | AG68: 是 | AK68: 800GPH Submersible Pump(3000L/H, 24W), Ultra Quiet Water Fountain Pump with 10ft. High Lift with 6.5ft.
A69: IC947270260117155 | B69: SW202601150006DE | C69: FB4 | D69: 入库操作费-DE | E69: 947270 | F69: 2026-04-15 20:24:26 | G69: 0 | H69: 8440.56 | I69: 305131-EU | J69: 150 | K69: 入库操作费 | L69: 入库操作费 | M69: EUR | N69: 34.5 | O69: 0 | P69: 30 | Q69: 0 | R69: 30 | S69: 个 | T69: 0.09 | U69: 德国法兰克福2仓 | X69: 入库操作费-F230DE_260410（公布价)-2 | AA69: DE | AB69: 65462C | AC69: 65462C | AD69: PZ_国际 | AE69: DEFRAB德国法兰克福2仓 | AG69: 是 | AK69: Soil tester
A70: IC947270260117155 | B70: SW202601150006DE | C70: FB4 | D70: 入库操作费-DE | E70: 947270 | F70: 2026-04-15 20:24:26 | G70: 0 | H70: 8440.56 | I70: VSI-FFSW6-4-EU | J70: 46 | K70: 入库操作费 | L70: 入库操作费 | M70: EUR | N70: 23 | O70: 0 | P70: 19.78 | Q70: 0 | R70: 19.78 | S70: 个 | T70: 4.72 | U70: 德国法兰克福2仓 | X70: 入库操作费-F230DE_260410（公布价)-2 | AA70: DE | AB70: 65462C | AC70: 65462C | AD70: PZ_国际 | AE70: DEFRAB德国法兰克福2仓 | AG70: 是 | AK70: 4-Pack FlexFeed Self-Watering Irrigation Pot
A71: IC947270260117155 | B71: SW202601150006DE | C71: FB4 | D71: 入库操作费-DE | E71: 947270 | F71: 2026-04-15 20:24:26 | G71: 0 | H71: 8440.56 | I71: VSE-ASU075-EU | J71: 120 | K71: 入库操作费 | L71: 入库操作费 | M71: EUR | N71: 27.6 | O71: 0 | P71: 24 | Q71: 0 | R71: 24 | S71: 个 | T71: 0.39 | U71: 德国法兰克福2仓 | X71: 入库操作费-F230DE_260410（公布价)-2 | AA71: DE | AB71: 65462C | AC71: 65462C | AD71: PZ_国际 | AE71: DEFRAB德国法兰克福2仓 | AG71: 是 | AK71: AeroStream U075 USB Humidifier
A72: IC947270260117155 | B72: SW202601150006DE | C72: FB4 | D72: 入库操作费-DE | E72: 947270 | F72: 2026-04-15 20:24:26 | G72: 0 | H72: 8440.56 | I72: VSA-AG-5B3-EU | J72: 4 | K72: 入库操作费 | L72: 入库操作费 | M72: EUR | N72: 1.32 | O72: 0 | P72: 1.12 | Q72: 0 | R72: 1.12 | S72: 个 | T72: 1.309 | U72: 德国法兰克福2仓 | X72: 入库操作费-F230DE_260410（公布价)-2 | AA72: DE | AB72: 65462C | AC72: 65462C | AD72: PZ_国际 | AE72: DEFRAB德国法兰克福2仓 | AG72: 是 | AK72: 3-Pack 5-Gallon AeroBase Grow Bag | AL72: AeroBase空气底种植袋黑色5加仑3pcs
A73: IC947270260117155 | B73: SW202601150006DE | C73: FB4 | D73: 入库操作费-DE | E73: 947270 | F73: 2026-04-15 20:24:26 | G73: 0 | H73: 8440.56 | I73: 304113-P276-EU | J73: 10 | K73: 入库操作费 | L73: 入库操作费 | M73: EUR | N73: 14.5 | O73: 0 | P73: 12.5 | Q73: 0 | R73: 12.5 | S73: 个 | T73: 11.4 | U73: 德国法兰克福2仓 | X73: 入库操作费-F230DE_260410（公布价)-2 | AA73: DE | AB73: 65462C | AC73: 65462C | AD73: PZ_国际 | AE73: DEFRAB德国法兰克福2仓 | AG73: 是 | AK73: P276 32"×32"×63" PRO Grow Tent | AL73: P276 Pro款27帐篷-32"x32"x63"/80*80*160cm 22mm管径
A74: IC947270260117155 | B74: SW202601150006DE | C74: FB4 | D74: 入库操作费-DE | E74: 947270 | F74: 2026-04-15 20:24:26 | G74: 0 | H74: 8440.56 | I74: GH-E42AP-EU | J74: 96 | K74: 入库操作费 | L74: 入库操作费 | M74: EUR | N74: 26.88 | O74: 0 | P74: 23.04 | Q74: 0 | R74: 23.04 | S74: 个 | T74: 0.719 | U74: 德国法兰克福2仓 | X74: 入库操作费-F230DE_260410（公布价)-2 | AA74: DE | AB74: 65462C | AC74: 65462C | AD74: PZ_国际 | AE74: DEFRAB德国法兰克福2仓 | AG74: 是 | AK74: GrowHub E42A+ Controller for Grow Tent | AL74: GrowHub E42A+ Controller 欧版
A75: IC947270260117155 | B75: SW202601150006DE | C75: FB4 | D75: 入库操作费-DE | E75: 947270 | F75: 2026-04-15 20:24:26 | G75: 0 | H75: 8440.56 | I75: GH-E25-EU | J75: 200 | K75: 入库操作费 | L75: 入库操作费 | M75: EUR | N75: 46 | O75: 0 | P75: 40 | Q75: 0 | R75: 40 | S75: 个 | T75: 0.02 | U75: 德国法兰克福2仓 | X75: 入库操作费-F230DE_260410（公布价)-2 | AA75: DE | AB75: 65462C | AC75: 65462C | AD75: PZ_国际 | AE75: DEFRAB德国法兰克福2仓 | AG75: 是 | AK75: E25控制器-单品包装 | AL75: E25控制器-单品包装
A76: IC947270260117155 | B76: SW202601150006DE | C76: FB4 | D76: 入库操作费-DE | E76: 947270 | F76: 2026-04-15 20:24:26 | G76: 0 | H76: 8440.56 | I76: 304113-P336-EU | J76: 24 | K76: 入库操作费 | L76: 入库操作费 | M76: EUR | N76: 34.8 | O76: 0 | P76: 30 | Q76: 0 | R76: 30 | S76: 个 | T76: 14.46 | U76: 德国法兰克福2仓 | X76: 入库操作费-F230DE_260410（公布价)-2 | AA76: DE | AB76: 65462C | AC76: 65462C | AD76: PZ_国际 | AE76: DEFRAB德国法兰克福2仓 | AG76: 是 | AK76: P336 36"×36"×72" PRO Grow Tent | AL76: P336 Pro款33帐篷-36"x36"x72"/90*90*180cm 22mm管径
A77: IC947270260117155 | B77: SW202601150006DE | C77: FB4 | D77: 入库操作费-DE | E77: 947270 | F77: 2026-04-15 20:24:26 | G77: 0 | H77: 8440.56 | I77: 306143-0412-EU | J77: 179 | K77: 入库操作费 | L77: 入库操作费 | M77: EUR | N77: 59.07 | O77: 0 | P77: 50.12 | Q77: 0 | R77: 50.12 | S77: 个 | T77: 2.475 | U77: 德国法兰克福2仓 | X77: 入库操作费-F230DE_260410（公布价)-2 | AA77: DE | AB77: 65462C | AC77: 65462C | AD77: PZ_国际 | AE77: DEFRAB德国法兰克福2仓 | AG77: 是 | AK77: VIVOSUN钢印滤芯 4" | AL77: VIVOSUN钢印滤芯 4"
A78: IC947270260117155 | B78: SW202601150006DE | C78: FB4 | D78: 入库操作费-DE | E78: 947270 | F78: 2026-04-15 20:24:26 | G78: 0 | H78: 8440.56 | I78: VSEX-HID1-ST-EU | J78: 8 | K78: 入库操作费 | L78: 入库操作费 | M78: EUR | N78: 4 | O78: 0 | P78: 3.44 | Q78: 0 | R78: 3.44 | S78: 个 | T78: 3.812 | U78: 德国法兰克福2仓 | X78: 入库操作费-F230DE_260410（公布价)-2 | AA78: DE | AB78: 65462C | AC78: 65462C | AD78: PZ_国际 | AE78: DEFRAB德国法兰克福2仓 | AG78: 是 | AK78: Herbal Decarboxylation and Infusion Machine | AL78: S4508B 黄油机套装-欧版
A79: IC947270260117155 | B79: SW202601150006DE | C79: FB4 | D79: 入库操作费-DE | E79: 947270 | F79: 2026-04-15 20:24:26 | G79: 0 | H79: 8440.56 | I79: VGA-TN13-EU | J79: 30 | K79: 入库操作费 | L79: 入库操作费 | M79: EUR | N79: 6.9 | O79: 0 | P79: 6 | Q79: 0 | R79: 6 | S79: 个 | T79: 0.07 | U79: 德国法兰克福2仓 | X79: 入库操作费-F230DE_260410（公布价)-2 | AA79: DE | AB79: 65462C | AC79: 65462C | AD79: PZ_国际 | AE79: DEFRAB德国法兰克福2仓 | AG79: 是 | AK79: Trellis Net | AL79: Y18 爬藤网
A80: IC947270260117155 | B80: SW202601150006DE | C80: FB4 | D80: 入库操作费-DE | E80: 947270 | F80: 2026-04-15 20:24:26 | G80: 0 | H80: 8440.56 | I80: VSE-ADD12-EU | J80: 8 | K80: 入库操作费 | L80: 入库操作费 | M80: EUR | N80: 11.6 | O80: 0 | P80: 10 | Q80: 0 | R80: 10 | S80: 个 | T80: 12.5 | U80: 德国法兰克福2仓 | X80: 入库操作费-F230DE_260410（公布价)-2 | AA80: DE | AB80: 65462C | AC80: 65462C | AD80: PZ_国际 | AE80: DEFRAB德国法兰克福2仓 | AG80: 是 | AK80: Desumidificador AeroDrain D12 | AL80: AeroDrain WiFi除湿机_12L_欧版
A81: IC947270260117155 | B81: SW202601150006DE | C81: FB4 | D81: 入库操作费-DE | E81: 947270 | F81: 2026-04-15 20:24:26 | G81: 0 | H81: 8440.56 | I81: 332823-100J-EU | J81: 48 | K81: 入库操作费 | L81: 入库操作费 | M81: EUR | N81: 11.04 | O81: 0 | P81: 9.6 | Q81: 0 | R81: 9.6 | S81: 个 | T81: 0.2 | U81: 德国法兰克福2仓 | X81: 入库操作费-F230DE_260410（公布价)-2 | AA81: DE | AB81: 65462C | AC81: 65462C | AD81: PZ_国际 | AE81: DEFRAB德国法兰克福2仓 | AG81: 是 | AK81: 328 Feet (100m) PE-Coated Twist Ties | AL81: 园林扎线-100米
A82: IC947270260117155 | B82: SW202601150006DE | C82: FB4 | D82: 入库操作费-DE | E82: 947270 | F82: 2026-04-15 20:24:26 | G82: 0 | H82: 8440.56 | I82: VSL-LRSF50-4-EU | J82: 96 | K82: 入库操作费 | L82: 入库操作费 | M82: EUR | N82: 31.68 | O82: 0 | P82: 26.88 | Q82: 0 | R82: 26.88 | S82: 个 | T82: 1.378 | U82: 德国法兰克福2仓 | X82: 入库操作费-F230DE_260410（公布价)-2 | AA82: DE | AB82: 65462C | AC82: 65462C | AD82: PZ_国际 | AE82: DEFRAB德国法兰克福2仓 | AG82: 是 | AK82: Supplemental light LumaRay Side lighting 4bar | AL82: Supplemental light LumaRay Side lighting 4bar补光灯 欧版
A83: IC947270260117155 | B83: SW202601150006DE | C83: FB4 | D83: 入库操作费-DE | E83: 947270 | F83: 2026-04-15 20:24:26 | G83: 0 | H83: 8440.56 | I83: PS-002-EU | J83: 145 | K83: 入库操作费 | L83: 入库操作费 | M83: EUR | N83: 33.35 | O83: 0 | P83: 29 | Q83: 0 | R83: 29 | S83: 个 | T83: 0.07 | U83: 德国法兰克福2仓 | X83: 入库操作费-F230DE_260410（公布价)-2 | AA83: DE | AB83: 65462C | AC83: 65462C | AD83: PZ_国际 | AE83: DEFRAB德国法兰克福2仓 | AG83: 是 | AK83: 黑绿配色花枝剪1个装 | AL83: 黑绿配色花枝剪1个装
... A85: IC947270260117155 | B85: SW202601150006DE | C85: FB4 | D85: 入库操作费-DE | E85: 947270 | F85: 2026-04-15 20:24:26 | G85: 0 | H85: 8440.56 | I85: SST-H-0001-EU | J85: 80 | K85: 入库操作费 | L85: 入库操作费 | M85: EUR | N85: 26.4 | O85: 0 | P85: 22.4 | Q85: 0 | R85: 22.4 | S85: 个 | T85: 1.06 | U85: 德国法兰克福2仓 | X85: 入库操作费-F230DE_260410（公布价)-2 | AA85: DE | AB85: 65462C | AC85: 65462C | AD85: PZ_国际 | AE85: DEFRAB德国法兰克福2仓 | AG85: 是 | AK85: 6-Pack Seed Starter Trays with 10"x20.75" Seedling Heat Mat | AL85: 欧规 12孔育苗盘6套装+10*20.75育苗垫组合款
A86: IC947270260117155 | B86: SW202601150006DE | C86: FB4 | D86: 入库操作费-DE | E86: 947270 | F86: 2026-04-15 20:24:26 | G86: 0 | H86: 8440.56 | I86: VSF-AWD4X2-EU | J86: 54 | K86: 入库操作费 | L86: 入库操作费 | M86: EUR | N86: 15.12 | O86: 0 | P86: 12.96 | Q86: 0 | R86: 12.96 | S86: 个 | T86: 0.61 | U86: 德国法兰克福2仓 | X86: 入库操作费-F230DE_260410（公布价)-2 | AA86: DE | AB86: 65462C | AC86: 65462C | AD86: PZ_国际 | AE86: DEFRAB德国法兰克福2仓 | AG86: 是 | AK86: AeroWave D4, 4” Grow Tent Clip Fan with Detachable Hook
A87: IC947270260117155 | B87: SW202601150006DE | C87: FB4 | D87: 入库操作费-DE | E87: 947270 | F87: 2026-04-15 20:24:26 | G87: 0 | H87: 8440.56 | I87: VSE-ATW70-EU | J87: 84 | K87: 入库操作费 | L87: 入库操作费 | M87: EUR | N87: 42 | O87: 0 | P87: 36.12 | Q87: 0 | R87: 36.12 | S87: 个 | T87: 3.216 | U87: 德国法兰克福2仓 | X87: 入库操作费-F230DE_260410（公布价)-2 | AA87: DE | AB87: 65462C | AC87: 65462C | AD87: PZ_国际 | AE87: DEFRAB德国法兰克福2仓 | AG87: 是 | AK87: AeroFlux Heater 70w | AL87: AeroFlux Heater 70w
A88: IC947270260117155 | B88: SW202601150006DE | C88: FB4 | D88: 入库操作费-DE | E88: 947270 | F88: 2026-04-15 20:24:26 | G88: 0 | H88: 8440.56 | I88: 330101X2NJ-EU | J88: 20 | K88: 入库操作费 | L88: 入库操作费 | M88: EUR | N88: 5.6 | O88: 0 | P88: 4.8 | Q88: 0 | R88: 4.8 | S88: 个 | T88: 0.755 | U88: 德国法兰克福2仓 | X88: 入库操作费-F230DE_260410（公布价)-2 | AA88: DE | AB88: 65462C | AC88: 65462C | AD88: PZ_国际 | AE88: DEFRAB德国法兰克福2仓 | AG88: 是 | AK88: Seedling heating pad 10''x20'' 2 pieces for sale
A89: IC947270260117155 | B89: SW202601150006DE | C89: FB4 | D89: 入库操作费-DE | E89: 947270 | F89: 2026-04-15 20:24:26 | G89: 0 | H89: 8440.56 | I89: VSV-AZT4E42AP-EU | J89: 27 | K89: 入库操作费 | L89: 入库操作费 | M89: EUR | N89: 8.91 | O89: 0 | P89: 7.56 | Q89: 0 | R89: 7.56 | S89: 个 | T89: 2.638 | U89: 德国法兰克福2仓 | X89: 入库操作费-F230DE_260410（公布价)-2 | AA89: DE | AB89: 65462C | AC89: 65462C | AD89: PZ_国际 | AE89: DEFRAB德国法兰克福2仓 | AG89: 是 | AK89: AeroZesh T4+E42AP | AL89: AeroZesh T4 金属底座风机 4寸 + GrowHub E42A+控制器 欧版
A90: IC947270260117155 | B90: SW202601150006DE | C90: FB4 | D90: 入库操作费-DE | E90: 947270 | F90: 2026-04-15 20:24:26 | G90: 0 | H90: 8440.56 | I90: VSI-FFSW6GB5-4-EU | J90: 30 | K90: 入库操作费 | L90: 入库操作费 | M90: EUR | N90: 28.2 | O90: 0 | P90: 24.3 | Q90: 0 | R90: 24.3 | S90: 个 | T90: 5.11 | U90: 德国法兰克福2仓 | X90: 入库操作费-F230DE_260410（公布价)-2 | AA90: DE | AB90: 65462C | AC90: 65462C | AD90: PZ_国际 | AE90: DEFRAB德国法兰克福2仓 | AG90: 是 | AK90: FlexFeed Self-Watering Fabric Pot Base with Grow Gags | AL90: FlexFleed Self Watering Pots with 5 Gallon Grow Bags 4只装
A91: IC947270260117155 | B91: SW202601150006DE | C91: FB4 | D91: 入库操作费-DE | E91: 947270 | F91: 2026-04-15 20:24:26 | G91: 0 | H91: 8440.56 | I91: VSF-AWD4-EU | J91: 360 | K91: 入库操作费 | L91: 入库操作费 | M91: EUR | N91: 82.8 | O91: 0 | P91: 72 | Q91: 0 | R91: 72 | S91: 个 | T91: 0.31 | U91: 德国法兰克福2仓 | X91: 入库操作费-F230DE_260410（公布价)-2 | AA91: DE | AB91: 65462C | AC91: 65462C | AD91: PZ_国际 | AE91: DEFRAB德国法兰克福2仓 | AG91: 是 | AK91: 黑色4寸夹扇 | AL91: 黑色4寸夹扇
A92: IC947270260117155 | B92: SW202601150006DE | C92: FB4 | D92: 入库操作费-DE | E92: 947270 | F92: 2026-04-15 20:24:26 | G92: 0 | H92: 8440.56 | I92: VSVC-AZG8-EU | J92: 8 | K92: 入库操作费 | L92: 入库操作费 | M92: EUR | N92: 11.6 | O92: 0 | P92: 10 | Q92: 0 | R92: 10 | S92: 个 | T92: 15 | U92: 德国法兰克福2仓 | X92: 入库操作费-F230DE_260410（公布价)-2 | AA92: DE | AB92: 65462C | AC92: 65462C | AD92: PZ_国际 | AE92: DEFRAB德国法兰克福2仓 | AG92: 是 | AK92: Smart Air Filtration G8 Kit 8" | AL92: AeroZesh G8风机+E12线控+滤芯+风管—欧规
A93: IC947270260117155 | B93: SW202601150006DE | C93: FB4 | D93: 入库操作费-DE | E93: 947270 | F93: 2026-04-15 20:24:26 | G93: 0 | H93: 8440.56 | I93: VSF-AWA6G2-EU | J93: 96 | K93: 入库操作费 | L93: 入库操作费 | M93: EUR | N93: 31.68 | O93: 0 | P93: 26.88 | Q93: 0 | R93: 26.88 | S93: 个 | T93: 1.468 | U93: 德国法兰克福2仓 | X93: 入库操作费-F230DE_260410（公布价)-2 | AA93: DE | AB93: 65462C | AC93: 65462C | AD93: PZ_国际 | AE93: DEFRAB德国法兰克福2仓 | AG93: 是 | AK93: Aerowave A6 Gen2 Grow Tent Clip Fan | AL93: 入门款AC电机夹扇A6 Gen2 欧版
A94: IC947270260117155 | B94: SW202601150006DE | C94: FB4 | D94: 入库操作费-DE | E94: 947270 | F94: 2026-04-15 20:24:26 | G94: 0 | H94: 8440.56 | I94: VSF-AWE6-G2X2-EU | J94: 92 | K94: 入库操作费 | L94: 入库操作费 | M94: EUR | N94: 30.36 | O94: 0 | P94: 25.76 | Q94: 0 | R94: 25.76 | S94: 个 | T94: 2.13 | U94: 德国法兰克福2仓 | X94: 入库操作费-F230DE_260410（公布价)-2 | AA94: DE | AB94: 65462C | AC94: 65462C | AD94: PZ_国际 | AE94: DEFRAB德国法兰克福2仓 | AG94: 是 | AK94: Aerowave E6 Gen 2 black clip fan 2-pack
A95: IC947270260117155 | B95: SW202601150006DE | C95: FB4 | D95: 入库操作费-DE | E95: 947270 | F95: 2026-04-15 20:24:26 | G95: 0 | H95: 8440.56 | I95: VSF-AWE6-G2-EU | J95: 48 | K95: 入库操作费 | L95: 入库操作费 | M95: EUR | N95: 15.84 | O95: 0 | P95: 13.44 | Q95: 0 | R95: 13.44 | S95: 个 | T95: 1.1 | U95: 德国法兰克福2仓 | X95: 入库操作费-F230DE_260410（公布价)-2 | AA95: DE | AB95: 65462C | AC95: 65462C | AD95: PZ_国际 | AE95: DEFRAB德国法兰克福2仓 | AG95: 是 | AK95: AeroWave E6 Grow Tent Fan 6”
A96: IC947270260117155 | B96: SW202601150006DE | C96: FB4 | D96: 入库操作费-DE | E96: 947270 | F96: 2026-04-15 20:24:26 | G96: 0 | H96: 8440.56 | I96: VS1000E-EU | J96: 55 | K96: 入库操作费 | L96: 入库操作费 | M96: EUR | N96: 18.15 | O96: 0 | P96: 15.4 | Q96: 0 | R96: 15.4 | S96: 个 | T96: 2.03 | U96: 德国法兰克福2仓 | X96: 入库操作费-F230DE_260410（公布价)-2 | AA96: DE | AB96: 65462C | AC96: 65462C | AD96: PZ_国际 | AE96: DEFRAB德国法兰克福2仓 | AG96: 是 | AK96: VS1000E LED Grow Light with Samsung Diodes | AL96: 欧规 VS1000E量子版100W (带绿色新钩子)
A97: IC947270260117155 | B97: SW202601150006DE | C97: FB4 | D97: 入库操作费-DE | E97: 947270 | F97: 2026-04-15 20:24:26 | G97: 0 | H97: 8440.56 | I97: 304113-52-EU | J97: 6 | K97: 入库操作费 | L97: 入库操作费 | M97: EUR | N97: 8.7 | O97: 0 | P97: 7.5 | Q97: 0 | R97: 7.5 | S97: 个 | T97: 11.821 | U97: 德国法兰克福2仓 | X97: 入库操作费-F230DE_260410（公布价)-2 | AA97: DE | AB97: 65462C | AC97: 65462C | AD97: PZ_国际 | AE97: DEFRAB德国法兰克福2仓 | AG97: 是 | AK97: 52帐篷-60"x32"x80"/150*80*200cm 16mm管径 | AL97: 52帐篷-60"x32"x80"/150*80*200cm 16mm管径
A98: IC947270260117155 | B98: SW202601150006DE | C98: FB4 | D98: 入库操作费-DE | E98: 947270 | F98: 2026-04-15 20:24:26 | G98: 0 | H98: 8440.56 | I98: VSI-DWCRR-4-EU | J98: 50 | K98: 入库操作费 | L98: 入库操作费 | M98: EUR | N98: 11.5 | O98: 0 | P98: 10 | Q98: 0 | R98: 10 | S98: 个 | T98: 0.083 | U98: 德国法兰克福2仓 | X98: 入库操作费-F230DE_260410（公布价)-2 | AA98: DE | AB98: 65462C | AC98: 65462C | AD98: PZ_国际 | AE98: DEFRAB德国法兰克福2仓 | AG98: 是 | AK98: FlexFeed DWC Growing Medium 4 Pack | AL98: FlexFeed DWC 水培桶基质配件 4个装
A99: IC947270260117155 | B99: SW202601150006DE | C99: FB4 | D99: 入库操作费-DE | E99: 947270 | F99: 2026-04-15 20:24:26 | G99: 0 | H99: 8440.56 | I99: E331905-EU | J99: 24 | K99: 入库操作费 | L99: 入库操作费 | M99: EUR | N99: 12 | O99: 0 | P99: 10.32 | Q99: 0 | R99: 10.32 | S99: 个 | T99: 3.623 | U99: 德国法兰克福2仓 | X99: 入库操作费-F230DE_260410（公布价)-2 | AA99: DE | AB99: 65462C | AC99: 65462C | AD99: PZ_国际 | AE99: DEFRAB德国法兰克福2仓 | AG99: 是 | AK99: E331905 || Hand-cranked leaf trimmer | AL99: E331905||手摇叶芽割草机
A100: IC947270260117155 | B100: SW202601150006DE | C100: FB4 | D100: 入库操作费-DE | E100: 947270 | F100: 2026-04-15 20:24:26 | G100: 0 | H100: 8440.56 | I100: 306109-6C-EU | J100: 20 | K100: 入库操作费 | L100: 入库操作费 | M100: EUR | N100: 6.6 | O100: 0 | P100: 5.6 | Q100: 0 | R100: 5.6 | S100: 个 | T100: 1.64 | U100: 德国法兰克福2仓 | X100: 入库操作费-F230DE_260410（公布价)-2 | AA100: DE | AB100: 65462C | AC100: 65462C | AD100: PZ_国际 | AE100: DEFRAB德国法兰克福2仓 | AG100: 是 | AK100: 6 Inch 25 Feet Black Non-Insulated Flex Air Aluminum Ducting | AL100: 风管卡箍组合黑色 6" 25ft
A101: IC947270260117155 | B101: SW202601150006DE | C101: FB4 | D101: 入库操作费-DE | E101: 947270 | F101: 2026-04-15 20:24:26 | G101: 0 | H101: 8440.56 | I101: VSH-IS02-EU | J101: 36 | K101: 入库操作费 | L101: 入库操作费 | M101: EUR | N101: 11.88 | O101: 0 | P101: 10.08 | Q101: 0 | R101: 10.08 | S101: 个 | T101: 1.14 | U101: 德国法兰克福2仓 | X101: 入库操作费-F230DE_260410（公布价)-2 | AA101: DE | AB101: 65462C | AC101: 65462C | AD101: PZ_国际 | AE101: DEFRAB德国法兰克福2仓 | AG101: 是 | AK101: Professional Automatic Drip Irrigation Kits | AL101: 欧版 滴灌套装
A102: IC947270260117155 | B102: SW202601150006DE | C102: FB4 | D102: 入库操作费-DE | E102: 947270 | F102: 2026-04-15 20:24:26 | G102: 0 | H102: 8440.56 | I102: VC-0002-EU | J102: 100 | K102: 入库操作费 | L102: 入库操作费 | M102: EUR | N102: 23 | O102: 0 | P102: 20 | Q102: 0 | R102: 20 | S102: 个 | T102: 0.03 | U102: 德国法兰克福2仓 | X102: 入库操作费-F230DE_260410（公布价)-2 | AA102: DE | AB102: 65462C | AC102: 65462C | AD102: PZ_国际 | AE102: DEFRAB德国法兰克福2仓 | AG102: 是 | AK102: 2-Pcs. Grow Tent Vent Cover 6inch | AL102: 防尘罩-6-Inch两个装
...

Sheet 入库订单 (2)
A1: 业务单号 | B1: 客户单号 | C1: 客户单号 | D1: 平台 | E1: 服务类别 | F1: 服务产品 | G1: 下单子账号 | H1: 计费时间 | I1: 计费重 | J1: 实重 | K1: SKU | L1: SKU数量 | M1: 费用类型 | N1: 费用名称 | O1: 币种 | P1: 计费金额 | Q1: 优惠金额 | R1: 应收金额 | S1: 含代收代付税费 | T1: 可开票金额 | U1: 计费单位 | V1: 计费数量 | W1: 计费地点 | X1: 计算公式 | Y1: 数字公式 | Z1: 报价单编号 | AA1: 优惠券信息 | AB1: 服务商单号 | AC1: 目的地国家 | AD1: 起运地邮编 | AE1: 目的地邮编 | AF1: 起运分区 | AG1: 目的分区 | AH1: 分区名称 | AI1: 有红冲单 | AJ1: 划拨单号 | AK1: 是否跨月重计 | AL1: 备注 | AM1: SKU英文 | AN1: SKU中文 | AO1: 关联入库单号
A2: IC947270260117132 | B2: SW202601150004DE | C2: SW202601150004DE | D2: VS AMZ28.41+WEB39.96 除湿机+空调含制冷剂 | E2: FB4 | F2: 入库操作费-DE | G2: 947270 | H2: 2026-03-31 17:38:38 | I2: 0 | J2: 10762.26 | K2: VSF-AWA6G2X2-EU | L2: 240 | M2: 入库操作费 | N2: 海外仓查验费 | O2: EUR | P2: 2.75 | Q2: 0 | R2: 2.75 | S2: 0 | T2: 2.75 | W2: 德国法兰克福2仓 | Z2: 入库操作费-F230DE-250327（公布价）-3 | AC2: DE | AD2: 65462C | AE2: 65462C | AF2: PZ_国际 | AG2: DEFRAB德国法兰克福2仓 | AM2: 2-Pack AeroWave A6 Gen2 Grow Tent Clip Fan | AN2: 入门款AC电机夹扇A6 Gen2 欧版 两只装
A3: IC947270260117132 | B3: SW202601150004DE | C3: SW202601150004DE | D3: VS AMZ28.41+WEB39.96 除湿机+空调含制冷剂 | E3: FB4 | F3: 入库操作费-DE | G3: 947270 | H3: 2026-03-31 17:38:38 | I3: 0 | J3: 10762.26 | M3: 入库操作费 | N3: 入库卸货费 | O3: EUR | P3: 348.6 | Q3: 0 | R3: 348.6 | S3: 0 | T3: 348.6 | U3: mums.measurement_info.code.CBM | V3: 67.03768 | W3: 德国法兰克福2仓 | Z3: 入库操作费-F230DE-250327（公布价）-3 | AC3: DE | AD3: 65462C | AE3: 65462C | AF3: PZ_国际 | AG3: DEFRAB德国法兰克福2仓
A4: IC947270260117132 | B4: SW202601150004DE | C4: SW202601150004DE | D4: VS AMZ28.41+WEB39.96 除湿机+空调含制冷剂 | E4: FB4 | F4: 入库操作费-DE | G4: 947270 | H4: 2026-03-31 17:38:38 | I4: 0 | J4: 10762.26 | K4: VSE-ALC08-EU | L4: 180 | M4: 入库操作费 | N4: 入库操作费 | O4: EUR | P4: 432 | Q4: 0 | R4: 370.8 | S4: 0 | T4: 370.8 | U4: 个 | V4: 25.778 | W4: 德国法兰克福2仓 | Z4: 入库操作费-F230DE-250327（公布价）-3 | AC4: DE | AD4: 65462C | AE4: 65462C | AF4: PZ_国际 | AG4: DEFRAB德国法兰克福2仓 | AM4: AeroLush Air Conditioner - 8000 BTU - European Standard | AN4: AeroLush 空调_8000BTU_欧规
A5: IC947270260117132 | B5: SW202601150004DE | C5: SW202601150004DE | D5: VS AMZ28.41+WEB39.96 除湿机+空调含制冷剂 | E5: FB4 | F5: 入库操作费-DE | G5: 947270 | H5: 2026-03-31 17:38:38 | I5: 0 | J5: 10762.26 | K5: VSE-ASH05-EU | L5: 240 | M5: 入库操作费 | N5: 入库操作费 | O5: EUR | P5: 72 | Q5: 0 | R5: 62.4 | S5: 0 | T5: 62.4 | U5: 个 | V5: 1.954 | W5: 德国法兰克福2仓 | Z5: 入库操作费-F230DE-250327（公布价）-3 | AC5: DE | AD5: 65462C | AE5: 65462C | AF5: PZ_国际 | AG5: DEFRAB德国法兰克福2仓 | AM5: AeroStream Humidificateur pour plantes 5 l | AN5: AeroStream 5L智能Wi-Fi加湿器（SGS，单核雾化片）-欧版
A6: IC947270260117132 | B6: SW202601150004DE | C6: SW202601150004DE | D6: VS AMZ28.41+WEB39.96 除湿机+空调含制冷剂 | E6: FB4 | F6: 入库操作费-DE | G6: 947270 | H6: 2026-03-31 17:38:38 | I6: 0 | J6: 10762.26 | K6: VSE-ADD12-EU | L6: 240 | M6: 入库操作费 | N6: 入库操作费 | O6: EUR | P6: 348 | Q6: 0 | R6: 300 | S6: 0 | T6: 300 | U6: 个 | V6: 12.5 | W6: 德国法兰克福2仓 | Z6: 入库操作费-F230DE-250327（公布价）-3 | AC6: DE | AD6: 65462C | AE6: 65462C | AF6: PZ_国际 | AG6: DEFRAB德国法兰克福2仓 | AM6: Desumidificador AeroDrain D12 | AN6: AeroDrain WiFi除湿机_12L_欧版
A7: IC947270260117132 | B7: SW202601150004DE | C7: SW202601150004DE | D7: VS AMZ28.41+WEB39.96 除湿机+空调含制冷剂 | E7: FB4 | F7: 入库操作费-DE | G7: 947270 | H7: 2026-03-31 17:38:38 | I7: 0 | J7: 10762.26 | K7: VG-Y18B-EU | L7: 50 | M7: 入库操作费 | N7: 入库操作费 | O7: EUR | P7: 120 | Q7: 0 | R7: 103 | S7: 0 | T7: 103 | U7: 个 | V7: 23.55 | W7: 德国法兰克福2仓 | Z7: 入库操作费-F230DE-250327（公布价）-3 | AC7: DE | AD7: 65462C | AE7: 65462C | AF7: PZ_国际 | AG7: DEFRAB德国法兰克福2仓 | AM7: 欧版 VGrow 智能种植箱 | AN7: 欧版 VGrow 智能种植箱
A8: IC947270260117132 | B8: SW202601150004DE | C8: SW202601150004DE | D8: VS AMZ28.41+WEB39.96 除湿机+空调含制冷剂 | E8: FB4 | F8: 入库操作费-DE | G8: 947270 | H8: 2026-03-31 17:38:38 | I8: 0 | J8: 10762.26 | K8: 306146-0412-EU | L8: 300 | M8: 入库操作费 | N8: 入库操作费 | O8: EUR | P8: 90 | Q8: 0 | R8: 78 | S8: 0 | T8: 78 | U8: 个 | V8: 2.826 | W8: 德国法兰克福2仓 | Z8: 入库操作费-F230DE-250327（公布价）-3 | AC8: DE | AD8: 65462C | AE8: 65462C | AF8: PZ_国际 | AG8: DEFRAB德国法兰克福2仓 | AM8: VIVOSUN钢印滤芯 黑色4" | AN8: VIVOSUN钢印滤芯 黑色4"
A9: IC947270260117132 | B9: SW202601150004DE | C9: SW202601150004DE | D9: VS AMZ28.41+WEB39.96 除湿机+空调含制冷剂 | E9: FB4 | F9: 入库操作费-DE | G9: 947270 | H9: 2026-03-31 17:38:38 | I9: 0 | J9: 10762.26 | K9: VSF-AWA6G2X2-EU | L9: 240 | M9: 入库操作费 | N9: 入库操作费 | O9: EUR | P9: 72 | Q9: 0 | R9: 62.4 | S9: 0 | T9: 62.4 | U9: 个 | V9: 2.838 | W9: 德国法兰克福2仓 | Z9: 入库操作费-F230DE-250327（公布价）-3 | AC9: DE | AD9: 65462C | AE9: 65462C | AF9: PZ_国际 | AG9: DEFRAB德国法兰克福2仓 | AM9: 2-Pack AeroWave A6 Gen2 Grow Tent Clip Fan | AN9: 入门款AC电机夹扇A6 Gen2 欧版 两只装
A10: IC947270260117143 | B10: SW202601150003DE | C10: SW202601150003DE | D10: VS Amazon25.39+eBay4.78+Web38.15 除湿机含制冷剂 | E10: FB4 | F10: 入库操作费-DE | G10: 947270 | H10: 2026-03-31 15:23:58 | I10: 0 | J10: 9259.808 | K10: VSF-AWA6G2-EU | L10: 240 | M10: 入库操作费 | N10: 海外仓查验费 | O10: EUR | P10: 2.75 | Q10: 0 | R10: 2.75 | S10: 0 | T10: 2.75 | W10: 德国法兰克福2仓 | Z10: 入库操作费-F230DE-250327（公布价）-3 | AC10: DE | AD10: 65462C | AE10: 65462C | AF10: PZ_国际 | AG10: DEFRAB德国法兰克福2仓 | AM10: Aerowave A6 Gen2 Grow Tent Clip Fan | AN10: 入门款AC电机夹扇A6 Gen2 欧版
A11: IC947270260117143 | B11: SW202601150003DE | C11: SW202601150003DE | D11: VS Amazon25.39+eBay4.78+Web38.15 除湿机含制冷剂 | E11: FB4 | F11: 入库操作费-DE | G11: 947270 | H11: 2026-03-31 15:23:58 | I11: 0 | J11: 9259.808 | M11: 入库操作费 | N11: 入库卸货费 | O11: EUR | P11: 317.89 | Q11: 0 | R11: 317.89 | S11: 0 | T11: 317.89 | U11: mums.measurement_info.code.CBM | V11: 61.13187 | W11: 德国法兰克福2仓 | Z11: 入库操作费-F230DE-250327（公布价）-3 | AC11: DE | AD11: 65462C | AE11: 65462C | AF11: PZ_国际 | AG11: DEFRAB德国法兰克福2仓
A12: IC947270260117143 | B12: SW202601150003DE | C12: SW202601150003DE | D12: VS Amazon25.39+eBay4.78+Web38.15 除湿机含制冷剂 | E12: FB4 | F12: 入库操作费-DE | G12: 947270 | H12: 2026-03-31 15:23:58 | I12: 0 | J12: 9259.808 | K12: VSL-LRUC100-EU | L12: 96 | M12: 入库操作费 | N12: 入库操作费 | O12: EUR | P12: 28.8 | Q12: 0 | R12: 24.96 | S12: 0 | T12: 24.96 | U12: 个 | V12: 2.9 | W12: 德国法兰克福2仓 | Z12: 入库操作费-F230DE-250327（公布价）-3 | AC12: DE | AD12: 65462C | AE12: 65462C | AF12: PZ_国际 | AG12: DEFRAB德国法兰克福2仓 | AM12: Supplemental light LumaRay-under canopy 100W-EU | AN12: Supplemental light LumaRay-under canopy 100W-EU
A13: IC947270260117143 | B13: SW202601150003DE | C13: SW202601150003DE | D13: VS Amazon25.39+eBay4.78+Web38.15 除湿机含制冷剂 | E13: FB4 | F13: 入库操作费-DE | G13: 947270 | H13: 2026-03-31 15:23:58 | I13: 0 | J13: 9259.808 | K13: VG-Y18B-EU | L13: 25 | M13: 入库操作费 | N13: 入库操作费 | O13: EUR | P13: 60 | Q13: 0 | R13: 51.5 | S13: 0 | T13: 51.5 | U13: 个 | V13: 23.55 | W13: 德国法兰克福2仓 | Z13: 入库操作费-F230DE-250327（公布价）-3 | AC13: DE | AD13: 65462C | AE13: 65462C | AF13: PZ_国际 | AG13: DEFRAB德国法兰克福2仓 | AM13: 欧版 VGrow 智能种植箱 | AN13: 欧版 VGrow 智能种植箱
A14: IC947270260117143 | B14: SW202601150003DE | C14: SW202601150003DE | D14: VS Amazon25.39+eBay4.78+Web38.15 除湿机含制冷剂 | E14: FB4 | F14: 入库操作费-DE | G14: 947270 | H14: 2026-03-31 15:23:58 | I14: 0 | J14: 9259.808 | K14: VSVC-AZT6E42AP-EU | L14: 25 | M14: 入库操作费 | N14: 入库操作费 | O14: EUR | P14: 23.5 | Q14: 0 | R14: 20.25 | S14: 0 | T14: 20.25 | U14: 个 | V14: 10 | W14: 德国法兰克福2仓 | Z14: 入库操作费-F230DE-250327（公布价）-3 | AC14: DE | AD14: 65462C | AE14: 65462C | AF14: PZ_国际 | AG14: DEFRAB德国法兰克福2仓 | AM14: Smart Air Filtration Kit Pro 6″ | AN14: AeroZesh T6 金属底座风机 6寸 + GrowHub E42A+控制器+黑色滤芯6寸+黑色风管6寸8ft 欧版
A15: IC947270260117143 | B15: SW202601150003DE | C15: SW202601150003DE | D15: VS Amazon25.39+eBay4.78+Web38.15 除湿机含制冷剂 | E15: FB4 | F15: 入库操作费-DE | G15: 947270 | H15: 2026-03-31 15:23:58 | I15: 0 | J15: 9259.808 | K15: VSF-AWD4X2-EU | L15: 432 | M15: 入库操作费 | N15: 入库操作费 | O15: EUR | P15: 116.64 | Q15: 0 | R15: 99.36 | S15: 0 | T15: 99.36 | U15: 个 | V15: 0.61 | W15: 德国法兰克福2仓 | Z15: 入库操作费-F230DE-250327（公布价）-3 | AC15: DE | AD15: 65462C | AE15: 65462C | AF15: PZ_国际 | AG15: DEFRAB德国法兰克福2仓 | AM15: AeroWave D4, 4” Grow Tent Clip Fan with Detachable Hook
A16: IC947270260117143 | B16: SW202601150003DE | C16: SW202601150003DE | D16: VS Amazon25.39+eBay4.78+Web38.15 除湿机含制冷剂 | E16: FB4 | F16: 入库操作费-DE | G16: 947270 | H16: 2026-03-31 15:23:58 | I16: 0 | J16: 9259.808 | K16: VSE-ATW70-EU | L16: 72 | M16: 入库操作费 | N16: 入库操作费 | O16: EUR | P16: 34.56 | Q16: 0 | R16: 29.52 | S16: 0 | T16: 29.52 | U16: 个 | V16: 3.216 | W16: 德国法兰克福2仓 | Z16: 入库操作费-F230DE-250327（公布价）-3 | AC16: DE | AD16: 65462C | AE16: 65462C | AF16: PZ_国际 | AG16: DEFRAB德国法兰克福2仓 | AM16: AeroFlux Heater 70w | AN16: AeroFlux Heater 70w
A17: IC947270260117143 | B17: SW202601150003DE | C17: SW202601150003DE | D17: VS Amazon25.39+eBay4.78+Web38.15 除湿机含制冷剂 | E17: FB4 | F17: 入库操作费-DE | G17: 947270 | H17: 2026-03-31 15:23:58 | I17: 0 | J17: 9259.808 | K17: VSF-AWA6G2-EU | L17: 240 | M17: 入库操作费 | N17: 入库操作费 | O17: EUR | P17: 72 | Q17: 0 | R17: 62.4 | S17: 0 | T17: 62.4 | U17: 个 | V17: 1.468 | W17: 德国法兰克福2仓 | Z17: 入库操作费-F230DE-250327（公布价）-3 | AC17: DE | AD17: 65462C | AE17: 65462C | AF17: PZ_国际 | AG17: DEFRAB德国法兰克福2仓 | AM17: Aerowave A6 Gen2 Grow Tent Clip Fan | AN17: 入门款AC电机夹扇A6 Gen2 欧版
A18: IC947270260117143 | B18: SW202601150003DE | C18: SW202601150003DE | D18: VS Amazon25.39+eBay4.78+Web38.15 除湿机含制冷剂 | E18: FB4 | F18: 入库操作费-DE | G18: 947270 | H18: 2026-03-31 15:23:58 | I18: 0 | J18: 9259.808 | K18: VSVC-AZG4E42AP-EU | L18: 36 | M18: 入库操作费 | N18: 入库操作费 | O18: EUR | P18: 33.84 | Q18: 0 | R18: 29.16 | S18: 0 | T18: 29.16 | U18: 个 | V18: 7 | W18: 德国法兰克福2仓 | Z18: 入库操作费-F230DE-250327（公布价）-3 | AC18: DE | AD18: 65462C | AE18: 65462C | AF18: PZ_国际 | AG18: DEFRAB德国法兰克福2仓 | AM18: Smart Air Filtration PRO G4 Kit 4" | AN18: AeroZesh G4 金属底座风机 4寸 + GrowHub E42A+控制器+黑色滤芯4寸+黑色风管4寸8ft 欧版
A19: IC947270260117143 | B19: SW202601150003DE | C19: SW202601150003DE | D19: VS Amazon25.39+eBay4.78+Web38.15 除湿机含制冷剂 | E19: FB4 | F19: 入库操作费-DE | G19: 947270 | H19: 2026-03-31 15:23:58 | I19: 0 | J19: 9259.808 | K19: VSF-AWE6-G2-EU | L19: 336 | M19: 入库操作费 | N19: 入库操作费 | O19: EUR | P19: 100.8 | Q19: 0 | R19: 87.36 | S19: 0 | T19: 87.36 | U19: 个 | V19: 1.1 | W19: 德国法兰克福2仓 | Z19: 入库操作费-F230DE-250327（公布价）-3 | AC19: DE | AD19: 65462C | AE19: 65462C | AF19: PZ_国际 | AG19: DEFRAB德国法兰克福2仓 | AM19: AeroWave E6 Grow Tent Fan 6”
A20: IC947270260117143 | B20: SW202601150003DE | C20: SW202601150003DE | D20: VS Amazon25.39+eBay4.78+Web38.15 除湿机含制冷剂 | E20: FB4 | F20: 入库操作费-DE | G20: 947270 | H20: 2026-03-31 15:23:58 | I20: 0 | J20: 9259.808 | K20: 304113-52-EU | L20: 32 | M20: 入库操作费 | N20: 入库操作费 | O20: EUR | P20: 46.4 | Q20: 0 | R20: 40 | S20: 0 | T20: 40 | U20: 个 | V20: 11.821 | W20: 德国法兰克福2仓 | Z20: 入库操作费-F230DE-250327（公布价）-3 | AC20: DE | AD20: 65462C | AE20: 65462C | AF20: PZ_国际 | AG20: DEFRAB德国法兰克福2仓 | AM20: 52帐篷-60"x32"x80"/150*80*200cm 16mm管径 | AN20: 52帐篷-60"x32"x80"/150*80*200cm 16mm管径
A21: IC947270260117143 | B21: SW202601150003DE | C21: SW202601150003DE | D21: VS Amazon25.39+eBay4.78+Web38.15 除湿机含制冷剂 | E21: FB4 | F21: 入库操作费-DE | G21: 947270 | H21: 2026-03-31 15:23:58 | I21: 0 | J21: 9259.808 | K21: E331903J-EU | L21: 36 | M21: 入库操作费 | N21: 入库操作费 | O21: EUR | P21: 33.84 | Q21: 0 | R21: 29.16 | S21: 0 | T21: 29.16 | U21: 个 | V21: 6.262 | W21: 德国法兰克福2仓 | Z21: 入库操作费-F230DE-250327（公布价）-3 | AC21: DE | AD21: 65462C | AE21: 65462C | AF21: PZ_国际 | AG21: DEFRAB德国法兰克福2仓 | AM21: E331903J || New lawn mower 16" (with orange flower trimmer) | AN21: E331903J||新款 割草机16"（带橘色花枝剪）
A22: IC947270260117143 | B22: SW202601150003DE | C22: SW202601150003DE | D22: VS Amazon25.39+eBay4.78+Web38.15 除湿机含制冷剂 | E22: FB4 | F22: 入库操作费-DE | G22: 947270 | H22: 2026-03-31 15:23:58 | I22: 0 | J22: 9259.808 | K22: VSK-GIYS336-EU | L22: 20 | M22: 入库操作费 | N22: 入库操作费 | O22: EUR | P22: 48 | Q22: 0 | R22: 41.2 | S22: 0 | T22: 41.2 | U22: 个 | V22: 23 | W22: 德国法兰克福2仓 | Z22: 入库操作费-F230DE-250327（公布价）-3 | AC22: DE | AD22: 65462C | AE22: 65462C | AF22: PZ_国际 | AG22: DEFRAB德国法兰克福2仓 | AM22: Smart Grow Tent Kit GIY-SE-33 3x3, 3-Plant Complete System | AN22: GIY SGS智能标准款帐篷套装S336欧版
A23: IC947270260117143 | B23: SW202601150003DE | C23: SW202601150003DE | D23: VS Amazon25.39+eBay4.78+Web38.15 除湿机含制冷剂 | E23: FB4 | F23: 入库操作费-DE | G23: 947270 | H23: 2026-03-31 15:23:58 | I23: 0 | J23: 9259.808 | K23: VSE-ASH05-EU | L23: 120 | M23: 入库操作费 | N23: 入库操作费 | O23: EUR | P23: 36 | Q23: 0 | R23: 31.2 | S23: 0 | T23: 31.2 | U23: 个 | V23: 1.954 | W23: 德国法兰克福2仓 | Z23: 入库操作费-F230DE-250327（公布价）-3 | AC23: DE | AD23: 65462C | AE23: 65462C | AF23: PZ_国际 | AG23: DEFRAB德国法兰克福2仓 | AM23: AeroStream Humidificateur pour plantes 5 l | AN23: AeroStream 5L智能Wi-Fi加湿器（SGS，单核雾化片）-欧版
A24: IC947270260117143 | B24: SW202601150003DE | C24: SW202601150003DE | D24: VS Amazon25.39+eBay4.78+Web38.15 除湿机含制冷剂 | E24: FB4 | F24: 入库操作费-DE | G24: 947270 | H24: 2026-03-31 15:23:58 | I24: 0 | J24: 9259.808 | K24: VSE-ASH09-EU | L24: 168 | M24: 入库操作费 | N24: 入库操作费 | O24: EUR | P24: 80.64 | Q24: 0 | R24: 68.88 | S24: 0 | T24: 68.88 | U24: 个 | V24: 3.346 | W24: 德国法兰克福2仓 | Z24: 入库操作费-F230DE-250327（公布价）-3 | AC24: DE | AD24: 65462C | AE24: 65462C | AF24: PZ_国际 | AG24: DEFRAB德国法兰克福2仓 | AM24: AeroStream - Humidificador para plantas (9 L) | AN24: AeroStream 9L智能Wi-Fi加湿器（SGS，单核雾化片）-欧版
A25: IC947270260117143 | B25: SW202601150003DE | C25: SW202601150003DE | D25: VS Amazon25.39+eBay4.78+Web38.15 除湿机含制冷剂 | E25: FB4 | F25: 入库操作费-DE | G25: 947270 | H25: 2026-03-31 15:23:58 | I25: 0 | J25: 9259.808 | K25: VSI-FFSW6-4-EU | L25: 120 | M25: 入库操作费 | N25: 入库操作费 | O25: EUR | P25: 57.6 | Q25: 0 | R25: 49.2 | S25: 0 | T25: 49.2 | U25: 个 | V25: 4.72 | W25: 德国法兰克福2仓 | Z25: 入库操作费-F230DE-250327（公布价）-3 | AC25: DE | AD25: 65462C | AE25: 65462C | AF25: PZ_国际 | AG25: DEFRAB德国法兰克福2仓 | AM25: 4-Pack FlexFeed Self-Watering Irrigation Pot
A26: IC947270260117143 | B26: SW202601150003DE | C26: SW202601150003DE | D26: VS Amazon25.39+eBay4.78+Web38.15 除湿机含制冷剂 | E26: FB4 | F26: 入库操作费-DE | G26: 947270 | H26: 2026-03-31 15:23:58 | I26: 0 | J26: 9259.808 | K26: VST-SP2-GL-EU | L26: 200 | M26: 入库操作费 | N26: 入库操作费 | O26: EUR | P26: 60 | Q26: 0 | R26: 52 | S26: 0 | T26: 52 | U26: 个 | V26: 2.014 | W26: 德国法兰克福2仓 | Z26: 入库操作费-F230DE-250327（公布价）-3 | AC26: DE | AD26: 65462C | AE26: 65462C | AF26: PZ_国际 | AG26: DEFRAB德国法兰克福2仓 | AM26: Grow Tent High CFM Kit 100-150cm | AN26: 帐篷伸缩支撑杆100-150cm
A27: IC947270260117143 | B27: SW202601150003DE | C27: SW202601150003DE | D27: VS Amazon25.39+eBay4.78+Web38.15 除湿机含制冷剂 | E27: FB4 | F27: 入库操作费-DE | G27: 947270 | H27: 2026-03-31 15:23:58 | I27: 0 | J27: 9259.808 | K27: VSFL6450-EU | L27: 15 | M27: 入库操作费 | N27: 入库操作费 | O27: EUR | P27: 14.1 | Q27: 0 | R27: 12.15 | S27: 0 | T27: 12.15 | U27: 个 | V27: 10 | W27: 德国法兰克福2仓 | Z27: 入库操作费-F230DE-250327（公布价）-3 | AC27: DE | AD27: 65462C | AE27: 65462C | AF27: PZ_国际 | AG27: DEFRAB德国法兰克福2仓 | AM27: LED Grow Light
A28: IC947270260117143 | B28: SW202601150003DE | C28: SW202601150003DE | D28: VS Amazon25.39+eBay4.78+Web38.15 除湿机含制冷剂 | E28: FB4 | F28: 入库操作费-DE | G28: 947270 | H28: 2026-03-31 15:23:58 | I28: 0 | J28: 9259.808 | K28: VSEX-HID1-ST-EU | L28: 88 | M28: 入库操作费 | N28: 入库操作费 | O28: EUR | P28: 42.24 | Q28: 0 | R28: 36.08 | S28: 0 | T28: 36.08 | U28: 个 | V28: 3.812 | W28: 德国法兰克福2仓 | Z28: 入库操作费-F230DE-250327（公布价）-3 | AC28: DE | AD28: 65462C | AE28: 65462C | AF28: PZ_国际 | AG28: DEFRAB德国法兰克福2仓 | AM28: Herbal Decarboxylation and Infusion Machine | AN28: S4508B 黄油机套装-欧版
A29: IC947270260117143 | B29: SW202601150003DE | C29: SW202601150003DE | D29: VS Amazon25.39+eBay4.78+Web38.15 除湿机含制冷剂 | E29: FB4 | F29: 入库操作费-DE | G29: 947270 | H29: 2026-03-31 15:23:58 | I29: 0 | J29: 9259.808 | K29: VSE-ADD12-EU | L29: 50 | M29: 入库操作费 | N29: 入库操作费 | O29: EUR | P29: 72.5 | Q29: 0 | R29: 62.5 | S29: 0 | T29: 62.5 | U29: 个 | V29: 12.5 | W29: 德国法兰克福2仓 | Z29: 入库操作费-F230DE-250327（公布价）-3 | AC29: DE | AD29: 65462C | AE29: 65462C | AF29: PZ_国际 | AG29: DEFRAB德国法兰克福2仓 | AM29: Desumidificador AeroDrain D12 | AN29: AeroDrain WiFi除湿机_12L_欧版
A30: IC947270260117143 | B30: SW202601150003DE | C30: SW202601150003DE | D30: VS Amazon25.39+eBay4.78+Web38.15 除湿机含制冷剂 | E30: FB4 | F30: 入库操作费-DE | G30: 947270 | H30: 2026-03-31 15:23:58 | I30: 0 | J30: 9259.808 | K30: VSK-GIYS448-EU | L30: 18 | M30: 入库操作费 | N30: 入库操作费 | O30: EUR | P30: 55.08 | Q30: 0 | R30: 47.34 | S30: 0 | T30: 47.34 | U30: 个 | V30: 33 | W30: 德国法兰克福2仓 | Z30: 入库操作费-F230DE-250327（公布价）-3 | AC30: DE | AD30: 65462C | AE30: 65462C | AF30: PZ_国际 | AG30: DEFRAB德国法兰克福2仓 | AM30: Smart Grow Tent Kit GIY-SE-44 4x4, 4-Plant Complete System | AN30: GIY SGS智能标准款帐篷套装S448欧版
A31: IC947270260117143 | B31: SW202601150003DE | C31: SW202601150003DE | D31: VS Amazon25.39+eBay4.78+Web38.15 除湿机含制冷剂 | E31: FB4 | F31: 入库操作费-DE | G31: 947270 | H31: 2026-03-31 15:23:58 | I31: 0 | J31: 9259.808 | K31: VSI-VGDWC15-EU | L31: 60 | M31: 入库操作费 | N31: 入库操作费 | O31: EUR | P31: 28.8 | Q31: 0 | R31: 24.6 | S31: 0 | T31: 24.6 | U31: 个 | V31: 5 | W31: 德国法兰克福2仓 | Z31: 入库操作费-F230DE-250327（公布价）-3 | AC31: DE | AD31: 65462C | AE31: 65462C | AF31: PZ_国际 | AG31: DEFRAB德国法兰克福2仓 | AM31: VGrow DWC Hydroponics Growing System Kit for VGrow Smart Grow Box | AN31: VGrow DWC水培套装 4加仑
A32: IC947270260117143 | B32: SW202601150003DE | C32: SW202601150003DE | D32: VS Amazon25.39+eBay4.78+Web38.15 除湿机含制冷剂 | E32: FB4 | F32: 入库操作费-DE | G32: 947270 | H32: 2026-03-31 15:23:58 | I32: 0 | J32: 9259.808 | K32: SST-1-0001-EU | L32: 120 | M32: 入库操作费 | N32: 入库操作费 | O32: EUR | P32: 36 | Q32: 0 | R32: 31.2 | S32: 0 | T32: 31.2 | U32: 个 | V32: 1.13 | W32: 德国法兰克福2仓 | Z32: 入库操作费-F230DE-250327（公布价）-3 | AC32: DE | AD32: 65462C | AE32: 65462C | AF32: PZ_国际 | AG32: DEFRAB德国法兰克福2仓 | AM32: 1-Pack 40-Cell Seed Starter Trays with 1 Set of LED Lights and 10"x20.75" Seedling Heat Mat | AN32: 欧规 40孔育苗盘1套装+LED灯条1套+加热垫1套
A33: IC947270260117143 | B33: SW202601150003DE | C33: SW202601150003DE | D33: VS Amazon25.39+eBay4.78+Web38.15 除湿机含制冷剂 | E33: FB4 | F33: 入库操作费-DE | G33: 947270 | H33: 2026-03-31 15:23:58 | I33: 0 | J33: 9259.808 | K33: E331904J-EU | L33: 30 | M33: 入库操作费 | N33: 入库操作费 | O33: EUR | P33: 28.2 | Q33: 0 | R33: 24.3 | S33: 0 | T33: 24.3 | U33: 个 | V33: 7.25 | W33: 德国法兰克福2仓 | Z33: 入库操作费-F230DE-250327（公布价）-3 | AC33: DE | AD33: 65462C | AE33: 65462C | AF33: PZ_国际 | AG33: DEFRAB德国法兰克福2仓 | AM33: E331904J || New lawn mower 19" (with orange flower trimmer) | AN33: E331904J||新款 割草机19"（带橘色花枝剪）
A34: IC947270260117143 | B34: SW202601150003DE | C34: SW202601150003DE | D34: VS Amazon25.39+eBay4.78+Web38.15 除湿机含制冷剂 | E34: FB4 | F34: 入库操作费-DE | G34: 947270 | H34: 2026-03-31 15:23:58 | I34: 0 | J34: 9259.808 | K34: 304113-P426-EU | L34: 40 | M34: 入库操作费 | N34: 入库操作费 | O34: EUR | P34: 58 | Q34: 0 | R34: 50 | S34: 0 | T34: 50 | U34: 个 | V34: 15 | W34: 德国法兰克福2仓 | Z34: 入库操作费-F230DE-250327（公布价）-3 | AC34: DE | AD34: 65462C | AE34: 65462C | AF34: PZ_国际 | AG34: DEFRAB德国法兰克福2仓 | AM34: P426 48"×24"×72" PRO Grow Tent | AN34: P426 Pro款42帐篷-48"x24"x72"/120*60*180cm 22mm管径
A35: IC947270260117143 | B35: SW202601150003DE | C35: SW202601150003DE | D35: VS Amazon25.39+eBay4.78+Web38.15 除湿机含制冷剂 | E35: FB4 | F35: 入库操作费-DE | G35: 947270 | H35: 2026-03-31 15:23:58 | I35: 0 | J35: 9259.808 | K35: 304113-P448-EU | L35: 20 | M35: 入库操作费 | N35: 入库操作费 | O35: EUR | P35: 38.6 | Q35: 0 | R35: 33.2 | S35: 0 | T35: 33.2 | U35: 个 | V35: 20 | W35: 德国法兰克福2仓 | Z35: 入库操作费-F230DE-250327（公布价）-3 | AC35: DE | AD35: 65462C | AE35: 65462C | AF35: PZ_国际 | AG35: DEFRAB德国法兰克福2仓 | AM35: P448 48"×48"×80" PRO Grow Tent | AN35: P448 Pro款44帐篷-48"x48"x80"/120*120*200cm 22mm管径
A36: IC947270260117143 | B36: SW202601150003DE | C36: SW202601150003DE | D36: VS Amazon25.39+eBay4.78+Web38.15 除湿机含制冷剂 | E36: FB4 | F36: 入库操作费-DE | G36: 947270 | H36: 2026-03-31 15:23:58 | I36: 0 | J36: 9259.808 | K36: VSVC-AZT4E42AP-EU | L36: 45 | M36: 入库操作费 | N36: 入库操作费 | O36: EUR | P36: 42.3 | Q36: 0 | R36: 36.45 | S36: 0 | T36: 36.45 | U36: 个 | V36: 6.5 | W36: 德国法兰克福2仓 | Z36: 入库操作费-F230DE-250327（公布价）-3 | AC36: DE | AD36: 65462C | AE36: 65462C | AF36: PZ_国际 | AG36: DEFRAB德国法兰克福2仓 | AM36: Smart Air Filtration PRO T4 Kit 4" | AN36: AeroZesh T4 金属底座风机 4寸 + GrowHub E42A+控制器+黑色滤芯4寸+黑色风管4寸8ft 欧版
A37: IC947270260117143 | B37: SW202601150003DE | C37: SW202601150003DE | D37: VS Amazon25.39+eBay4.78+Web38.15 除湿机含制冷剂 | E37: FB4 | F37: 入库操作费-DE | G37: 947270 | H37: 2026-03-31 15:23:58 | I37: 0 | J37: 9259.808 | K37: 304113-P558-EU | L37: 12 | M37: 入库操作费 | N37: 入库操作费 | O37: EUR | P37: 28.8 | Q37: 0 | R37: 24.72 | S37: 0 | T37: 24.72 | U37: 个 | V37: 24 | W37: 德国法兰克福2仓 | Z37: 入库操作费-F230DE-250327（公布价）-3 | AC37: DE | AD37: 65462C | AE37: 65462C | AF37: PZ_国际 | AG37: DEFRAB德国法兰克福2仓 | AM37: P558 60"×60"×80" PRO Grow Tent | AN37: P558 Pro款55帐篷-60"x60"x80"/150*150*200cm 22mm管径
A38: IC947270260117155 | B38: SW202601150006DE | C38: SW202601150006DE | D38: VS Amazon+eBay+Web 58.5方 11354KG 1519箱 测试笔+喷雾器+滴灌套装 含电 除湿机含制冷剂 | E38: FB4 | F38: 入库操作费-DE | G38: 947270 | H38: 2026-04-15 20:24:26 | I38: 0 | J38: 8440.56 | K38: VSL-LL100X2-EU,VSV-IFP4C-EU,VSV-IFP6C-EU | L38: 20,160,48 | M38: 入库操作费 | N38: 海外仓查验费 | O38: EUR | P38: 8.25 | Q38: 0 | R38: 8.25 | S38: 0 | T38: 8.25 | W38: 德国法兰克福2仓 | Z38: 入库操作费-F230DE_260410（公布价)-2 | AC38: DE | AD38: 65462C | AE38: 65462C | AF38: PZ_国际 | AG38: DEFRAB德国法兰克福2仓 | AI38: 是 | AM38: Lumalight Grow Light 100Wx2,Plastic exhaust fan with adjustable speed 4 inch,Plastic exhaust fan with adjustable speed 6 inch | AN38: VS-lumalight-量子版2025-100W-两只装-EU,P4 塑料抽风扇调速款单品-欧标,P6 塑料抽风扇调速款单品-欧标
A39: IC947270260117155 | B39: SW202601150006DE | C39: SW202601150006DE | D39: VS Amazon+eBay+Web 58.5方 11354KG 1519箱 测试笔+喷雾器+滴灌套装 含电 除湿机含制冷剂 | E39: FB4 | F39: 入库操作费-DE | G39: 947270 | H39: 2026-04-15 20:24:26 | I39: 0 | J39: 8440.56 | K39: 330101CNJ-EU | L39: 120 | M39: 入库操作费 | N39: 入库操作费 | O39: EUR | P39: 33.6 | Q39: 0 | R39: 28.8 | S39: 0 | T39: 28.8 | U39: 个 | V39: 0.85 | W39: 德国法兰克福2仓 | Z39: 入库操作费-F230DE_260410（公布价)-2 | AC39: DE | AD39: 65462C | AE39: 65462C | AF39: PZ_国际 | AG39: DEFRAB德国法兰克福2仓 | AI39: 是 | AM39: 10"x 20.75" Seedling Heat Mat and Digital Thermostat Combo Set | AN39: 欧规 恒温器+育苗垫组合10*20
A40: IC947270260117155 | B40: SW202601150006DE | C40: SW202601150006DE | D40: VS Amazon+eBay+Web 58.5方 11354KG 1519箱 测试笔+喷雾器+滴灌套装 含电 除湿机含制冷剂 | E40: FB4 | F40: 入库操作费-DE | G40: 947270 | H40: 2026-04-15 20:24:26 | I40: 0 | J40: 8440.56 | K40: VSL-LRUC100-EU | L40: 92 | M40: 入库操作费 | N40: 入库操作费 | O40: EUR | P40: 30.36 | Q40: 0 | R40: 25.76 | S40: 0 | T40: 25.76 | U40: 个 | V40: 2.9 | W40: 德国法兰克福2仓 | Z40: 入库操作费-F230DE_260410（公布价)-2 | AC40: DE | AD40: 65462C | AE40: 65462C | AF40: PZ_国际 | AG40: DEFRAB德国法兰克福2仓 | AI40: 是 | AM40: Supplemental light LumaRay-under canopy 100W-EU | AN40: Supplemental light LumaRay-under canopy 100W-EU
A41: IC947270260117155 | B41: SW202601150006DE | C41: SW202601150006DE | D41: VS Amazon+eBay+Web 58.5方 11354KG 1519箱 测试笔+喷雾器+滴灌套装 含电 除湿机含制冷剂 | E41: FB4 | F41: 入库操作费-DE | G41: 947270 | H41: 2026-04-15 20:24:26 | I41: 0 | J41: 8440.56 | K41: VSV-AZG6-EU | L41: 12 | M41: 入库操作费 | N41: 入库操作费 | O41: EUR | P41: 6 | Q41: 0 | R41: 5.16 | S41: 0 | T41: 5.16 | U41: 个 | V41: 3.318 | W41: 德国法兰克福2仓 | Z41: 入库操作费-F230DE_260410（公布价)-2 | AC41: DE | AD41: 65462C | AE41: 65462C | AF41: PZ_国际 | AG41: DEFRAB德国法兰克福2仓 | AI41: 是 | AM41: AeroZesh G6金属风机6寸+线控 | AN41: AeroZesh G6金属风机6寸+线控
A42: IC947270260117155 | B42: SW202601150006DE | C42: SW202601150006DE | D42: VS Amazon+eBay+Web 58.5方 11354KG 1519箱 测试笔+喷雾器+滴灌套装 含电 除湿机含制冷剂 | E42: FB4 | F42: 入库操作费-DE | G42: 947270 | H42: 2026-04-15 20:24:26 | I42: 0 | J42: 8440.56 | K42: VSVC-AZT6E42AP-EU | L42: 12 | M42: 入库操作费 | N42: 入库操作费 | O42: EUR | P42: 11.28 | Q42: 0 | R42: 9.72 | S42: 0 | T42: 9.72 | U42: 个 | V42: 10 | W42: 德国法兰克福2仓 | Z42: 入库操作费-F230DE_260410（公布价)-2 | AC42: DE | AD42: 65462C | AE42: 65462C | AF42: PZ_国际 | AG42: DEFRAB德国法兰克福2仓 | AI42: 是 | AM42: Smart Air Filtration Kit Pro 6″ | AN42: AeroZesh T6 金属底座风机 6寸 + GrowHub E42A+控制器+黑色滤芯6寸+黑色风管6寸8ft 欧版
A43: IC947270260117155 | B43: SW202601150006DE | C43: SW202601150006DE | D43: VS Amazon+eBay+Web 58.5方 11354KG 1519箱 测试笔+喷雾器+滴灌套装 含电 除湿机含制冷剂 | E43: FB4 | F43: 入库操作费-DE | G43: 947270 | H43: 2026-04-15 20:24:26 | I43: 0 | J43: 8440.56 | K43: VSL-LL100X2-EU | L43: 20 | M43: 入库操作费 | N43: 入库操作费 | O43: EUR | P43: 18.8 | Q43: 0 | R43: 16.2 | S43: 0 | T43: 16.2 | U43: 个 | V43: 5.522 | W43: 德国法兰克福2仓 | Z43: 入库操作费-F230DE_260410（公布价)-2 | AC43: DE | AD43: 65462C | AE43: 65462C | AF43: PZ_国际 | AG43: DEFRAB德国法兰克福2仓 | AI43: 是 | AM43: Lumalight Grow Light 100Wx2 | AN43: VS-lumalight-量子版2025-100W-两只装-EU
A44: IC947270260117155 | B44: SW202601150006DE | C44: SW202601150006DE | D44: VS Amazon+eBay+Web 58.5方 11354KG 1519箱 测试笔+喷雾器+滴灌套装 含电 除湿机含制冷剂 | E44: FB4 | F44: 入库操作费-DE | G44: 947270 | H44: 2026-04-15 20:24:26 | I44: 0 | J44: 8440.56 | K44: VSVC-AZT4-EU | L44: 10 | M44: 入库操作费 | N44: 入库操作费 | O44: EUR | P44: 9.4 | Q44: 0 | R44: 8.1 | S44: 0 | T44: 8.1 | U44: 个 | V44: 6.005 | W44: 德国法兰克福2仓 | Z44: 入库操作费-F230DE_260410（公布价)-2 | AC44: DE | AD44: 65462C | AE44: 65462C | AF44: PZ_国际 | AG44: DEFRAB德国法兰克福2仓 | AI44: 是 | AM44: Smart Air Filtration T4 Kit 4"
A45: IC947270260117155 | B45: SW202601150006DE | C45: SW202601150006DE | D45: VS Amazon+eBay+Web 58.5方 11354KG 1519箱 测试笔+喷雾器+滴灌套装 含电 除湿机含制冷剂 | E45: FB4 | F45: 入库操作费-DE | G45: 947270 | H45: 2026-04-15 20:24:26 | I45: 0 | J45: 8440.56 | K45: 311001-5X5-EU | L45: 220 | M45: 入库操作费 | N45: 入库操作费 | O45: EUR | P45: 61.6 | Q45: 0 | R45: 52.8 | S45: 0 | T45: 52.8 | U45: 个 | V45: 0.65 | W45: 德国法兰克福2仓 | Z45: 入库操作费-F230DE_260410（公布价)-2 | AC45: DE | AD45: 65462C | AE45: 65462C | AF45: PZ_国际 | AG45: DEFRAB德国法兰克福2仓 | AI45: 是 | AM45: 5 gallon Grow Bags | AN45: 5加仑黑色种植袋 5个一卖
A46: IC947270260117155 | B46: SW202601150006DE | C46: SW202601150006DE | D46: VS Amazon+eBay+Web 58.5方 11354KG 1519箱 测试笔+喷雾器+滴灌套装 含电 除湿机含制冷剂 | E46: FB4 | F46: 入库操作费-DE | G46: 947270 | H46: 2026-04-15 20:24:26 | I46: 0 | J46: 8440.56 | K46: VSVC-AZG6-EU | L46: 17 | M46: 入库操作费 | N46: 入库操作费 | O46: EUR | P46: 15.98 | Q46: 0 | R46: 13.77 | S46: 0 | T46: 13.77 | U46: 个 | V46: 9 | W46: 德国法兰克福2仓 | Z46: 入库操作费-F230DE_260410（公布价)-2 | AC46: DE | AD46: 65462C | AE46: 65462C | AF46: PZ_国际 | AG46: DEFRAB德国法兰克福2仓 | AI46: 是 | AM46: Smart Air Filtration G6 Kit 6"
A47: IC947270260117155 | B47: SW202601150006DE | C47: SW202601150006DE | D47: VS Amazon+eBay+Web 58.5方 11354KG 1519箱 测试笔+喷雾器+滴灌套装 含电 除湿机含制冷剂 | E47: FB4 | F47: 入库操作费-DE | G47: 947270 | H47: 2026-04-15 20:24:26 | I47: 0 | J47: 8440.56 | K47: VGS-CF10-2-EU | L47: 60 | M47: 入库操作费 | N47: 入库操作费 | O47: EUR | P47: 13.8 | Q47: 0 | R47: 12 | S47: 0 | T47: 12 | U47: 个 | V47: 0.34 | W47: 德国法兰克福2仓 | Z47: 入库操作费-F230DE_260410（公布价)-2 | AC47: DE | AD47: 65462C | AE47: 65462C | AF47: PZ_国际 | AG47: DEFRAB德国法兰克福2仓 | AI47: 是 | AM47: Filter Replacement | AN47: Y18 替换滤芯 2只装
A48: IC947270260117155 | B48: SW202601150006DE | C48: SW202601150006DE | D48: VS Amazon+eBay+Web 58.5方 11354KG 1519箱 测试笔+喷雾器+滴灌套装 含电 除湿机含制冷剂 | E48: FB4 | F48: 入库操作费-DE | G48: 947270 | H48: 2026-04-15 20:24:26 | I48: 0 | J48: 8440.56 | K48: VSV-AZT6E42AP-EU | L48: 30 | M48: 入库操作费 | N48: 入库操作费 | O48: EUR | P48: 15 | Q48: 0 | R48: 12.9 | S48: 0 | T48: 12.9 | U48: 个 | V48: 3.215 | W48: 德国法兰克福2仓 | Z48: 入库操作费-F230DE_260410（公布价)-2 | AC48: DE | AD48: 65462C | AE48: 65462C | AF48: PZ_国际 | AG48: DEFRAB德国法兰克福2仓 | AI48: 是 | AM48: AeroZesh T6 金属底座风机 6寸 + GrowHub E42A+控制器 欧版 | AN48: AeroZesh T6 金属底座风机 6寸 + GrowHub E42A+控制器 欧版
A49: IC947270260117155 | B49: SW202601150006DE | C49: SW202601150006DE | D49: VS Amazon+eBay+Web 58.5方 11354KG 1519箱 测试笔+喷雾器+滴灌套装 含电 除湿机含制冷剂 | E49: FB4 | F49: 入库操作费-DE | G49: 947270 | H49: 2026-04-15 20:24:26 | I49: 0 | J49: 8440.56 | K49: VSL-LL150-EU | L49: 65 | M49: 入库操作费 | N49: 入库操作费 | O49: EUR | P49: 32.5 | Q49: 0 | R49: 27.95 | S49: 0 | T49: 27.95 | U49: 个 | V49: 3.981 | W49: 德国法兰克福2仓 | Z49: 入库操作费-F230DE_260410（公布价)-2 | AC49: DE | AD49: 65462C | AE49: 65462C | AF49: PZ_国际 | AG49: DEFRAB德国法兰克福2仓 | AI49: 是 | AM49: Vivosun Lumalight LED Grow Light 150W | AN49: VS-lumalight-量子版2025-150W-EU
A50: IC947270260117155 | B50: SW202601150006DE | C50: SW202601150006DE | D50: VS Amazon+eBay+Web 58.5方 11354KG 1519箱 测试笔+喷雾器+滴灌套装 含电 除湿机含制冷剂 | E50: FB4 | F50: 入库操作费-DE | G50: 947270 | H50: 2026-04-15 20:24:26 | I50: 0 | J50: 8440.56 | K50: VSVC-AZT8E42AP-EU | L50: 2 | M50: 入库操作费 | N50: 入库操作费 | O50: EUR | P50: 3.86 | Q50: 0 | R50: 3.32 | S50: 0 | T50: 3.32 | U50: 个 | V50: 16.5 | W50: 德国法兰克福2仓 | Z50: 入库操作费-F230DE_260410（公布价)-2 | AC50: DE | AD50: 65462C | AE50: 65462C | AF50: PZ_国际 | AG50: DEFRAB德国法兰克福2仓 | AI50: 是 | AM50: Smart Air Filtration PRO T8 Kit 8" | AN50: AeroZesh T8 金属底座风机 8寸 + GrowHub E42A+控制器+黑色滤芯8寸+黑色风管8寸25ft 欧版
A51: IC947270260117155 | B51: SW202601150006DE | C51: SW202601150006DE | D51: VS Amazon+eBay+Web 58.5方 11354KG 1519箱 测试笔+喷雾器+滴灌套装 含电 除湿机含制冷剂 | E51: FB4 | F51: 入库操作费-DE | G51: 947270 | H51: 2026-04-15 20:24:26 | I51: 0 | J51: 8440.56 | K51: LH-001-EU | L51: 200 | M51: 入库操作费 | N51: 入库操作费 | O51: EUR | P51: 46 | Q51: 0 | R51: 40 | S51: 0 | T51: 40 | U51: 个 | V51: 0.16 | W51: 德国法兰克福2仓 | Z51: 入库操作费-F230DE_260410（公布价)-2 | AC51: DE | AD51: 65462C | AE51: 65462C | AF51: PZ_国际 | AG51: DEFRAB德国法兰克福2仓 | AI51: 是 | AM51: 1-Pair 1/8 Inch Adjustable Grow Light Hanger, Heavy Duty Rope Hanger with Reinforced Metal Gears, 8Ft
A52: IC947270260117155 | B52: SW202601150006DE | C52: SW202601150006DE | D52: VS Amazon+eBay+Web 58.5方 11354KG 1519箱 测试笔+喷雾器+滴灌套装 含电 除湿机含制冷剂 | E52: FB4 | F52: 入库操作费-DE | G52: 947270 | H52: 2026-04-15 20:24:26 | I52: 0 | J52: 8440.56 | K52: HDR006-EU | L52: 40 | M52: 入库操作费 | N52: 入库操作费 | O52: EUR | P52: 11.2 | Q52: 0 | R52: 9.6 | S52: 0 | T52: 9.6 | U52: 个 | V52: 0.94 | W52: 德国法兰克福2仓 | Z52: 入库操作费-F230DE_260410（公布价)-2 | AC52: DE | AD52: 65462C | AE52: 65462C | AF52: PZ_国际 | AG52: DEFRAB德国法兰克福2仓 | AI52: 是 | AM52: 6-Layer Mesh Drying Rack | AN52: 六层草药晾晒网
A53: IC947270260117155 | B53: SW202601150006DE | C53: SW202601150006DE | D53: VS Amazon+eBay+Web 58.5方 11354KG 1519箱 测试笔+喷雾器+滴灌套装 含电 除湿机含制冷剂 | E53: FB4 | F53: 入库操作费-DE | G53: 947270 | H53: 2026-04-15 20:24:26 | I53: 0 | J53: 8440.56 | K53: VSEX-CGM-BL-EU | L53: 50 | M53: 入库操作费 | N53: 入库操作费 | O53: EUR | P53: 16.5 | Q53: 0 | R53: 14 | S53: 0 | T53: 14 | U53: 个 | V53: 1.362 | W53: 德国法兰克福2仓 | Z53: 入库操作费-F230DE_260410（公布价)-2 | AC53: DE | AD53: 65462C | AE53: 65462C | AF53: PZ_国际 | AG53: DEFRAB德国法兰克福2仓 | AI53: 是 | AM53: Vivosun Gummy Machine | AN53: 糖果机套装 欧规
A54: IC947270260117155 | B54: SW202601150006DE | C54: SW202601150006DE | D54: VS Amazon+eBay+Web 58.5方 11354KG 1519箱 测试笔+喷雾器+滴灌套装 含电 除湿机含制冷剂 | E54: FB4 | F54: 入库操作费-DE | G54: 947270 | H54: 2026-04-15 20:24:26 | I54: 0 | J54: 8440.56 | K54: VSC-GCC4-EU | L54: 648 | M54: 入库操作费 | N54: 入库操作费 | O54: EUR | P54: 149.04 | Q54: 0 | R54: 129.6 | S54: 0 | T54: 129.6 | U54: 个 | V54: 0.262 | W54: 德国法兰克福2仓 | Z54: 入库操作费-F230DE_260410（公布价)-2 | AC54: DE | AD54: 65462C | AE54: 65462C | AF54: PZ_国际 | AG54: DEFRAB德国法兰克福2仓 | AI54: 是 | AM54: GrowCam C4 | AN54: GrowCam 摄像头 400W 2K-欧版
A55: IC947270260117155 | B55: SW202601150006DE | C55: SW202601150006DE | D55: VS Amazon+eBay+Web 58.5方 11354KG 1519箱 测试笔+喷雾器+滴灌套装 含电 除湿机含制冷剂 | E55: FB4 | F55: 入库操作费-DE | G55: 947270 | H55: 2026-04-15 20:24:26 | I55: 0 | J55: 8440.56 | K55: VSVC-AZG8E42AP-EU | L55: 10 | M55: 入库操作费 | N55: 入库操作费 | O55: EUR | P55: 19.3 | Q55: 0 | R55: 16.6 | S55: 0 | T55: 16.6 | U55: 个 | V55: 15.5 | W55: 德国法兰克福2仓 | Z55: 入库操作费-F230DE_260410（公布价)-2 | AC55: DE | AD55: 65462C | AE55: 65462C | AF55: PZ_国际 | AG55: DEFRAB德国法兰克福2仓 | AI55: 是 | AM55: Smart Air Filtration PRO G8 Kit 8" | AN55: AeroZesh G8 金属底座风机 8寸 + GrowHub E42A+控制器+黑色滤芯8寸+黑色风管8寸25ft 欧版
A56: IC947270260117155 | B56: SW202601150006DE | C56: SW202601150006DE | D56: VS Amazon+eBay+Web 58.5方 11354KG 1519箱 测试笔+喷雾器+滴灌套装 含电 除湿机含制冷剂 | E56: FB4 | F56: 入库操作费-DE | G56: 947270 | H56: 2026-04-15 20:24:26 | I56: 0 | J56: 8440.56 | K56: 306146-0820-EU | L56: 10 | M56: 入库操作费 | N56: 入库操作费 | O56: EUR | P56: 9.4 | Q56: 0 | R56: 8.1 | S56: 0 | T56: 8.1 | U56: 个 | V56: 7.51 | W56: 德国法兰克福2仓 | Z56: 入库操作费-F230DE_260410（公布价)-2 | AC56: DE | AD56: 65462C | AE56: 65462C | AF56: PZ_国际 | AG56: DEFRAB德国法兰克福2仓 | AI56: 是 | AM56: 8-Inch Air Carbon Filter for Odor Control, black | AN56: VIVOSUN钢印滤芯 黑色8寸
A57: IC947270260117155 | B57: SW202601150006DE | C57: SW202601150006DE | D57: VS Amazon+eBay+Web 58.5方 11354KG 1519箱 测试笔+喷雾器+滴灌套装 含电 除湿机含制冷剂 | E57: FB4 | F57: 入库操作费-DE | G57: 947270 | H57: 2026-04-15 20:24:26 | I57: 0 | J57: 8440.56 | K57: VSV-AZG8E42AP-EU | L57: 4 | M57: 入库操作费 | N57: 入库操作费 | O57: EUR | P57: 2 | Q57: 0 | R57: 1.72 | S57: 0 | T57: 1.72 | U57: 个 | V57: 4.792 | W57: 德国法兰克福2仓 | Z57: 入库操作费-F230DE_260410（公布价)-2 | AC57: DE | AD57: 65462C | AE57: 65462C | AF57: PZ_国际 | AG57: DEFRAB德国法兰克福2仓 | AI57: 是 | AM57: VSV-AZG8E42AP-EU||AeroZesh G8 金属底座风机 8寸 + GrowHub E42A+控制器 欧版 | AN57: AeroZesh G8 金属底座风机 8寸 + GrowHub E42A+控制器 欧版
A58: IC947270260117155 | B58: SW202601150006DE | C58: SW202601150006DE | D58: VS Amazon+eBay+Web 58.5方 11354KG 1519箱 测试笔+喷雾器+滴灌套装 含电 除湿机含制冷剂 | E58: FB4 | F58: 入库操作费-DE | G58: 947270 | H58: 2026-04-15 20:24:26 | I58: 0 | J58: 8440.56 | K58: TN-44-EU | L58: 12 | M58: 入库操作费 | N58: 入库操作费 | O58: EUR | P58: 2.76 | Q58: 0 | R58: 2.4 | S58: 0 | T58: 2.4 | U58: 个 | V58: 0.2 | W58: 德国法兰克福2仓 | Z58: 入库操作费-F230DE_260410（公布价)-2 | AC58: DE | AD58: 65462C | AE58: 65462C | AF58: PZ_国际 | AG58: DEFRAB德国法兰克福2仓 | AI58: 是 | AM58: 4 x 4Ft. Elastic Trellis Netting | AN58: 弹力爬藤网 4*4FT(网格尺寸：10*10cm)
A59: IC947270260117155 | B59: SW202601150006DE | C59: SW202601150006DE | D59: VS Amazon+eBay+Web 58.5方 11354KG 1519箱 测试笔+喷雾器+滴灌套装 含电 除湿机含制冷剂 | E59: FB4 | F59: 入库操作费-DE | G59: 947270 | H59: 2026-04-15 20:24:26 | I59: 0 | J59: 8440.56 | K59: VSV-IFP4C-EU | L59: 160 | M59: 入库操作费 | N59: 入库操作费 | O59: EUR | P59: 44.8 | Q59: 0 | R59: 38.4 | S59: 0 | T59: 38.4 | U59: 个 | V59: 0.506 | W59: 德国法兰克福2仓 | Z59: 入库操作费-F230DE_260410（公布价)-2 | AC59: DE | AD59: 65462C | AE59: 65462C | AF59: PZ_国际 | AG59: DEFRAB德国法兰克福2仓 | AI59: 是 | AM59: Plastic exhaust fan with adjustable speed 4 inch | AN59: P4 塑料抽风扇调速款单品-欧标
A60: IC947270260117155 | B60: SW202601150006DE | C60: SW202601150006DE | D60: VS Amazon+eBay+Web 58.5方 11354KG 1519箱 测试笔+喷雾器+滴灌套装 含电 除湿机含制冷剂 | E60: FB4 | F60: 入库操作费-DE | G60: 947270 | H60: 2026-04-15 20:24:26 | I60: 0 | J60: 8440.56 | K60: VSV-AZT6-EU | L60: 8 | M60: 入库操作费 | N60: 入库操作费 | O60: EUR | P60: 2.64 | Q60: 0 | R60: 2.24 | S60: 0 | T60: 2.24 | U60: 个 | V60: 2.776 | W60: 德国法兰克福2仓 | Z60: 入库操作费-F230DE_260410（公布价)-2 | AC60: DE | AD60: 65462C | AE60: 65462C | AF60: PZ_国际 | AG60: DEFRAB德国法兰克福2仓 | AI60: 是 | AM60: AeroZesh T6金属支架风机6寸+线控 | AN60: AeroZesh T6金属支架风机6寸+线控
A61: IC947270260117155 | B61: SW202601150006DE | C61: SW202601150006DE | D61: VS Amazon+eBay+Web 58.5方 11354KG 1519箱 测试笔+喷雾器+滴灌套装 含电 除湿机含制冷剂 | E61: FB4 | F61: 入库操作费-DE | G61: 947270 | H61: 2026-04-15 20:24:26 | I61: 0 | J61: 8440.56 | K61: TN-55-EU | L61: 20 | M61: 入库操作费 | N61: 入库操作费 | O61: EUR | P61: 4.6 | Q61: 0 | R61: 4 | S61: 0 | T61: 4 | U61: 个 | V61: 0.27 | W61: 德国法兰克福2仓 | Z61: 入库操作费-F230DE_260410（公布价)-2 | AC61: DE | AD61: 65462C | AE61: 65462C | AF61: PZ_国际 | AG61: DEFRAB德国法兰克福2仓 | AI61: 是 | AM61: 5 x 5Ft. Elastic Trellis Netting | AN61: 弹力爬藤网 5*5FT(网格尺寸：10*10cm)
A62: IC947270260117155 | B62: SW202601150006DE | C62: SW202601150006DE | D62: VS Amazon+eBay+Web 58.5方 11354KG 1519箱 测试笔+喷雾器+滴灌套装 含电 除湿机含制冷剂 | E62: FB4 | F62: 入库操作费-DE | G62: 947270 | H62: 2026-04-15 20:24:26 | I62: 0 | J62: 8440.56 | K62: VSK-GIYS336-EU | L62: 4 | M62: 入库操作费 | N62: 入库操作费 | O62: EUR | P62: 9.6 | Q62: 0 | R62: 8.24 | S62: 0 | T62: 8.24 | U62: 个 | V62: 23 | W62: 德国法兰克福2仓 | Z62: 入库操作费-F230DE_260410（公布价)-2 | AC62: DE | AD62: 65462C | AE62: 65462C | AF62: PZ_国际 | AG62: DEFRAB德国法兰克福2仓 | AI62: 是 | AM62: Smart Grow Tent Kit GIY-SE-33 3x3, 3-Plant Complete System | AN62: GIY SGS智能标准款帐篷套装S336欧版
A63: IC947270260117155 | B63: SW202601150006DE | C63: SW202601150006DE | D63: VS Amazon+eBay+Web 58.5方 11354KG 1519箱 测试笔+喷雾器+滴灌套装 含电 除湿机含制冷剂 | E63: FB4 | F63: 入库操作费-DE | G63: 947270 | H63: 2026-04-15 20:24:26 | I63: 0 | J63: 8440.56 | K63: VSL-LL100-EU | L63: 84 | M63: 入库操作费 | N63: 入库操作费 | O63: EUR | P63: 27.72 | Q63: 0 | R63: 23.52 | S63: 0 | T63: 23.52 | U63: 个 | V63: 2.997 | W63: 德国法兰克福2仓 | Z63: 入库操作费-F230DE_260410（公布价)-2 | AC63: DE | AD63: 65462C | AE63: 65462C | AF63: PZ_国际 | AG63: DEFRAB德国法兰克福2仓 | AI63: 是 | AM63: VS lumalight LED Grow Light Board 100W | AN63: VS-lumalight-量子版2025-100W-EU
... A65: IC947270260117155 | B65: SW202601150006DE | C65: SW202601150006DE | D65: VS Amazon+eBay+Web 58.5方 11354KG 1519箱 测试笔+喷雾器+滴灌套装 含电 除湿机含制冷剂 | E65: FB4 | F65: 入库操作费-DE | G65: 947270 | H65: 2026-04-15 20:24:26 | I65: 0 | J65: 8440.56 | K65: VSV-AZG4E42AP-EU | L65: 8 | M65: 入库操作费 | N65: 入库操作费 | O65: EUR | P65: 2.64 | Q65: 0 | R65: 2.24 | S65: 0 | T65: 2.24 | U65: 个 | V65: 2.859 | W65: 德国法兰克福2仓 | Z65: 入库操作费-F230DE_260410（公布价)-2 | AC65: DE | AD65: 65462C | AE65: 65462C | AF65: PZ_国际 | AG65: DEFRAB德国法兰克福2仓 | AI65: 是 | AM65: AeroZesh G4 Inline fan + GrowHub E42A+ | AN65: AeroZesh G4 金属底座风机 4寸 + GrowHub E42A+控制器 欧版
A66: IC947270260117155 | B66: SW202601150006DE | C66: SW202601150006DE | D66: VS Amazon+eBay+Web 58.5方 11354KG 1519箱 测试笔+喷雾器+滴灌套装 含电 除湿机含制冷剂 | E66: FB4 | F66: 入库操作费-DE | G66: 947270 | H66: 2026-04-15 20:24:26 | I66: 0 | J66: 8440.56 | K66: 332572-EU | L66: 30 | M66: 入库操作费 | N66: 入库操作费 | O66: EUR | P66: 8.4 | Q66: 0 | R66: 7.2 | S66: 0 | T66: 7.2 | U66: 个 | V66: 0.89 | W66: 德国法兰克福2仓 | Z66: 入库操作费-F230DE_260410（公布价)-2 | AC66: DE | AD66: 65462C | AE66: 65462C | AF66: PZ_国际 | AG66: DEFRAB德国法兰克福2仓 | AI66: 是 | AM66: 800GPH Submersible Pump(3000L/H, 24W), Ultra Quiet Water Fountain Pump with 10ft. High Lift with 6.5ft.
A67: IC947270260117155 | B67: SW202601150006DE | C67: SW202601150006DE | D67: VS Amazon+eBay+Web 58.5方 11354KG 1519箱 测试笔+喷雾器+滴灌套装 含电 除湿机含制冷剂 | E67: FB4 | F67: 入库操作费-DE | G67: 947270 | H67: 2026-04-15 20:24:26 | I67: 0 | J67: 8440.56 | K67: 305131-EU | L67: 150 | M67: 入库操作费 | N67: 入库操作费 | O67: EUR | P67: 34.5 | Q67: 0 | R67: 30 | S67: 0 | T67: 30 | U67: 个 | V67: 0.09 | W67: 德国法兰克福2仓 | Z67: 入库操作费-F230DE_260410（公布价)-2 | AC67: DE | AD67: 65462C | AE67: 65462C | AF67: PZ_国际 | AG67: DEFRAB德国法兰克福2仓 | AI67: 是 | AM67: Soil tester
A68: IC947270260117155 | B68: SW202601150006DE | C68: SW202601150006DE | D68: VS Amazon+eBay+Web 58.5方 11354KG 1519箱 测试笔+喷雾器+滴灌套装 含电 除湿机含制冷剂 | E68: FB4 | F68: 入库操作费-DE | G68: 947270 | H68: 2026-04-15 20:24:26 | I68: 0 | J68: 8440.56 | K68: VSI-FFSW6-4-EU | L68: 46 | M68: 入库操作费 | N68: 入库操作费 | O68: EUR | P68: 23 | Q68: 0 | R68: 19.78 | S68: 0 | T68: 19.78 | U68: 个 | V68: 4.72 | W68: 德国法兰克福2仓 | Z68: 入库操作费-F230DE_260410（公布价)-2 | AC68: DE | AD68: 65462C | AE68: 65462C | AF68: PZ_国际 | AG68: DEFRAB德国法兰克福2仓 | AI68: 是 | AM68: 4-Pack FlexFeed Self-Watering Irrigation Pot
A69: IC947270260117155 | B69: SW202601150006DE | C69: SW202601150006DE | D69: VS Amazon+eBay+Web 58.5方 11354KG 1519箱 测试笔+喷雾器+滴灌套装 含电 除湿机含制冷剂 | E69: FB4 | F69: 入库操作费-DE | G69: 947270 | H69: 2026-04-15 20:24:26 | I69: 0 | J69: 8440.56 | K69: VSE-ASU075-EU | L69: 120 | M69: 入库操作费 | N69: 入库操作费 | O69: EUR | P69: 27.6 | Q69: 0 | R69: 24 | S69: 0 | T69: 24 | U69: 个 | V69: 0.39 | W69: 德国法兰克福2仓 | Z69: 入库操作费-F230DE_260410（公布价)-2 | AC69: DE | AD69: 65462C | AE69: 65462C | AF69: PZ_国际 | AG69: DEFRAB德国法兰克福2仓 | AI69: 是 | AM69: AeroStream U075 USB Humidifier
A70: IC947270260117155 | B70: SW202601150006DE | C70: SW202601150006DE | D70: VS Amazon+eBay+Web 58.5方 11354KG 1519箱 测试笔+喷雾器+滴灌套装 含电 除湿机含制冷剂 | E70: FB4 | F70: 入库操作费-DE | G70: 947270 | H70: 2026-04-15 20:24:26 | I70: 0 | J70: 8440.56 | K70: VSA-AG-5B3-EU | L70: 4 | M70: 入库操作费 | N70: 入库操作费 | O70: EUR | P70: 1.32 | Q70: 0 | R70: 1.12 | S70: 0 | T70: 1.12 | U70: 个 | V70: 1.309 | W70: 德国法兰克福2仓 | Z70: 入库操作费-F230DE_260410（公布价)-2 | AC70: DE | AD70: 65462C | AE70: 65462C | AF70: PZ_国际 | AG70: DEFRAB德国法兰克福2仓 | AI70: 是 | AM70: 3-Pack 5-Gallon AeroBase Grow Bag | AN70: AeroBase空气底种植袋黑色5加仑3pcs
A71: IC947270260117155 | B71: SW202601150006DE | C71: SW202601150006DE | D71: VS Amazon+eBay+Web 58.5方 11354KG 1519箱 测试笔+喷雾器+滴灌套装 含电 除湿机含制冷剂 | E71: FB4 | F71: 入库操作费-DE | G71: 947270 | H71: 2026-04-15 20:24:26 | I71: 0 | J71: 8440.56 | K71: 304113-P276-EU | L71: 10 | M71: 入库操作费 | N71: 入库操作费 | O71: EUR | P71: 14.5 | Q71: 0 | R71: 12.5 | S71: 0 | T71: 12.5 | U71: 个 | V71: 11.4 | W71: 德国法兰克福2仓 | Z71: 入库操作费-F230DE_260410（公布价)-2 | AC71: DE | AD71: 65462C | AE71: 65462C | AF71: PZ_国际 | AG71: DEFRAB德国法兰克福2仓 | AI71: 是 | AM71: P276 32"×32"×63" PRO Grow Tent | AN71: P276 Pro款27帐篷-32"x32"x63"/80*80*160cm 22mm管径
A72: IC947270260117155 | B72: SW202601150006DE | C72: SW202601150006DE | D72: VS Amazon+eBay+Web 58.5方 11354KG 1519箱 测试笔+喷雾器+滴灌套装 含电 除湿机含制冷剂 | E72: FB4 | F72: 入库操作费-DE | G72: 947270 | H72: 2026-04-15 20:24:26 | I72: 0 | J72: 8440.56 | K72: GH-E42AP-EU | L72: 96 | M72: 入库操作费 | N72: 入库操作费 | O72: EUR | P72: 26.88 | Q72: 0 | R72: 23.04 | S72: 0 | T72: 23.04 | U72: 个 | V72: 0.719 | W72: 德国法兰克福2仓 | Z72: 入库操作费-F230DE_260410（公布价)-2 | AC72: DE | AD72: 65462C | AE72: 65462C | AF72: PZ_国际 | AG72: DEFRAB德国法兰克福2仓 | AI72: 是 | AM72: GrowHub E42A+ Controller for Grow Tent | AN72: GrowHub E42A+ Controller 欧版
A73: IC947270260117155 | B73: SW202601150006DE | C73: SW202601150006DE | D73: VS Amazon+eBay+Web 58.5方 11354KG 1519箱 测试笔+喷雾器+滴灌套装 含电 除湿机含制冷剂 | E73: FB4 | F73: 入库操作费-DE | G73: 947270 | H73: 2026-04-15 20:24:26 | I73: 0 | J73: 8440.56 | K73: GH-E25-EU | L73: 200 | M73: 入库操作费 | N73: 入库操作费 | O73: EUR | P73: 46 | Q73: 0 | R73: 40 | S73: 0 | T73: 40 | U73: 个 | V73: 0.02 | W73: 德国法兰克福2仓 | Z73: 入库操作费-F230DE_260410（公布价)-2 | AC73: DE | AD73: 65462C | AE73: 65462C | AF73: PZ_国际 | AG73: DEFRAB德国法兰克福2仓 | AI73: 是 | AM73: E25控制器-单品包装 | AN73: E25控制器-单品包装
A74: IC947270260117155 | B74: SW202601150006DE | C74: SW202601150006DE | D74: VS Amazon+eBay+Web 58.5方 11354KG 1519箱 测试笔+喷雾器+滴灌套装 含电 除湿机含制冷剂 | E74: FB4 | F74: 入库操作费-DE | G74: 947270 | H74: 2026-04-15 20:24:26 | I74: 0 | J74: 8440.56 | K74: 304113-P336-EU | L74: 24 | M74: 入库操作费 | N74: 入库操作费 | O74: EUR | P74: 34.8 | Q74: 0 | R74: 30 | S74: 0 | T74: 30 | U74: 个 | V74: 14.46 | W74: 德国法兰克福2仓 | Z74: 入库操作费-F230DE_260410（公布价)-2 | AC74: DE | AD74: 65462C | AE74: 65462C | AF74: PZ_国际 | AG74: DEFRAB德国法兰克福2仓 | AI74: 是 | AM74: P336 36"×36"×72" PRO Grow Tent | AN74: P336 Pro款33帐篷-36"x36"x72"/90*90*180cm 22mm管径
A75: IC947270260117155 | B75: SW202601150006DE | C75: SW202601150006DE | D75: VS Amazon+eBay+Web 58.5方 11354KG 1519箱 测试笔+喷雾器+滴灌套装 含电 除湿机含制冷剂 | E75: FB4 | F75: 入库操作费-DE | G75: 947270 | H75: 2026-04-15 20:24:26 | I75: 0 | J75: 8440.56 | K75: 306143-0412-EU | L75: 179 | M75: 入库操作费 | N75: 入库操作费 | O75: EUR | P75: 59.07 | Q75: 0 | R75: 50.12 | S75: 0 | T75: 50.12 | U75: 个 | V75: 2.475 | W75: 德国法兰克福2仓 | Z75: 入库操作费-F230DE_260410（公布价)-2 | AC75: DE | AD75: 65462C | AE75: 65462C | AF75: PZ_国际 | AG75: DEFRAB德国法兰克福2仓 | AI75: 是 | AM75: VIVOSUN钢印滤芯 4" | AN75: VIVOSUN钢印滤芯 4"
A76: IC947270260117155 | B76: SW202601150006DE | C76: SW202601150006DE | D76: VS Amazon+eBay+Web 58.5方 11354KG 1519箱 测试笔+喷雾器+滴灌套装 含电 除湿机含制冷剂 | E76: FB4 | F76: 入库操作费-DE | G76: 947270 | H76: 2026-04-15 20:24:26 | I76: 0 | J76: 8440.56 | K76: VSEX-HID1-ST-EU | L76: 8 | M76: 入库操作费 | N76: 入库操作费 | O76: EUR | P76: 4 | Q76: 0 | R76: 3.44 | S76: 0 | T76: 3.44 | U76: 个 | V76: 3.812 | W76: 德国法兰克福2仓 | Z76: 入库操作费-F230DE_260410（公布价)-2 | AC76: DE | AD76: 65462C | AE76: 65462C | AF76: PZ_国际 | AG76: DEFRAB德国法兰克福2仓 | AI76: 是 | AM76: Herbal Decarboxylation and Infusion Machine | AN76: S4508B 黄油机套装-欧版
A77: IC947270260117155 | B77: SW202601150006DE | C77: SW202601150006DE | D77: VS Amazon+eBay+Web 58.5方 11354KG 1519箱 测试笔+喷雾器+滴灌套装 含电 除湿机含制冷剂 | E77: FB4 | F77: 入库操作费-DE | G77: 947270 | H77: 2026-04-15 20:24:26 | I77: 0 | J77: 8440.56 | K77: VGA-TN13-EU | L77: 30 | M77: 入库操作费 | N77: 入库操作费 | O77: EUR | P77: 6.9 | Q77: 0 | R77: 6 | S77: 0 | T77: 6 | U77: 个 | V77: 0.07 | W77: 德国法兰克福2仓 | Z77: 入库操作费-F230DE_260410（公布价)-2 | AC77: DE | AD77: 65462C | AE77: 65462C | AF77: PZ_国际 | AG77: DEFRAB德国法兰克福2仓 | AI77: 是 | AM77: Trellis Net | AN77: Y18 爬藤网
A78: IC947270260117155 | B78: SW202601150006DE | C78: SW202601150006DE | D78: VS Amazon+eBay+Web 58.5方 11354KG 1519箱 测试笔+喷雾器+滴灌套装 含电 除湿机含制冷剂 | E78: FB4 | F78: 入库操作费-DE | G78: 947270 | H78: 2026-04-15 20:24:26 | I78: 0 | J78: 8440.56 | K78: VSE-ADD12-EU | L78: 8 | M78: 入库操作费 | N78: 入库操作费 | O78: EUR | P78: 11.6 | Q78: 0 | R78: 10 | S78: 0 | T78: 10 | U78: 个 | V78: 12.5 | W78: 德国法兰克福2仓 | Z78: 入库操作费-F230DE_260410（公布价)-2 | AC78: DE | AD78: 65462C | AE78: 65462C | AF78: PZ_国际 | AG78: DEFRAB德国法兰克福2仓 | AI78: 是 | AM78: Desumidificador AeroDrain D12 | AN78: AeroDrain WiFi除湿机_12L_欧版
A79: IC947270260117155 | B79: SW202601150006DE | C79: SW202601150006DE | D79: VS Amazon+eBay+Web 58.5方 11354KG 1519箱 测试笔+喷雾器+滴灌套装 含电 除湿机含制冷剂 | E79: FB4 | F79: 入库操作费-DE | G79: 947270 | H79: 2026-04-15 20:24:26 | I79: 0 | J79: 8440.56 | K79: 332823-100J-EU | L79: 48 | M79: 入库操作费 | N79: 入库操作费 | O79: EUR | P79: 11.04 | Q79: 0 | R79: 9.6 | S79: 0 | T79: 9.6 | U79: 个 | V79: 0.2 | W79: 德国法兰克福2仓 | Z79: 入库操作费-F230DE_260410（公布价)-2 | AC79: DE | AD79: 65462C | AE79: 65462C | AF79: PZ_国际 | AG79: DEFRAB德国法兰克福2仓 | AI79: 是 | AM79: 328 Feet (100m) PE-Coated Twist Ties | AN79: 园林扎线-100米
A80: IC947270260117155 | B80: SW202601150006DE | C80: SW202601150006DE | D80: VS Amazon+eBay+Web 58.5方 11354KG 1519箱 测试笔+喷雾器+滴灌套装 含电 除湿机含制冷剂 | E80: FB4 | F80: 入库操作费-DE | G80: 947270 | H80: 2026-04-15 20:24:26 | I80: 0 | J80: 8440.56 | K80: VSL-LRSF50-4-EU | L80: 96 | M80: 入库操作费 | N80: 入库操作费 | O80: EUR | P80: 31.68 | Q80: 0 | R80: 26.88 | S80: 0 | T80: 26.88 | U80: 个 | V80: 1.378 | W80: 德国法兰克福2仓 | Z80: 入库操作费-F230DE_260410（公布价)-2 | AC80: DE | AD80: 65462C | AE80: 65462C | AF80: PZ_国际 | AG80: DEFRAB德国法兰克福2仓 | AI80: 是 | AM80: Supplemental light LumaRay Side lighting 4bar | AN80: Supplemental light LumaRay Side lighting 4bar补光灯 欧版
A81: IC947270260117155 | B81: SW202601150006DE | C81: SW202601150006DE | D81: VS Amazon+eBay+Web 58.5方 11354KG 1519箱 测试笔+喷雾器+滴灌套装 含电 除湿机含制冷剂 | E81: FB4 | F81: 入库操作费-DE | G81: 947270 | H81: 2026-04-15 20:24:26 | I81: 0 | J81: 8440.56 | K81: PS-002-EU | L81: 145 | M81: 入库操作费 | N81: 入库操作费 | O81: EUR | P81: 33.35 | Q81: 0 | R81: 29 | S81: 0 | T81: 29 | U81: 个 | V81: 0.07 | W81: 德国法兰克福2仓 | Z81: 入库操作费-F230DE_260410（公布价)-2 | AC81: DE | AD81: 65462C | AE81: 65462C | AF81: PZ_国际 | AG81: DEFRAB德国法兰克福2仓 | AI81: 是 | AM81: 黑绿配色花枝剪1个装 | AN81: 黑绿配色花枝剪1个装
... A83: IC947270260117155 | B83: SW202601150006DE | C83: SW202601150006DE | D83: VS Amazon+eBay+Web 58.5方 11354KG 1519箱 测试笔+喷雾器+滴灌套装 含电 除湿机含制冷剂 | E83: FB4 | F83: 入库操作费-DE | G83: 947270 | H83: 2026-04-15 20:24:26 | I83: 0 | J83: 8440.56 | K83: SST-H-0001-EU | L83: 80 | M83: 入库操作费 | N83: 入库操作费 | O83: EUR | P83: 26.4 | Q83: 0 | R83: 22.4 | S83: 0 | T83: 22.4 | U83: 个 | V83: 1.06 | W83: 德国法兰克福2仓 | Z83: 入库操作费-F230DE_260410（公布价)-2 | AC83: DE | AD83: 65462C | AE83: 65462C | AF83: PZ_国际 | AG83: DEFRAB德国法兰克福2仓 | AI83: 是 | AM83: 6-Pack Seed Starter Trays with 10"x20.75" Seedling Heat Mat | AN83: 欧规 12孔育苗盘6套装+10*20.75育苗垫组合款
A84: IC947270260117155 | B84: SW202601150006DE | C84: SW202601150006DE | D84: VS Amazon+eBay+Web 58.5方 11354KG 1519箱 测试笔+喷雾器+滴灌套装 含电 除湿机含制冷剂 | E84: FB4 | F84: 入库操作费-DE | G84: 947270 | H84: 2026-04-15 20:24:26 | I84: 0 | J84: 8440.56 | K84: VSF-AWD4X2-EU | L84: 54 | M84: 入库操作费 | N84: 入库操作费 | O84: EUR | P84: 15.12 | Q84: 0 | R84: 12.96 | S84: 0 | T84: 12.96 | U84: 个 | V84: 0.61 | W84: 德国法兰克福2仓 | Z84: 入库操作费-F230DE_260410（公布价)-2 | AC84: DE | AD84: 65462C | AE84: 65462C | AF84: PZ_国际 | AG84: DEFRAB德国法兰克福2仓 | AI84: 是 | AM84: AeroWave D4, 4” Grow Tent Clip Fan with Detachable Hook
A85: IC947270260117155 | B85: SW202601150006DE | C85: SW202601150006DE | D85: VS Amazon+eBay+Web 58.5方 11354KG 1519箱 测试笔+喷雾器+滴灌套装 含电 除湿机含制冷剂 | E85: FB4 | F85: 入库操作费-DE | G85: 947270 | H85: 2026-04-15 20:24:26 | I85: 0 | J85: 8440.56 | K85: VSE-ATW70-EU | L85: 84 | M85: 入库操作费 | N85: 入库操作费 | O85: EUR | P85: 42 | Q85: 0 | R85: 36.12 | S85: 0 | T85: 36.12 | U85: 个 | V85: 3.216 | W85: 德国法兰克福2仓 | Z85: 入库操作费-F230DE_260410（公布价)-2 | AC85: DE | AD85: 65462C | AE85: 65462C | AF85: PZ_国际 | AG85: DEFRAB德国法兰克福2仓 | AI85: 是 | AM85: AeroFlux Heater 70w | AN85: AeroFlux Heater 70w
A86: IC947270260117155 | B86: SW202601150006DE | C86: SW202601150006DE | D86: VS Amazon+eBay+Web 58.5方 11354KG 1519箱 测试笔+喷雾器+滴灌套装 含电 除湿机含制冷剂 | E86: FB4 | F86: 入库操作费-DE | G86: 947270 | H86: 2026-04-15 20:24:26 | I86: 0 | J86: 8440.56 | K86: 330101X2NJ-EU | L86: 20 | M86: 入库操作费 | N86: 入库操作费 | O86: EUR | P86: 5.6 | Q86: 0 | R86: 4.8 | S86: 0 | T86: 4.8 | U86: 个 | V86: 0.755 | W86: 德国法兰克福2仓 | Z86: 入库操作费-F230DE_260410（公布价)-2 | AC86: DE | AD86: 65462C | AE86: 65462C | AF86: PZ_国际 | AG86: DEFRAB德国法兰克福2仓 | AI86: 是 | AM86: Seedling heating pad 10''x20'' 2 pieces for sale
A87: IC947270260117155 | B87: SW202601150006DE | C87: SW202601150006DE | D87: VS Amazon+eBay+Web 58.5方 11354KG 1519箱 测试笔+喷雾器+滴灌套装 含电 除湿机含制冷剂 | E87: FB4 | F87: 入库操作费-DE | G87: 947270 | H87: 2026-04-15 20:24:26 | I87: 0 | J87: 8440.56 | K87: VSV-AZT4E42AP-EU | L87: 27 | M87: 入库操作费 | N87: 入库操作费 | O87: EUR | P87: 8.91 | Q87: 0 | R87: 7.56 | S87: 0 | T87: 7.56 | U87: 个 | V87: 2.638 | W87: 德国法兰克福2仓 | Z87: 入库操作费-F230DE_260410（公布价)-2 | AC87: DE | AD87: 65462C | AE87: 65462C | AF87: PZ_国际 | AG87: DEFRAB德国法兰克福2仓 | AI87: 是 | AM87: AeroZesh T4+E42AP | AN87: AeroZesh T4 金属底座风机 4寸 + GrowHub E42A+控制器 欧版
A88: IC947270260117155 | B88: SW202601150006DE | C88: SW202601150006DE | D88: VS Amazon+eBay+Web 58.5方 11354KG 1519箱 测试笔+喷雾器+滴灌套装 含电 除湿机含制冷剂 | E88: FB4 | F88: 入库操作费-DE | G88: 947270 | H88: 2026-04-15 20:24:26 | I88: 0 | J88: 8440.56 | K88: VSI-FFSW6GB5-4-EU | L88: 30 | M88: 入库操作费 | N88: 入库操作费 | O88: EUR | P88: 28.2 | Q88: 0 | R88: 24.3 | S88: 0 | T88: 24.3 | U88: 个 | V88: 5.11 | W88: 德国法兰克福2仓 | Z88: 入库操作费-F230DE_260410（公布价)-2 | AC88: DE | AD88: 65462C | AE88: 65462C | AF88: PZ_国际 | AG88: DEFRAB德国法兰克福2仓 | AI88: 是 | AM88: FlexFeed Self-Watering Fabric Pot Base with Grow Gags | AN88: FlexFleed Self Watering Pots with 5 Gallon Grow Bags 4只装
A89: IC947270260117155 | B89: SW202601150006DE | C89: SW202601150006DE | D89: VS Amazon+eBay+Web 58.5方 11354KG 1519箱 测试笔+喷雾器+滴灌套装 含电 除湿机含制冷剂 | E89: FB4 | F89: 入库操作费-DE | G89: 947270 | H89: 2026-04-15 20:24:26 | I89: 0 | J89: 8440.56 | K89: VSF-AWD4-EU | L89: 360 | M89: 入库操作费 | N89: 入库操作费 | O89: EUR | P89: 82.8 | Q89: 0 | R89: 72 | S89: 0 | T89: 72 | U89: 个 | V89: 0.31 | W89: 德国法兰克福2仓 | Z89: 入库操作费-F230DE_260410（公布价)-2 | AC89: DE | AD89: 65462C | AE89: 65462C | AF89: PZ_国际 | AG89: DEFRAB德国法兰克福2仓 | AI89: 是 | AM89: 黑色4寸夹扇 | AN89: 黑色4寸夹扇
A90: IC947270260117155 | B90: SW202601150006DE | C90: SW202601150006DE | D90: VS Amazon+eBay+Web 58.5方 11354KG 1519箱 测试笔+喷雾器+滴灌套装 含电 除湿机含制冷剂 | E90: FB4 | F90: 入库操作费-DE | G90: 947270 | H90: 2026-04-15 20:24:26 | I90: 0 | J90: 8440.56 | K90: VSVC-AZG8-EU | L90: 8 | M90: 入库操作费 | N90: 入库操作费 | O90: EUR | P90: 11.6 | Q90: 0 | R90: 10 | S90: 0 | T90: 10 | U90: 个 | V90: 15 | W90: 德国法兰克福2仓 | Z90: 入库操作费-F230DE_260410（公布价)-2 | AC90: DE | AD90: 65462C | AE90: 65462C | AF90: PZ_国际 | AG90: DEFRAB德国法兰克福2仓 | AI90: 是 | AM90: Smart Air Filtration G8 Kit 8" | AN90: AeroZesh G8风机+E12线控+滤芯+风管—欧规
A91: IC947270260117155 | B91: SW202601150006DE | C91: SW202601150006DE | D91: VS Amazon+eBay+Web 58.5方 11354KG 1519箱 测试笔+喷雾器+滴灌套装 含电 除湿机含制冷剂 | E91: FB4 | F91: 入库操作费-DE | G91: 947270 | H91: 2026-04-15 20:24:26 | I91: 0 | J91: 8440.56 | K91: VSF-AWA6G2-EU | L91: 96 | M91: 入库操作费 | N91: 入库操作费 | O91: EUR | P91: 31.68 | Q91: 0 | R91: 26.88 | S91: 0 | T91: 26.88 | U91: 个 | V91: 1.468 | W91: 德国法兰克福2仓 | Z91: 入库操作费-F230DE_260410（公布价)-2 | AC91: DE | AD91: 65462C | AE91: 65462C | AF91: PZ_国际 | AG91: DEFRAB德国法兰克福2仓 | AI91: 是 | AM91: Aerowave A6 Gen2 Grow Tent Clip Fan | AN91: 入门款AC电机夹扇A6 Gen2 欧版
A92: IC947270260117155 | B92: SW202601150006DE | C92: SW202601150006DE | D92: VS Amazon+eBay+Web 58.5方 11354KG 1519箱 测试笔+喷雾器+滴灌套装 含电 除湿机含制冷剂 | E92: FB4 | F92: 入库操作费-DE | G92: 947270 | H92: 2026-04-15 20:24:26 | I92: 0 | J92: 8440.56 | K92: VSF-AWE6-G2X2-EU | L92: 92 | M92: 入库操作费 | N92: 入库操作费 | O92: EUR | P92: 30.36 | Q92: 0 | R92: 25.76 | S92: 0 | T92: 25.76 | U92: 个 | V92: 2.13 | W92: 德国法兰克福2仓 | Z92: 入库操作费-F230DE_260410（公布价)-2 | AC92: DE | AD92: 65462C | AE92: 65462C | AF92: PZ_国际 | AG92: DEFRAB德国法兰克福2仓 | AI92: 是 | AM92: Aerowave E6 Gen 2 black clip fan 2-pack
A93: IC947270260117155 | B93: SW202601150006DE | C93: SW202601150006DE | D93: VS Amazon+eBay+Web 58.5方 11354KG 1519箱 测试笔+喷雾器+滴灌套装 含电 除湿机含制冷剂 | E93: FB4 | F93: 入库操作费-DE | G93: 947270 | H93: 2026-04-15 20:24:26 | I93: 0 | J93: 8440.56 | K93: VSF-AWE6-G2-EU | L93: 48 | M93: 入库操作费 | N93: 入库操作费 | O93: EUR | P93: 15.84 | Q93: 0 | R93: 13.44 | S93: 0 | T93: 13.44 | U93: 个 | V93: 1.1 | W93: 德国法兰克福2仓 | Z93: 入库操作费-F230DE_260410（公布价)-2 | AC93: DE | AD93: 65462C | AE93: 65462C | AF93: PZ_国际 | AG93: DEFRAB德国法兰克福2仓 | AI93: 是 | AM93: AeroWave E6 Grow Tent Fan 6”
A94: IC947270260117155 | B94: SW202601150006DE | C94: SW202601150006DE | D94: VS Amazon+eBay+Web 58.5方 11354KG 1519箱 测试笔+喷雾器+滴灌套装 含电 除湿机含制冷剂 | E94: FB4 | F94: 入库操作费-DE | G94: 947270 | H94: 2026-04-15 20:24:26 | I94: 0 | J94: 8440.56 | K94: VS1000E-EU | L94: 55 | M94: 入库操作费 | N94: 入库操作费 | O94: EUR | P94: 18.15 | Q94: 0 | R94: 15.4 | S94: 0 | T94: 15.4 | U94: 个 | V94: 2.03 | W94: 德国法兰克福2仓 | Z94: 入库操作费-F230DE_260410（公布价)-2 | AC94: DE | AD94: 65462C | AE94: 65462C | AF94: PZ_国际 | AG94: DEFRAB德国法兰克福2仓 | AI94: 是 | AM94: VS1000E LED Grow Light with Samsung Diodes | AN94: 欧规 VS1000E量子版100W (带绿色新钩子)
A95: IC947270260117155 | B95: SW202601150006DE | C95: SW202601150006DE | D95: VS Amazon+eBay+Web 58.5方 11354KG 1519箱 测试笔+喷雾器+滴灌套装 含电 除湿机含制冷剂 | E95: FB4 | F95: 入库操作费-DE | G95: 947270 | H95: 2026-04-15 20:24:26 | I95: 0 | J95: 8440.56 | K95: 304113-52-EU | L95: 6 | M95: 入库操作费 | N95: 入库操作费 | O95: EUR | P95: 8.7 | Q95: 0 | R95: 7.5 | S95: 0 | T95: 7.5 | U95: 个 | V95: 11.821 | W95: 德国法兰克福2仓 | Z95: 入库操作费-F230DE_260410（公布价)-2 | AC95: DE | AD95: 65462C | AE95: 65462C | AF95: PZ_国际 | AG95: DEFRAB德国法兰克福2仓 | AI95: 是 | AM95: 52帐篷-60"x32"x80"/150*80*200cm 16mm管径 | AN95: 52帐篷-60"x32"x80"/150*80*200cm 16mm管径
A96: IC947270260117155 | B96: SW202601150006DE | C96: SW202601150006DE | D96: VS Amazon+eBay+Web 58.5方 11354KG 1519箱 测试笔+喷雾器+滴灌套装 含电 除湿机含制冷剂 | E96: FB4 | F96: 入库操作费-DE | G96: 947270 | H96: 2026-04-15 20:24:26 | I96: 0 | J96: 8440.56 | K96: VSI-DWCRR-4-EU | L96: 50 | M96: 入库操作费 | N96: 入库操作费 | O96: EUR | P96: 11.5 | Q96: 0 | R96: 10 | S96: 0 | T96: 10 | U96: 个 | V96: 0.083 | W96: 德国法兰克福2仓 | Z96: 入库操作费-F230DE_260410（公布价)-2 | AC96: DE | AD96: 65462C | AE96: 65462C | AF96: PZ_国际 | AG96: DEFRAB德国法兰克福2仓 | AI96: 是 | AM96: FlexFeed DWC Growing Medium 4 Pack | AN96: FlexFeed DWC 水培桶基质配件 4个装
A97: IC947270260117155 | B97: SW202601150006DE | C97: SW202601150006DE | D97: VS Amazon+eBay+Web 58.5方 11354KG 1519箱 测试笔+喷雾器+滴灌套装 含电 除湿机含制冷剂 | E97: FB4 | F97: 入库操作费-DE | G97: 947270 | H97: 2026-04-15 20:24:26 | I97: 0 | J97: 8440.56 | K97: E331905-EU | L97: 24 | M97: 入库操作费 | N97: 入库操作费 | O97: EUR | P97: 12 | Q97: 0 | R97: 10.32 | S97: 0 | T97: 10.32 | U97: 个 | V97: 3.623 | W97: 德国法兰克福2仓 | Z97: 入库操作费-F230DE_260410（公布价)-2 | AC97: DE | AD97: 65462C | AE97: 65462C | AF97: PZ_国际 | AG97: DEFRAB德国法兰克福2仓 | AI97: 是 | AM97: E331905 || Hand-cranked leaf trimmer | AN97: E331905||手摇叶芽割草机
A98: IC947270260117155 | B98: SW202601150006DE | C98: SW202601150006DE | D98: VS Amazon+eBay+Web 58.5方 11354KG 1519箱 测试笔+喷雾器+滴灌套装 含电 除湿机含制冷剂 | E98: FB4 | F98: 入库操作费-DE | G98: 947270 | H98: 2026-04-15 20:24:26 | I98: 0 | J98: 8440.56 | K98: 306109-6C-EU | L98: 20 | M98: 入库操作费 | N98: 入库操作费 | O98: EUR | P98: 6.6 | Q98: 0 | R98: 5.6 | S98: 0 | T98: 5.6 | U98: 个 | V98: 1.64 | W98: 德国法兰克福2仓 | Z98: 入库操作费-F230DE_260410（公布价)-2 | AC98: DE | AD98: 65462C | AE98: 65462C | AF98: PZ_国际 | AG98: DEFRAB德国法兰克福2仓 | AI98: 是 | AM98: 6 Inch 25 Feet Black Non-Insulated Flex Air Aluminum Ducting | AN98: 风管卡箍组合黑色 6" 25ft
A99: IC947270260117155 | B99: SW202601150006DE | C99: SW202601150006DE | D99: VS Amazon+eBay+Web 58.5方 11354KG 1519箱 测试笔+喷雾器+滴灌套装 含电 除湿机含制冷剂 | E99: FB4 | F99: 入库操作费-DE | G99: 947270 | H99: 2026-04-15 20:24:26 | I99: 0 | J99: 8440.56 | K99: VSH-IS02-EU | L99: 36 | M99: 入库操作费 | N99: 入库操作费 | O99: EUR | P99: 11.88 | Q99: 0 | R99: 10.08 | S99: 0 | T99: 10.08 | U99: 个 | V99: 1.14 | W99: 德国法兰克福2仓 | Z99: 入库操作费-F230DE_260410（公布价)-2 | AC99: DE | AD99: 65462C | AE99: 65462C | AF99: PZ_国际 | AG99: DEFRAB德国法兰克福2仓 | AI99: 是 | AM99: Professional Automatic Drip Irrigation Kits | AN99: 欧版 滴灌套装
A100: IC947270260117155 | B100: SW202601150006DE | C100: SW202601150006DE | D100: VS Amazon+eBay+Web 58.5方 11354KG 1519箱 测试笔+喷雾器+滴灌套装 含电 除湿机含制冷剂 | E100: FB4 | F100: 入库操作费-DE | G100: 947270 | H100: 2026-04-15 20:24:26 | I100: 0 | J100: 8440.56 | K100: VC-0002-EU | L100: 100 | M100: 入库操作费 | N100: 入库操作费 | O100: EUR | P100: 23 | Q100: 0 | R100: 20 | S100: 0 | T100: 20 | U100: 个 | V100: 0.03 | W100: 德国法兰克福2仓 | Z100: 入库操作费-F230DE_260410（公布价)-2 | AC100: DE | AD100: 65462C | AE100: 65462C | AF100: PZ_国际 | AG100: DEFRAB德国法兰克福2仓 | AI100: 是 | AM100: 2-Pcs. Grow Tent Vent Cover 6inch | AN100: 防尘罩-6-Inch两个装
A101: IC947270260117155 | B101: SW202601150006DE | C101: SW202601150006DE | D101: VS Amazon+eBay+Web 58.5方 11354KG 1519箱 测试笔+喷雾器+滴灌套装 含电 除湿机含制冷剂 | E101: FB4 | F101: 入库操作费-DE | G101: 947270 | H101: 2026-04-15 20:24:26 | I101: 0 | J101: 8440.56 | K101: LH-001-2-EU | L101: 50 | M101: 入库操作费 | N101: 入库操作费 | O101: EUR | P101: 11.5 | Q101: 0 | R101: 10 | S101: 0 | T101: 10 | U101: 个 | V101: 0.31 | W101: 德国法兰克福2仓 | Z101: 入库操作费-F230DE_260410（公布价)-2 | AC101: DE | AD101: 65462C | AE101: 65462C | AF101: PZ_国际 | AG101: DEFRAB德国法兰克福2仓 | AI101: 是 | AM101: New hook 2 pairs
A102: IC947270260117155 | B102: SW202601150006DE | C102: SW202601150006DE | D102: VS Amazon+eBay+Web 58.5方 11354KG 1519箱 测试笔+喷雾器+滴灌套装 含电 除湿机含制冷剂 | E102: FB4 | F102: 入库操作费-DE | G102: 947270 | H102: 2026-04-15 20:24:26 | I102: 0 | J102: 8440.56 | K102: 333101-G2J-EU | L102: 150 | M102: 入库操作费 | N102: 入库操作费 | O102: EUR | P102: 34.5 | Q102: 0 | R102: 30 | S102: 0 | T102: 30 | U102: 个 | V102: 0.25 | W102: 德国法兰克福2仓 | Z102: 入库操作费-F230DE_260410（公布价)-2 | AC102: DE | AD102: 65462C | AE102: 65462C | AF102: PZ_国际 | AG102: DEFRAB德国法兰克福2仓 | AI102: 是 | AM102: Titanium Non-Stick Coating Rose Scissors Orange
...

Sheet 出库订单
A1: 出库时间 | B1: 业务单号 | C1: 客户单号 | D1: 下单子账号 | E1: SKU | F1: SKU数量 | G1: 服务类别 | H1: 服务产品 | I1: 计费时间 | J1: 计费重 | K1: 实重 | L1: 费用类型 | M1: 费用名称 | N1: 库龄 | O1: 币种 | P1: 计费金额 | Q1: 优惠金额 | R1: 应收金额 | S1: 含代收代付税费 | T1: 可开票金额 | U1: 计算公式 | V1: 数字公式 | W1: 产品类型 | X1: 计费单位 | Y1: 计费数量 | Z1: 计费地点 | AA1: 报价单编号 | AB1: 优惠券信息 | AC1: 服务商单号 | AD1: 目的地国家 | AE1: 起运地邮编 | AF1: 目的地邮编 | AG1: 起运分区 | AH1: 目的分区 | AI1: 分区名称 | AJ1: 业务单状态 | AK1: 有红冲单 | AL1: 划拨单号 | AM1: 是否跨月重计 | AN1: 备注 | AO1: SKU英文 | AP1: SKU中文
B2: 606761975658 | C2: 05-14373-05460 | D2: 947270 | E2: 304113-52-EU | F2: 1 | G2: FB4 | H2: DE_DHL_RETURN_L | I2: 2026-03-19 11:25:53 | J2: 0 | K2: 11.821 | L2: FB4尾程 | M2: 超长超重附加费 | N2: 0 | O2: EUR | P2: 14 | Q2: 0 | R2: 14 | S2: 0 | T2: 14 | X2: 千克 | Y2: 0 | Z2: 德国法兰克福2仓 | AC2: 00340434648320258819 | AD2: DE | AE2: 71726 | AF2: 55459 | AM2: 是 | AN2: 【杂费加收备注:超长超重附加费】 | AO2: 52帐篷-60"x32"x80"/150*80*200cm 16mm管径 | AP2: 52帐篷-60"x32"x80"/150*80*200cm 16mm管径
B3: 606783542625 | C3: 09-14388-03807 | D3: 947270 | E3: 304114-43TENTKIT-EU | F3: 1 | G3: FB4 | H3: DE_DHL_RETURN_L | I3: 2026-03-31 13:45:56 | J3: 0 | K3: 31.5 | L3: FB4尾程 | M3: 超长超重附加费 | N3: 0 | O3: EUR | P3: 14 | Q3: 0 | R3: 14 | S3: 0 | T3: 14 | X3: 千克 | Y3: 0 | Z3: 德国法兰克福2仓 | AC3: 00340434648320290680 | AD3: DE | AE3: 37154 | AF3: 55459 | AM3: 是 | AN3: 【杂费加收备注:超长超重附加费】 | AO3: 2-in-1 Grow Tent Kit | AP3: 2合一 帐篷 套装
B4: 606785493240 | C4: 167739312226332841-1 | D4: 947270 | E4: VSE-ADD12-EU | F4: 1 | G4: FB4 | H4: DE_DHL_RETURN_L | I4: 2026-04-01 14:50:27 | J4: 12.5 | K4: 12.5 | L4: FB4尾程 | M4: 高速公路费 | N4: 0 | O4: EUR | P4: 0.19 | Q4: 0 | R4: 0.19 | S4: 0 | T4: 0.19 | X4: 千克 | Y4: 12.5 | Z4: 德国法兰克福2仓 | AA4: PQ_F1127_20260101 | AC4: 00340434648320294268 | AD4: DE | AE4: 99974 | AF4: 55459 | AO4: Desumidificador AeroDrain D12 | AP4: AeroDrain WiFi除湿机_12L_欧版
B5: 606785493240 | C5: 167739312226332841-1 | D5: 947270 | E5: VSE-ADD12-EU | F5: 1 | G5: FB4 | H5: DE_DHL_RETURN_L | I5: 2026-04-01 14:50:27 | J5: 12.5 | K5: 12.5 | L5: FB4尾程 | M5: 回邮运费 | N5: 0 | O5: EUR | P5: 4.11 | Q5: 0 | R5: 3.37 | S5: 0 | T5: 3.37 | X5: 千克 | Y5: 12.5 | Z5: 德国法兰克福2仓 | AA5: PQ_F1127_20260101 | AC5: 00340434648320294268 | AD5: DE | AE5: 99974 | AF5: 55459 | AG5: PZ_DE_DHL_Paket_Domestic_DE_德国仓 | AH5: OZ_DE_法兰2仓 | AO5: Desumidificador AeroDrain D12 | AP5: AeroDrain WiFi除湿机_12L_欧版
B6: 606785493240 | C6: 167739312226332841-1 | D6: 947270 | E6: VSE-ADD12-EU | F6: 1 | G6: FB4 | H6: DE_DHL_RETURN_L | I6: 2026-04-01 14:50:27 | J6: 0 | K6: 12.5 | L6: GRS_配送_其它费 | M6: 燃油附加费 | N6: 0 | O6: EUR | P6: 0.04 | Q6: 0 | R6: 0.04 | S6: 0 | T6: 0.04 | Z6: 德国法兰克福2仓 | AA6: v6 | AC6: 00340434648320294268 | AD6: DE | AE6: 99974 | AF6: 55459 | AN6: 【燃油率:0.0125】 | AO6: Desumidificador AeroDrain D12 | AP6: AeroDrain WiFi除湿机_12L_欧版
B7: 606785550265 | C7: 167831206272971807-1 | D7: 947270 | E7: VSFD6500-EU | F7: 1 | G7: FB4 | H7: DE_DHL_RETURN_L | I7: 2026-04-01 15:19:37 | J7: 11 | K7: 11 | L7: FB4尾程 | M7: 高速公路费 | N7: 0 | O7: EUR | P7: 0.19 | Q7: 0 | R7: 0.19 | S7: 0 | T7: 0.19 | X7: 千克 | Y7: 11 | Z7: 德国法兰克福2仓 | AA7: PQ_F1127_20260101 | AC7: 00340434648320294275 | AD7: DE | AE7: 39179 | AF7: 55459 | AO7: VSFD6500 630W | AP7: 欧规 VSFD6500可拆卸630W LED灯(加远红,紫外,串联)
B8: 606785550265 | C8: 167831206272971807-1 | D8: 947270 | E8: VSFD6500-EU | F8: 1 | G8: FB4 | H8: DE_DHL_RETURN_L | I8: 2026-04-01 15:19:37 | J8: 11 | K8: 11 | L8: FB4尾程 | M8: 回邮运费 | N8: 0 | O8: EUR | P8: 4.11 | Q8: 0 | R8: 3.37 | S8: 0 | T8: 3.37 | X8: 千克 | Y8: 11 | Z8: 德国法兰克福2仓 | AA8: PQ_F1127_20260101 | AC8: 00340434648320294275 | AD8: DE | AE8: 39179 | AF8: 55459 | AG8: PZ_DE_DHL_Paket_Domestic_DE_德国仓 | AH8: OZ_DE_法兰2仓 | AO8: VSFD6500 630W | AP8: 欧规 VSFD6500可拆卸630W LED灯(加远红,紫外,串联)
B9: 606785550265 | C9: 167831206272971807-1 | D9: 947270 | E9: VSFD6500-EU | F9: 1 | G9: FB4 | H9: DE_DHL_RETURN_L | I9: 2026-04-01 15:19:37 | J9: 0 | K9: 11 | L9: GRS_配送_其它费 | M9: 燃油附加费 | N9: 0 | O9: EUR | P9: 0.04 | Q9: 0 | R9: 0.04 | S9: 0 | T9: 0.04 | Z9: 德国法兰克福2仓 | AA9: v6 | AC9: 00340434648320294275 | AD9: DE | AE9: 39179 | AF9: 55459 | AN9: 【燃油率:0.0125】 | AO9: VSFD6500 630W | AP9: 欧规 VSFD6500可拆卸630W LED灯(加远红,紫外,串联)
B10: 606786902873 | C10: 01-14446-00032 | D10: 947270 | E10: VSA150SE-E25-EU | F10: 1 | G10: FB4 | H10: DE_DHL_RETURN_L | I10: 2026-04-02 10:54:07 | J10: 3.2 | K10: 3.17 | L10: FB4尾程 | M10: 高速公路费 | N10: 0 | O10: EUR | P10: 0.19 | Q10: 0 | R10: 0.19 | S10: 0 | T10: 0.19 | X10: 千克 | Y10: 3.17 | Z10: 德国法兰克福2仓 | AA10: PQ_F1127_20260101 | AC10: 00340434648320296804 | AD10: DE | AE10: 32423 | AF10: 55459 | AO10: AeroLight A150SE, LED Grow Light 150W with Integrated Circulation Fan & GrowHub Controller E25
B11: 606786902873 | C11: 01-14446-00032 | D11: 947270 | E11: VSA150SE-E25-EU | F11: 1 | G11: FB4 | H11: DE_DHL_RETURN_L | I11: 2026-04-02 10:54:07 | J11: 3.2 | K11: 3.17 | L11: FB4尾程 | M11: 回邮运费 | N11: 0 | O11: EUR | P11: 4.11 | Q11: 0 | R11: 3.37 | S11: 0 | T11: 3.37 | X11: 千克 | Y11: 3.17 | Z11: 德国法兰克福2仓 | AA11: PQ_F1127_20260101 | AC11: 00340434648320296804 | AD11: DE | AE11: 32423 | AF11: 55459 | AG11: PZ_DE_DHL_Paket_Domestic_DE_德国仓 | AH11: OZ_DE_法兰2仓 | AO11: AeroLight A150SE, LED Grow Light 150W with Integrated Circulation Fan & GrowHub Controller E25
B12: 606786902873 | C12: 01-14446-00032 | D12: 947270 | E12: VSA150SE-E25-EU | F12: 1 | G12: FB4 | H12: DE_DHL_RETURN_L | I12: 2026-04-02 10:54:07 | J12: 0 | K12: 3.17 | L12: GRS_配送_其它费 | M12: 燃油附加费 | N12: 0 | O12: EUR | P12: 0.04 | Q12: 0 | R12: 0.04 | S12: 0 | T12: 0.04 | Z12: 德国法兰克福2仓 | AA12: v6 | AC12: 00340434648320296804 | AD12: DE | AE12: 32423 | AF12: 55459 | AN12: 【燃油率:0.0125】 | AO12: AeroLight A150SE, LED Grow Light 150W with Integrated Circulation Fan & GrowHub Controller E25
B13: 606788393243 | C13: 09-14428-79871 | D13: 947270 | E13: 330301-EU | F13: 2 | G13: FB4 | H13: DE_DHL_RETURN_L | I13: 2026-04-03 10:22:50 | J13: 1 | K13: 0.91 | L13: FB4尾程 | M13: 高速公路费 | N13: 0 | O13: EUR | P13: 0.19 | Q13: 0 | R13: 0.19 | S13: 0 | T13: 0.19 | X13: 千克 | Y13: 0.91 | Z13: 德国法兰克福2仓 | AA13: PQ_F1127_20260101 | AC13: 00340434648320298990 | AD13: DE | AE13: 15517 | AF13: 55459 | AO13: Dual digital display heating pad 10" x 20.75"
B14: 606788393243 | C14: 09-14428-79871 | D14: 947270 | E14: 330301-EU | F14: 2 | G14: FB4 | H14: DE_DHL_RETURN_L | I14: 2026-04-03 10:22:50 | J14: 1 | K14: 0.91 | L14: FB4尾程 | M14: 回邮运费 | N14: 0 | O14: EUR | P14: 4.11 | Q14: 0 | R14: 3.37 | S14: 0 | T14: 3.37 | X14: 千克 | Y14: 0.91 | Z14: 德国法兰克福2仓 | AA14: PQ_F1127_20260101 | AC14: 00340434648320298990 | AD14: DE | AE14: 15517 | AF14: 55459 | AG14: PZ_DE_DHL_Paket_Domestic_DE_德国仓 | AH14: OZ_DE_法兰2仓 | AO14: Dual digital display heating pad 10" x 20.75"
B15: 606788393243 | C15: 09-14428-79871 | D15: 947270 | E15: 330301-EU | F15: 2 | G15: FB4 | H15: DE_DHL_RETURN_L | I15: 2026-04-03 10:22:50 | J15: 0 | K15: 0.91 | L15: GRS_配送_其它费 | M15: 燃油附加费 | N15: 0 | O15: EUR | P15: 0.04 | Q15: 0 | R15: 0.04 | S15: 0 | T15: 0.04 | Z15: 德国法兰克福2仓 | AA15: v6 | AC15: 00340434648320298990 | AD15: DE | AE15: 15517 | AF15: 55459 | AN15: 【燃油率:0.0125】 | AO15: Dual digital display heating pad 10" x 20.75"
B16: 606788555781 | C16: 302-0146966-3921961(606788555781) | D16: 947270 | E16: VSF-AWD4X2-EU | F16: 1 | G16: FB4 | H16: DE_DHL_RETURN_L | I16: 2026-04-03 11:37:09 | J16: 0 | K16: 0.61 | L16: FB4尾程 | M16: 高速公路费 | N16: 0 | O16: EUR | P16: 0 | Q16: 0 | R16: 0 | S16: 0 | T16: 0 | X16: 千克 | Y16: 0 | Z16: 德国法兰克福2仓 | AA16: PQ_F1127_20260101 | AD16: DE | AE16: 42369 | AF16: 55459 | AK16: 是 | AO16: AeroWave D4, 4” Grow Tent Clip Fan with Detachable Hook
B17: 606788555781 | C17: 302-0146966-3921961(606788555781) | D17: 947270 | E17: VSF-AWD4X2-EU | F17: 1 | G17: FB4 | H17: DE_DHL_RETURN_L | I17: 2026-04-03 11:37:09 | J17: 0 | K17: 0.61 | L17: FB4尾程 | M17: 回邮运费 | N17: 0 | O17: EUR | P17: 0 | Q17: 0 | R17: 0 | S17: 0 | T17: 0 | X17: 千克 | Y17: 0 | Z17: 德国法兰克福2仓 | AA17: PQ_F1127_20260101 | AD17: DE | AE17: 42369 | AF17: 55459 | AK17: 是 | AO17: AeroWave D4, 4” Grow Tent Clip Fan with Detachable Hook
B18: 606788555781 | C18: 302-0146966-3921961(606788555781) | D18: 947270 | E18: VSF-AWD4X2-EU | F18: 1 | G18: FB4 | H18: DE_DHL_RETURN_L | I18: 2026-04-03 11:37:09 | J18: 0 | K18: 0.61 | L18: GRS_配送_其它费 | M18: 燃油附加费 | N18: 0 | O18: EUR | P18: 0 | Q18: 0 | R18: 0 | S18: 0 | T18: 0 | Z18: 德国法兰克福2仓 | AA18: v6 | AD18: DE | AE18: 42369 | AF18: 55459 | AK18: 是 | AN18: 【燃油率:0.0125】 | AO18: AeroWave D4, 4” Grow Tent Clip Fan with Detachable Hook
B19: 606788565041 | C19: 302-0146966-3921961 | D19: 947270 | E19: VSF-AWD4X2-EU | F19: 1 | G19: FB4 | H19: DE_DHL_RETURN_L | I19: 2026-04-03 11:42:25 | J19: 0.7 | K19: 0.61 | L19: FB4尾程 | M19: 高速公路费 | N19: 0 | O19: EUR | P19: 0.19 | Q19: 0 | R19: 0.19 | S19: 0 | T19: 0.19 | X19: 千克 | Y19: 0.61 | Z19: 德国法兰克福2仓 | AA19: PQ_F1127_20260101 | AC19: 00340434648320299072 | AD19: DE | AE19: 42369 | AF19: 55459 | AO19: AeroWave D4, 4” Grow Tent Clip Fan with Detachable Hook
B20: 606788565041 | C20: 302-0146966-3921961 | D20: 947270 | E20: VSF-AWD4X2-EU | F20: 1 | G20: FB4 | H20: DE_DHL_RETURN_L | I20: 2026-04-03 11:42:25 | J20: 0.7 | K20: 0.61 | L20: FB4尾程 | M20: 回邮运费 | N20: 0 | O20: EUR | P20: 4.11 | Q20: 0 | R20: 3.37 | S20: 0 | T20: 3.37 | X20: 千克 | Y20: 0.61 | Z20: 德国法兰克福2仓 | AA20: PQ_F1127_20260101 | AC20: 00340434648320299072 | AD20: DE | AE20: 42369 | AF20: 55459 | AG20: PZ_DE_DHL_Paket_Domestic_DE_德国仓 | AH20: OZ_DE_法兰2仓 | AO20: AeroWave D4, 4” Grow Tent Clip Fan with Detachable Hook
B21: 606788565041 | C21: 302-0146966-3921961 | D21: 947270 | E21: VSF-AWD4X2-EU | F21: 1 | G21: FB4 | H21: DE_DHL_RETURN_L | I21: 2026-04-03 11:42:25 | J21: 0 | K21: 0.61 | L21: GRS_配送_其它费 | M21: 燃油附加费 | N21: 0 | O21: EUR | P21: 0.04 | Q21: 0 | R21: 0.04 | S21: 0 | T21: 0.04 | Z21: 德国法兰克福2仓 | AA21: v6 | AC21: 00340434648320299072 | AD21: DE | AE21: 42369 | AF21: 55459 | AN21: 【燃油率:0.0125】 | AO21: AeroWave D4, 4” Grow Tent Clip Fan with Detachable Hook
B22: 606789082979 | C22: 167666197655731804-1 | D22: 947270 | E22: VSL-LL100 | F22: 1 | G22: FB4 | H22: DE_DHL_RETURN_L | I22: 2026-04-03 18:07:13 | J22: 3 | K22: 3 | L22: FB4尾程 | M22: 高速公路费 | N22: 0 | O22: EUR | P22: 0.19 | Q22: 0 | R22: 0.19 | S22: 0 | T22: 0.19 | X22: 千克 | Y22: 3 | Z22: 德国法兰克福2仓 | AA22: PQ_F1127_20260101 | AC22: 00340434648320300815 | AD22: DE | AE22: 44789 | AF22: 55459
B23: 606789082979 | C23: 167666197655731804-1 | D23: 947270 | E23: VSL-LL100 | F23: 1 | G23: FB4 | H23: DE_DHL_RETURN_L | I23: 2026-04-03 18:07:13 | J23: 3 | K23: 3 | L23: FB4尾程 | M23: 回邮运费 | N23: 0 | O23: EUR | P23: 4.11 | Q23: 0 | R23: 3.37 | S23: 0 | T23: 3.37 | X23: 千克 | Y23: 3 | Z23: 德国法兰克福2仓 | AA23: PQ_F1127_20260101 | AC23: 00340434648320300815 | AD23: DE | AE23: 44789 | AF23: 55459 | AG23: PZ_DE_DHL_Paket_Domestic_DE_德国仓 | AH23: OZ_DE_法兰2仓
B24: 606789082979 | C24: 167666197655731804-1 | D24: 947270 | E24: VSL-LL100 | F24: 1 | G24: FB4 | H24: DE_DHL_RETURN_L | I24: 2026-04-03 18:07:13 | J24: 0 | K24: 3 | L24: GRS_配送_其它费 | M24: 燃油附加费 | N24: 0 | O24: EUR | P24: 0.04 | Q24: 0 | R24: 0.04 | S24: 0 | T24: 0.04 | Z24: 德国法兰克福2仓 | AA24: v6 | AC24: 00340434648320300815 | AD24: DE | AE24: 44789 | AF24: 55459 | AN24: 【燃油率:0.0125】
B25: 606790618821 | C25: 19-14421-20177 | D25: 947270 | E25: VSF-AWE6-G2-EU | F25: 1 | G25: FB4 | H25: DE_DHL_RETURN_L | I25: 2026-04-05 11:19:28 | J25: 1.1 | K25: 1.1 | L25: FB4尾程 | M25: 高速公路费 | N25: 0 | O25: EUR | P25: 0.19 | Q25: 0 | R25: 0.19 | S25: 0 | T25: 0.19 | X25: 千克 | Y25: 1.1 | Z25: 德国法兰克福2仓 | AA25: PQ_F1127_20260101 | AC25: 00340434648320301911 | AD25: DE | AE25: 37154 | AF25: 55459 | AO25: AeroWave E6 Grow Tent Fan 6”
B26: 606790618821 | C26: 19-14421-20177 | D26: 947270 | E26: VSF-AWE6-G2-EU | F26: 1 | G26: FB4 | H26: DE_DHL_RETURN_L | I26: 2026-04-05 11:19:28 | J26: 1.1 | K26: 1.1 | L26: FB4尾程 | M26: 回邮运费 | N26: 0 | O26: EUR | P26: 4.11 | Q26: 0 | R26: 3.37 | S26: 0 | T26: 3.37 | X26: 千克 | Y26: 1.1 | Z26: 德国法兰克福2仓 | AA26: PQ_F1127_20260101 | AC26: 00340434648320301911 | AD26: DE | AE26: 37154 | AF26: 55459 | AG26: PZ_DE_DHL_Paket_Domestic_DE_德国仓 | AH26: OZ_DE_法兰2仓 | AO26: AeroWave E6 Grow Tent Fan 6”
B27: 606790618821 | C27: 19-14421-20177 | D27: 947270 | E27: VSF-AWE6-G2-EU | F27: 1 | G27: FB4 | H27: DE_DHL_RETURN_L | I27: 2026-04-05 11:19:28 | J27: 0 | K27: 1.1 | L27: GRS_配送_其它费 | M27: 燃油附加费 | N27: 0 | O27: EUR | P27: 0.04 | Q27: 0 | R27: 0.04 | S27: 0 | T27: 0.04 | Z27: 德国法兰克福2仓 | AA27: v6 | AC27: 00340434648320301911 | AD27: DE | AE27: 37154 | AF27: 55459 | AN27: 【燃油率:0.0125】 | AO27: AeroWave E6 Grow Tent Fan 6”
B28: 606793790813 | C28: 167739320279396597-1 | D28: 947270 | E28: TN-22-EU;VC-0001-EU;VSE-ASU075-EU;VSF-AWD4-EU | F28: 2;1;1;2 | G28: FB4 | H28: DE_DHL_RETURN_L | I28: 2026-04-07 09:56:18 | J28: 1.2 | K28: 1.2 | L28: FB4尾程 | M28: 高速公路费 | N28: 0 | O28: EUR | P28: 0.19 | Q28: 0 | R28: 0.19 | S28: 0 | T28: 0.19 | X28: 千克 | Y28: 1.2 | Z28: 德国法兰克福2仓 | AA28: PQ_F1127_20260101 | AC28: 00340434648320302604 | AD28: DE | AE28: 38268 | AF28: 55459 | AO28: 2 x 2Ft. Elastic Trellis Netting;2-Pcs. Grow Tent Vent Cover 4inch;AeroStream U075 USB Humidifier;黑色4寸夹扇 | AP28: 弹力爬藤网 2*2FT(网格尺寸：10*10cm);防尘罩-4-Inch两个装;;黑色4寸夹扇
B29: 606793790813 | C29: 167739320279396597-1 | D29: 947270 | E29: TN-22-EU;VC-0001-EU;VSE-ASU075-EU;VSF-AWD4-EU | F29: 2;1;1;2 | G29: FB4 | H29: DE_DHL_RETURN_L | I29: 2026-04-07 09:56:18 | J29: 1.2 | K29: 1.2 | L29: FB4尾程 | M29: 回邮运费 | N29: 0 | O29: EUR | P29: 4.11 | Q29: 0 | R29: 3.37 | S29: 0 | T29: 3.37 | X29: 千克 | Y29: 1.2 | Z29: 德国法兰克福2仓 | AA29: PQ_F1127_20260101 | AC29: 00340434648320302604 | AD29: DE | AE29: 38268 | AF29: 55459 | AG29: PZ_DE_DHL_Paket_Domestic_DE_德国仓 | AH29: OZ_DE_法兰2仓 | AO29: 2 x 2Ft. Elastic Trellis Netting;2-Pcs. Grow Tent Vent Cover 4inch;AeroStream U075 USB Humidifier;黑色4寸夹扇 | AP29: 弹力爬藤网 2*2FT(网格尺寸：10*10cm);防尘罩-4-Inch两个装;;黑色4寸夹扇
B30: 606793790813 | C30: 167739320279396597-1 | D30: 947270 | E30: TN-22-EU;VC-0001-EU;VSE-ASU075-EU;VSF-AWD4-EU | F30: 2;1;1;2 | G30: FB4 | H30: DE_DHL_RETURN_L | I30: 2026-04-07 09:56:18 | J30: 0 | K30: 1.2 | L30: GRS_配送_其它费 | M30: 燃油附加费 | N30: 0 | O30: EUR | P30: 0.04 | Q30: 0 | R30: 0.04 | S30: 0 | T30: 0.04 | Z30: 德国法兰克福2仓 | AA30: v6 | AC30: 00340434648320302604 | AD30: DE | AE30: 38268 | AF30: 55459 | AN30: 【燃油率:0.0125】 | AO30: 2 x 2Ft. Elastic Trellis Netting;2-Pcs. Grow Tent Vent Cover 4inch;AeroStream U075 USB Humidifier;黑色4寸夹扇 | AP30: 弹力爬藤网 2*2FT(网格尺寸：10*10cm);防尘罩-4-Inch两个装;;黑色4寸夹扇
B31: 606794821152 | C31: 167553788697789080-1 | D31: 947270 | E31: 306146-0820-EU;VSV-AZG8-EU | F31: 1;1 | G31: FB4 | H31: DE_DHL_RETURN_L | I31: 2026-04-07 16:37:52 | J31: 12.7 | K31: 12.7 | L31: FB4尾程 | M31: 高速公路费 | N31: 0 | O31: EUR | P31: 0.19 | Q31: 0 | R31: 0.19 | S31: 0 | T31: 0.19 | X31: 千克 | Y31: 12.7 | Z31: 德国法兰克福2仓 | AA31: PQ_F1127_20260101 | AC31: 00340434648320304189 | AD31: DE | AE31: 33165 | AF31: 55459 | AO31: 8-Inch Air Carbon Filter for Odor Control, black;AeroZesh G8 8-inch Inline Duct Fan with E12 Speed Controller | AP31: VIVOSUN钢印滤芯 黑色8寸;欧版 低端8寸金属底座风机G8+E12线控
B32: 606794821152 | C32: 167553788697789080-1 | D32: 947270 | E32: 306146-0820-EU;VSV-AZG8-EU | F32: 1;1 | G32: FB4 | H32: DE_DHL_RETURN_L | I32: 2026-04-07 16:37:52 | J32: 12.7 | K32: 12.7 | L32: FB4尾程 | M32: 回邮运费 | N32: 0 | O32: EUR | P32: 4.11 | Q32: 0 | R32: 3.37 | S32: 0 | T32: 3.37 | X32: 千克 | Y32: 12.7 | Z32: 德国法兰克福2仓 | AA32: PQ_F1127_20260101 | AC32: 00340434648320304189 | AD32: DE | AE32: 33165 | AF32: 55459 | AG32: PZ_DE_DHL_Paket_Domestic_DE_德国仓 | AH32: OZ_DE_法兰2仓 | AO32: 8-Inch Air Carbon Filter for Odor Control, black;AeroZesh G8 8-inch Inline Duct Fan with E12 Speed Controller | AP32: VIVOSUN钢印滤芯 黑色8寸;欧版 低端8寸金属底座风机G8+E12线控
B33: 606794821152 | C33: 167553788697789080-1 | D33: 947270 | E33: 306146-0820-EU;VSV-AZG8-EU | F33: 1;1 | G33: FB4 | H33: DE_DHL_RETURN_L | I33: 2026-04-07 16:37:52 | J33: 0 | K33: 12.7 | L33: GRS_配送_其它费 | M33: 燃油附加费 | N33: 0 | O33: EUR | P33: 0.04 | Q33: 0 | R33: 0.04 | S33: 0 | T33: 0.04 | Z33: 德国法兰克福2仓 | AA33: v6 | AC33: 00340434648320304189 | AD33: DE | AE33: 33165 | AF33: 55459 | AN33: 【燃油率:0.0125】 | AO33: 8-Inch Air Carbon Filter for Odor Control, black;AeroZesh G8 8-inch Inline Duct Fan with E12 Speed Controller | AP33: VIVOSUN钢印滤芯 黑色8寸;欧版 低端8寸金属底座风机G8+E12线控
B34: 606795959273 | C34: 167739219616094550-1 | D34: 947270 | E34: VSF-AWE6-G2X2-EU | F34: 1 | G34: FB4 | H34: DE_DHL_RETURN_L | I34: 2026-04-08 10:01:39 | J34: 2.2 | K34: 2.13 | L34: FB4尾程 | M34: 高速公路费 | N34: 0 | O34: EUR | P34: 0.19 | Q34: 0 | R34: 0.19 | S34: 0 | T34: 0.19 | X34: 千克 | Y34: 2.13 | Z34: 德国法兰克福2仓 | AA34: PQ_F1127_20260101 | AC34: 00340434648320309597 | AD34: DE | AE34: 48599 | AF34: 55459 | AO34: Aerowave E6 Gen 2 black clip fan 2-pack
B35: 606795959273 | C35: 167739219616094550-1 | D35: 947270 | E35: VSF-AWE6-G2X2-EU | F35: 1 | G35: FB4 | H35: DE_DHL_RETURN_L | I35: 2026-04-08 10:01:39 | J35: 2.2 | K35: 2.13 | L35: FB4尾程 | M35: 回邮运费 | N35: 0 | O35: EUR | P35: 4.11 | Q35: 0 | R35: 3.37 | S35: 0 | T35: 3.37 | X35: 千克 | Y35: 2.13 | Z35: 德国法兰克福2仓 | AA35: PQ_F1127_20260101 | AC35: 00340434648320309597 | AD35: DE | AE35: 48599 | AF35: 55459 | AG35: PZ_DE_DHL_Paket_Domestic_DE_德国仓 | AH35: OZ_DE_法兰2仓 | AO35: Aerowave E6 Gen 2 black clip fan 2-pack
B36: 606795959273 | C36: 167739219616094550-1 | D36: 947270 | E36: VSF-AWE6-G2X2-EU | F36: 1 | G36: FB4 | H36: DE_DHL_RETURN_L | I36: 2026-04-08 10:01:39 | J36: 0 | K36: 2.13 | L36: GRS_配送_其它费 | M36: 燃油附加费 | N36: 0 | O36: EUR | P36: 0.04 | Q36: 0 | R36: 0.04 | S36: 0 | T36: 0.04 | Z36: 德国法兰克福2仓 | AA36: v6 | AC36: 00340434648320309597 | AD36: DE | AE36: 48599 | AF36: 55459 | AN36: 【燃油率:0.0125】 | AO36: Aerowave E6 Gen 2 black clip fan 2-pack
B37: 606795959285 | C37: 167739219616094550-2 | D37: 947270 | E37: VSVC-AZT6E42AP-EU | F37: 1 | G37: FB4 | H37: DE_DHL_RETURN_L | I37: 2026-04-08 10:01:39 | J37: 10 | K37: 10 | L37: FB4尾程 | M37: 高速公路费 | N37: 0 | O37: EUR | P37: 0.19 | Q37: 0 | R37: 0.19 | S37: 0 | T37: 0.19 | X37: 千克 | Y37: 10 | Z37: 德国法兰克福2仓 | AA37: PQ_F1127_20260101 | AC37: 00340434648320309580 | AD37: DE | AE37: 48599 | AF37: 55459 | AO37: Smart Air Filtration Kit Pro 6″ | AP37: AeroZesh T6 金属底座风机 6寸 + GrowHub E42A+控制器+黑色滤芯6寸+黑色风管6寸8ft 欧版
B38: 606795959285 | C38: 167739219616094550-2 | D38: 947270 | E38: VSVC-AZT6E42AP-EU | F38: 1 | G38: FB4 | H38: DE_DHL_RETURN_L | I38: 2026-04-08 10:01:39 | J38: 10 | K38: 10 | L38: FB4尾程 | M38: 回邮运费 | N38: 0 | O38: EUR | P38: 4.11 | Q38: 0 | R38: 3.37 | S38: 0 | T38: 3.37 | X38: 千克 | Y38: 10 | Z38: 德国法兰克福2仓 | AA38: PQ_F1127_20260101 | AC38: 00340434648320309580 | AD38: DE | AE38: 48599 | AF38: 55459 | AG38: PZ_DE_DHL_Paket_Domestic_DE_德国仓 | AH38: OZ_DE_法兰2仓 | AO38: Smart Air Filtration Kit Pro 6″ | AP38: AeroZesh T6 金属底座风机 6寸 + GrowHub E42A+控制器+黑色滤芯6寸+黑色风管6寸8ft 欧版
B39: 606795959285 | C39: 167739219616094550-2 | D39: 947270 | E39: VSVC-AZT6E42AP-EU | F39: 1 | G39: FB4 | H39: DE_DHL_RETURN_L | I39: 2026-04-08 10:01:39 | J39: 0 | K39: 10 | L39: GRS_配送_其它费 | M39: 燃油附加费 | N39: 0 | O39: EUR | P39: 0.04 | Q39: 0 | R39: 0.04 | S39: 0 | T39: 0.04 | Z39: 德国法兰克福2仓 | AA39: v6 | AC39: 00340434648320309580 | AD39: DE | AE39: 48599 | AF39: 55459 | AN39: 【燃油率:0.0125】 | AO39: Smart Air Filtration Kit Pro 6″ | AP39: AeroZesh T6 金属底座风机 6寸 + GrowHub E42A+控制器+黑色滤芯6寸+黑色风管6寸8ft 欧版
B40: 606795959309 | C40: 167739219616094550-3 | D40: 947270 | E40: 304113-P558-EU | F40: 1 | G40: FB4 | H40: DE_DHL_RETURN_L | I40: 2026-04-08 10:01:39 | J40: 24 | K40: 24 | L40: FB4尾程 | M40: 高速公路费 | N40: 0 | O40: EUR | P40: 0.19 | Q40: 0 | R40: 0.19 | S40: 0 | T40: 0.19 | X40: 千克 | Y40: 24 | Z40: 德国法兰克福2仓 | AA40: PQ_F1127_20260101 | AC40: 00340434648320309573 | AD40: DE | AE40: 48599 | AF40: 55459 | AO40: P558 60"×60"×80" PRO Grow Tent | AP40: P558 Pro款55帐篷-60"x60"x80"/150*150*200cm 22mm管径
B41: 606795959309 | C41: 167739219616094550-3 | D41: 947270 | E41: 304113-P558-EU | F41: 1 | G41: FB4 | H41: DE_DHL_RETURN_L | I41: 2026-04-08 10:01:39 | J41: 24 | K41: 24 | L41: FB4尾程 | M41: 回邮运费 | N41: 0 | O41: EUR | P41: 4.11 | Q41: 0 | R41: 3.37 | S41: 0 | T41: 3.37 | X41: 千克 | Y41: 24 | Z41: 德国法兰克福2仓 | AA41: PQ_F1127_20260101 | AC41: 00340434648320309573 | AD41: DE | AE41: 48599 | AF41: 55459 | AG41: PZ_DE_DHL_Paket_Domestic_DE_德国仓 | AH41: OZ_DE_法兰2仓 | AO41: P558 60"×60"×80" PRO Grow Tent | AP41: P558 Pro款55帐篷-60"x60"x80"/150*150*200cm 22mm管径
B42: 606795959309 | C42: 167739219616094550-3 | D42: 947270 | E42: 304113-P558-EU | F42: 1 | G42: FB4 | H42: DE_DHL_RETURN_L | I42: 2026-04-08 10:01:39 | J42: 0 | K42: 24 | L42: GRS_配送_其它费 | M42: 燃油附加费 | N42: 0 | O42: EUR | P42: 0.04 | Q42: 0 | R42: 0.04 | S42: 0 | T42: 0.04 | Z42: 德国法兰克福2仓 | AA42: v6 | AC42: 00340434648320309573 | AD42: DE | AE42: 48599 | AF42: 55459 | AN42: 【燃油率:0.0125】 | AO42: P558 60"×60"×80" PRO Grow Tent | AP42: P558 Pro款55帐篷-60"x60"x80"/150*150*200cm 22mm管径
B43: 606796218295 | C43: 09-14370-80704 | D43: 947270 | E43: 306146-0412-EU | F43: 2 | G43: FB4 | H43: DE_DHL_RETURN_L | I43: 2026-04-08 11:35:44 | J43: 5.9 | K43: 5.9 | L43: FB4尾程 | M43: 高速公路费 | N43: 0 | O43: EUR | P43: 0.19 | Q43: 0 | R43: 0.19 | S43: 0 | T43: 0.19 | X43: 千克 | Y43: 5.9 | Z43: 德国法兰克福2仓 | AA43: PQ_F1127_20260101 | AC43: 00340434648320309719 | AD43: DE | AE43: 01159 | AF43: 55459 | AO43: VIVOSUN钢印滤芯 黑色4" | AP43: VIVOSUN钢印滤芯 黑色4"
B44: 606796218295 | C44: 09-14370-80704 | D44: 947270 | E44: 306146-0412-EU | F44: 2 | G44: FB4 | H44: DE_DHL_RETURN_L | I44: 2026-04-08 11:35:44 | J44: 5.9 | K44: 5.9 | L44: FB4尾程 | M44: 回邮运费 | N44: 0 | O44: EUR | P44: 4.11 | Q44: 0 | R44: 3.37 | S44: 0 | T44: 3.37 | X44: 千克 | Y44: 5.9 | Z44: 德国法兰克福2仓 | AA44: PQ_F1127_20260101 | AC44: 00340434648320309719 | AD44: DE | AE44: 01159 | AF44: 55459 | AG44: PZ_DE_DHL_Paket_Domestic_DE_德国仓 | AH44: OZ_DE_法兰2仓 | AO44: VIVOSUN钢印滤芯 黑色4" | AP44: VIVOSUN钢印滤芯 黑色4"
B45: 606796218295 | C45: 09-14370-80704 | D45: 947270 | E45: 306146-0412-EU | F45: 2 | G45: FB4 | H45: DE_DHL_RETURN_L | I45: 2026-04-08 11:35:44 | J45: 0 | K45: 5.9 | L45: GRS_配送_其它费 | M45: 燃油附加费 | N45: 0 | O45: EUR | P45: 0.04 | Q45: 0 | R45: 0.04 | S45: 0 | T45: 0.04 | Z45: 德国法兰克福2仓 | AA45: v6 | AC45: 00340434648320309719 | AD45: DE | AE45: 01159 | AF45: 55459 | AN45: 【燃油率:0.0125】 | AO45: VIVOSUN钢印滤芯 黑色4" | AP45: VIVOSUN钢印滤芯 黑色4"
B46: 606796389101 | C46: 167902835321790128 | D46: 947270 | E46: VSE-ALC08-EU | F46: 1 | G46: FB4 | H46: DE_DHL_RETURN_L | I46: 2026-04-08 14:20:43 | J46: 25.8 | K46: 25.778 | L46: FB4尾程 | M46: 高速公路费 | N46: 0 | O46: EUR | P46: 0.19 | Q46: 0 | R46: 0.19 | S46: 0 | T46: 0.19 | X46: 千克 | Y46: 25.778 | Z46: 德国法兰克福1仓 | AA46: PQ_F1127_20260101 | AC46: 00340434648320310173 | AD46: DE | AE46: 84337 | AF46: 55459 | AO46: AeroLush Air Conditioner - 8000 BTU - European Standard | AP46: AeroLush 空调_8000BTU_欧规
B47: 606796389101 | C47: 167902835321790128 | D47: 947270 | E47: VSE-ALC08-EU | F47: 1 | G47: FB4 | H47: DE_DHL_RETURN_L | I47: 2026-04-08 14:20:43 | J47: 25.8 | K47: 25.778 | L47: FB4尾程 | M47: 回邮运费 | N47: 0 | O47: EUR | P47: 4.11 | Q47: 0 | R47: 3.37 | S47: 0 | T47: 3.37 | X47: 千克 | Y47: 25.778 | Z47: 德国法兰克福1仓 | AA47: PQ_F1127_20260101 | AC47: 00340434648320310173 | AD47: DE | AE47: 84337 | AF47: 55459 | AG47: PZ_DE_DHL_Paket_Domestic_DE_德国仓 | AH47: OZ_DE_法兰2仓 | AO47: AeroLush Air Conditioner - 8000 BTU - European Standard | AP47: AeroLush 空调_8000BTU_欧规
B48: 606796389101 | C48: 167902835321790128 | D48: 947270 | E48: VSE-ALC08-EU | F48: 1 | G48: FB4 | H48: DE_DHL_RETURN_L | I48: 2026-04-08 14:20:43 | J48: 0 | K48: 25.778 | L48: GRS_配送_其它费 | M48: 燃油附加费 | N48: 0 | O48: EUR | P48: 0.04 | Q48: 0 | R48: 0.04 | S48: 0 | T48: 0.04 | Z48: 德国法兰克福1仓 | AA48: v6 | AC48: 00340434648320310173 | AD48: DE | AE48: 84337 | AF48: 55459 | AN48: 【燃油率:0.0125】 | AO48: AeroLush Air Conditioner - 8000 BTU - European Standard | AP48: AeroLush 空调_8000BTU_欧规
B49: 606796674103 | C49: 168019031635567590-1 | D49: 947270 | E49: VSF-AWD4-EU | F49: 1 | G49: FB4 | H49: DE_DHL_RETURN_L | I49: 2026-04-08 17:11:31 | J49: 0.4 | K49: 0.31 | L49: FB4尾程 | M49: 高速公路费 | N49: 0 | O49: EUR | P49: 0.19 | Q49: 0 | R49: 0.19 | S49: 0 | T49: 0.19 | X49: 千克 | Y49: 0.31 | Z49: 德国法兰克福2仓 | AA49: PQ_F1127_20260101 | AC49: 00340434648320311163 | AD49: DE | AE49: 14109 | AF49: 55459 | AO49: 黑色4寸夹扇 | AP49: 黑色4寸夹扇
B50: 606796674103 | C50: 168019031635567590-1 | D50: 947270 | E50: VSF-AWD4-EU | F50: 1 | G50: FB4 | H50: DE_DHL_RETURN_L | I50: 2026-04-08 17:11:31 | J50: 0.4 | K50: 0.31 | L50: FB4尾程 | M50: 回邮运费 | N50: 0 | O50: EUR | P50: 4.11 | Q50: 0 | R50: 3.37 | S50: 0 | T50: 3.37 | X50: 千克 | Y50: 0.31 | Z50: 德国法兰克福2仓 | AA50: PQ_F1127_20260101 | AC50: 00340434648320311163 | AD50: DE | AE50: 14109 | AF50: 55459 | AG50: PZ_DE_DHL_Paket_Domestic_DE_德国仓 | AH50: OZ_DE_法兰2仓 | AO50: 黑色4寸夹扇 | AP50: 黑色4寸夹扇
B51: 606796674103 | C51: 168019031635567590-1 | D51: 947270 | E51: VSF-AWD4-EU | F51: 1 | G51: FB4 | H51: DE_DHL_RETURN_L | I51: 2026-04-08 17:11:31 | J51: 0 | K51: 0.31 | L51: GRS_配送_其它费 | M51: 燃油附加费 | N51: 0 | O51: EUR | P51: 0.04 | Q51: 0 | R51: 0.04 | S51: 0 | T51: 0.04 | Z51: 德国法兰克福2仓 | AA51: v6 | AC51: 00340434648320311163 | AD51: DE | AE51: 14109 | AF51: 55459 | AN51: 【燃油率:0.0125】 | AO51: 黑色4寸夹扇 | AP51: 黑色4寸夹扇
B52: 606796679240 | C52: 168019031635567590-2 | D52: 947270 | E52: VSE-ASU075-EU | F52: 1 | G52: FB4 | H52: DE_DHL_RETURN_L | I52: 2026-04-08 17:15:25 | J52: 0.4 | K52: 0.4 | L52: FB4尾程 | M52: 超长超重附加费 | N52: 0 | O52: EUR | P52: 14 | Q52: 0 | R52: 14 | S52: 0 | T52: 14 | X52: 千克 | Y52: 0.4 | Z52: 德国法兰克福2仓 | AA52: PQ_F1127_20260101 | AC52: 00340434648320311736 | AD52: DE | AE52: 14109 | AF52: 55459 | AO52: AeroStream U075 USB Humidifier
B53: 606796679240 | C53: 168019031635567590-2 | D53: 947270 | E53: VSE-ASU075-EU | F53: 1 | G53: FB4 | H53: DE_DHL_RETURN_L | I53: 2026-04-08 17:15:25 | J53: 0.4 | K53: 0.4 | L53: FB4尾程 | M53: 高速公路费 | N53: 0 | O53: EUR | P53: 0.19 | Q53: 0 | R53: 0.19 | S53: 0 | T53: 0.19 | X53: 千克 | Y53: 0.4 | Z53: 德国法兰克福2仓 | AA53: PQ_F1127_20260101 | AC53: 00340434648320311736 | AD53: DE | AE53: 14109 | AF53: 55459 | AO53: AeroStream U075 USB Humidifier
B54: 606796679240 | C54: 168019031635567590-2 | D54: 947270 | E54: VSE-ASU075-EU | F54: 1 | G54: FB4 | H54: DE_DHL_RETURN_L | I54: 2026-04-08 17:15:25 | J54: 0.4 | K54: 0.4 | L54: FB4尾程 | M54: 回邮运费 | N54: 0 | O54: EUR | P54: 4.11 | Q54: 0 | R54: 3.37 | S54: 0 | T54: 3.37 | X54: 千克 | Y54: 0.4 | Z54: 德国法兰克福2仓 | AA54: PQ_F1127_20260101 | AC54: 00340434648320311736 | AD54: DE | AE54: 14109 | AF54: 55459 | AG54: PZ_DE_DHL_Paket_Domestic_DE_德国仓 | AH54: OZ_DE_法兰2仓 | AO54: AeroStream U075 USB Humidifier
B55: 606796679240 | C55: 168019031635567590-2 | D55: 947270 | E55: VSE-ASU075-EU | F55: 1 | G55: FB4 | H55: DE_DHL_RETURN_L | I55: 2026-04-08 17:15:25 | J55: 0 | K55: 0.4 | L55: GRS_配送_其它费 | M55: 燃油附加费 | N55: 0 | O55: EUR | P55: 0.04 | Q55: 0 | R55: 0.04 | S55: 0 | T55: 0.04 | Z55: 德国法兰克福2仓 | AA55: v6 | AC55: 00340434648320311736 | AD55: DE | AE55: 14109 | AF55: 55459 | AN55: 【燃油率:0.0125】 | AO55: AeroStream U075 USB Humidifier
B56: 606797394937 | C56: 167831208152020348-1 | D56: 947270 | E56: VSC-GCC4-EU | F56: 1 | G56: FB4 | H56: DE_DHL_RETURN_L | I56: 2026-04-09 09:12:52 | J56: 0.3 | K56: 0.262 | L56: FB4尾程 | M56: 高速公路费 | N56: 0 | O56: EUR | P56: 0.19 | Q56: 0 | R56: 0.19 | S56: 0 | T56: 0.19 | X56: 千克 | Y56: 0.262 | Z56: 德国法兰克福2仓 | AA56: PQ_F1127_20260101 | AC56: 00340434648320313136 | AD56: DE | AE56: 59427 | AF56: 55459 | AO56: GrowCam C4 | AP56: GrowCam 摄像头 400W 2K-欧版
B57: 606797394937 | C57: 167831208152020348-1 | D57: 947270 | E57: VSC-GCC4-EU | F57: 1 | G57: FB4 | H57: DE_DHL_RETURN_L | I57: 2026-04-09 09:12:52 | J57: 0.3 | K57: 0.262 | L57: FB4尾程 | M57: 回邮运费 | N57: 0 | O57: EUR | P57: 4.11 | Q57: 0 | R57: 3.37 | S57: 0 | T57: 3.37 | X57: 千克 | Y57: 0.262 | Z57: 德国法兰克福2仓 | AA57: PQ_F1127_20260101 | AC57: 00340434648320313136 | AD57: DE | AE57: 59427 | AF57: 55459 | AG57: PZ_DE_DHL_Paket_Domestic_DE_德国仓 | AH57: OZ_DE_法兰2仓 | AO57: GrowCam C4 | AP57: GrowCam 摄像头 400W 2K-欧版
B58: 606797394937 | C58: 167831208152020348-1 | D58: 947270 | E58: VSC-GCC4-EU | F58: 1 | G58: FB4 | H58: DE_DHL_RETURN_L | I58: 2026-04-09 09:12:52 | J58: 0 | K58: 0.262 | L58: GRS_配送_其它费 | M58: 燃油附加费 | N58: 0 | O58: EUR | P58: 0.04 | Q58: 0 | R58: 0.04 | S58: 0 | T58: 0.04 | Z58: 德国法兰克福2仓 | AA58: v6 | AC58: 00340434648320313136 | AD58: DE | AE58: 59427 | AF58: 55459 | AN58: 【燃油率:0.0125】 | AO58: GrowCam C4 | AP58: GrowCam 摄像头 400W 2K-欧版
B59: 606799574290 | C59: 01-14453-34916 | D59: 947270 | E59: VSE-ATW70-EU | F59: 1 | G59: FB4 | H59: DE_DHL_RETURN_L | I59: 2026-04-10 13:42:51 | J59: 3.3 | K59: 3.216 | L59: FB4尾程 | M59: 高速公路费 | N59: 0 | O59: EUR | P59: 0.19 | Q59: 0 | R59: 0.19 | S59: 0 | T59: 0.19 | X59: 千克 | Y59: 3.216 | Z59: 德国法兰克福2仓 | AA59: PQ_F1127_20260101 | AC59: 00340434648320317080 | AD59: DE | AE59: 65187 | AF59: 55459 | AO59: AeroFlux Heater 70w | AP59: AeroFlux Heater 70w
B60: 606799574290 | C60: 01-14453-34916 | D60: 947270 | E60: VSE-ATW70-EU | F60: 1 | G60: FB4 | H60: DE_DHL_RETURN_L | I60: 2026-04-10 13:42:51 | J60: 3.3 | K60: 3.216 | L60: FB4尾程 | M60: 回邮运费 | N60: 0 | O60: EUR | P60: 4.11 | Q60: 0 | R60: 3.37 | S60: 0 | T60: 3.37 | X60: 千克 | Y60: 3.216 | Z60: 德国法兰克福2仓 | AA60: PQ_F1127_20260101 | AC60: 00340434648320317080 | AD60: DE | AE60: 65187 | AF60: 55459 | AG60: PZ_DE_DHL_Paket_Domestic_DE_德国仓 | AH60: OZ_DE_法兰2仓 | AO60: AeroFlux Heater 70w | AP60: AeroFlux Heater 70w
B61: 606799574290 | C61: 01-14453-34916 | D61: 947270 | E61: VSE-ATW70-EU | F61: 1 | G61: FB4 | H61: DE_DHL_RETURN_L | I61: 2026-04-10 13:42:51 | J61: 0 | K61: 3.216 | L61: GRS_配送_其它费 | M61: 燃油附加费 | N61: 0 | O61: EUR | P61: 0.04 | Q61: 0 | R61: 0.04 | S61: 0 | T61: 0.04 | Z61: 德国法兰克福2仓 | AA61: v6 | AC61: 00340434648320317080 | AD61: DE | AE61: 65187 | AF61: 55459 | AN61: 【燃油率:0.0125】 | AO61: AeroFlux Heater 70w | AP61: AeroFlux Heater 70w
B62: 606799738537 | C62: 167856961849739622-1 | D62: 947270 | E62: VSAW200-EU | F62: 1 | G62: FB4 | H62: DE_DHL_RETURN_L | I62: 2026-04-10 15:15:40 | J62: 10.5 | K62: 10.5 | L62: FB4尾程 | M62: 高速公路费 | N62: 0 | O62: EUR | P62: 0.19 | Q62: 0 | R62: 0.19 | S62: 0 | T62: 0.19 | X62: 千克 | Y62: 10.5 | Z62: 德国法兰克福2仓 | AA62: PQ_F1127_20260101 | AC62: 00340434648320317141 | AD62: DE | AE62: 66564 | AF62: 55459 | AO62: AeroLight Wing AW200 | AP62: 压铸款200W生长灯
B63: 606799738537 | C63: 167856961849739622-1 | D63: 947270 | E63: VSAW200-EU | F63: 1 | G63: FB4 | H63: DE_DHL_RETURN_L | I63: 2026-04-10 15:15:40 | J63: 10.5 | K63: 10.5 | L63: FB4尾程 | M63: 回邮运费 | N63: 0 | O63: EUR | P63: 4.11 | Q63: 0 | R63: 3.37 | S63: 0 | T63: 3.37 | X63: 千克 | Y63: 10.5 | Z63: 德国法兰克福2仓 | AA63: PQ_F1127_20260101 | AC63: 00340434648320317141 | AD63: DE | AE63: 66564 | AF63: 55459 | AG63: PZ_DE_DHL_Paket_Domestic_DE_德国仓 | AH63: OZ_DE_法兰2仓 | AO63: AeroLight Wing AW200 | AP63: 压铸款200W生长灯
B64: 606799738537 | C64: 167856961849739622-1 | D64: 947270 | E64: VSAW200-EU | F64: 1 | G64: FB4 | H64: DE_DHL_RETURN_L | I64: 2026-04-10 15:15:40 | J64: 0 | K64: 10.5 | L64: GRS_配送_其它费 | M64: 燃油附加费 | N64: 0 | O64: EUR | P64: 0.04 | Q64: 0 | R64: 0.04 | S64: 0 | T64: 0.04 | Z64: 德国法兰克福2仓 | AA64: v6 | AC64: 00340434648320317141 | AD64: DE | AE64: 66564 | AF64: 55459 | AN64: 【燃油率:0.0125】 | AO64: AeroLight Wing AW200 | AP64: 压铸款200W生长灯
B65: 606799738549 | C65: 167856961849739622-2 | D65: 947270 | E65: PS-002-EU;332823-100J-EU;TN-33-EU;VC-0001-EU;311001-5x5-EU;VSF-AWE6-G2-EU | F65: 1;1;1;1;1;1 | G65: FB4 | H65: DE_DHL_RETURN_L | I65: 2026-04-10 15:15:40 | J65: 5.5 | K65: 5.5 | L65: FB4尾程 | M65: 高速公路费 | N65: 0 | O65: EUR | P65: 0.19 | Q65: 0 | R65: 0.19 | S65: 0 | T65: 0.19 | X65: 千克 | Y65: 5.5 | Z65: 德国法兰克福2仓 | AA65: PQ_F1127_20260101 | AC65: 00340434648320317134 | AD65: DE | AE65: 66564 | AF65: 55459 | AO65: 黑绿配色花枝剪1个装;328 Feet (100m) PE-Coated Twist Ties;3 x 3Ft. Elastic Trellis Netting;2-Pcs. Grow Tent Vent Cover 4inch;AeroWave E6 Grow Tent Fan 6” | AP65: 黑绿配色花枝剪1个装;园林扎线-100米;弹力爬藤网 3*3FT(网格尺寸：10*10cm);防尘罩-4-Inch两个装;
B66: 606799738549 | C66: 167856961849739622-2 | D66: 947270 | E66: PS-002-EU;332823-100J-EU;TN-33-EU;VC-0001-EU;311001-5x5-EU;VSF-AWE6-G2-EU | F66: 1;1;1;1;1;1 | G66: FB4 | H66: DE_DHL_RETURN_L | I66: 2026-04-10 15:15:40 | J66: 5.5 | K66: 5.5 | L66: FB4尾程 | M66: 回邮运费 | N66: 0 | O66: EUR | P66: 4.11 | Q66: 0 | R66: 3.37 | S66: 0 | T66: 3.37 | X66: 千克 | Y66: 5.5 | Z66: 德国法兰克福2仓 | AA66: PQ_F1127_20260101 | AC66: 00340434648320317134 | AD66: DE | AE66: 66564 | AF66: 55459 | AG66: PZ_DE_DHL_Paket_Domestic_DE_德国仓 | AH66: OZ_DE_法兰2仓 | AO66: 黑绿配色花枝剪1个装;328 Feet (100m) PE-Coated Twist Ties;3 x 3Ft. Elastic Trellis Netting;2-Pcs. Grow Tent Vent Cover 4inch;AeroWave E6 Grow Tent Fan 6” | AP66: 黑绿配色花枝剪1个装;园林扎线-100米;弹力爬藤网 3*3FT(网格尺寸：10*10cm);防尘罩-4-Inch两个装;
B67: 606799738549 | C67: 167856961849739622-2 | D67: 947270 | E67: PS-002-EU;332823-100J-EU;TN-33-EU;VC-0001-EU;311001-5x5-EU;VSF-AWE6-G2-EU | F67: 1;1;1;1;1;1 | G67: FB4 | H67: DE_DHL_RETURN_L | I67: 2026-04-10 15:15:40 | J67: 0 | K67: 5.5 | L67: GRS_配送_其它费 | M67: 燃油附加费 | N67: 0 | O67: EUR | P67: 0.04 | Q67: 0 | R67: 0.04 | S67: 0 | T67: 0.04 | Z67: 德国法兰克福2仓 | AA67: v6 | AC67: 00340434648320317134 | AD67: DE | AE67: 66564 | AF67: 55459 | AN67: 【燃油率:0.0125】 | AO67: 黑绿配色花枝剪1个装;328 Feet (100m) PE-Coated Twist Ties;3 x 3Ft. Elastic Trellis Netting;2-Pcs. Grow Tent Vent Cover 4inch;AeroWave E6 Grow Tent Fan 6” | AP67: 黑绿配色花枝剪1个装;园林扎线-100米;弹力爬藤网 3*3FT(网格尺寸：10*10cm);防尘罩-4-Inch两个装;
B68: 606799738550 | C68: 167856961849739622-3 | D68: 947270 | E68: VSVC-AZT4E42AP-EU | F68: 1 | G68: FB4 | H68: DE_DHL_RETURN_L | I68: 2026-04-10 15:15:40 | J68: 6.5 | K68: 6.5 | L68: FB4尾程 | M68: 高速公路费 | N68: 0 | O68: EUR | P68: 0.19 | Q68: 0 | R68: 0.19 | S68: 0 | T68: 0.19 | X68: 千克 | Y68: 6.5 | Z68: 德国法兰克福2仓 | AA68: PQ_F1127_20260101 | AC68: 00340434648320317127 | AD68: DE | AE68: 66564 | AF68: 55459 | AO68: Smart Air Filtration PRO T4 Kit 4" | AP68: AeroZesh T4 金属底座风机 4寸 + GrowHub E42A+控制器+黑色滤芯4寸+黑色风管4寸8ft 欧版
B69: 606799738550 | C69: 167856961849739622-3 | D69: 947270 | E69: VSVC-AZT4E42AP-EU | F69: 1 | G69: FB4 | H69: DE_DHL_RETURN_L | I69: 2026-04-10 15:15:40 | J69: 6.5 | K69: 6.5 | L69: FB4尾程 | M69: 回邮运费 | N69: 0 | O69: EUR | P69: 4.11 | Q69: 0 | R69: 3.37 | S69: 0 | T69: 3.37 | X69: 千克 | Y69: 6.5 | Z69: 德国法兰克福2仓 | AA69: PQ_F1127_20260101 | AC69: 00340434648320317127 | AD69: DE | AE69: 66564 | AF69: 55459 | AG69: PZ_DE_DHL_Paket_Domestic_DE_德国仓 | AH69: OZ_DE_法兰2仓 | AO69: Smart Air Filtration PRO T4 Kit 4" | AP69: AeroZesh T4 金属底座风机 4寸 + GrowHub E42A+控制器+黑色滤芯4寸+黑色风管4寸8ft 欧版
B70: 606799738550 | C70: 167856961849739622-3 | D70: 947270 | E70: VSVC-AZT4E42AP-EU | F70: 1 | G70: FB4 | H70: DE_DHL_RETURN_L | I70: 2026-04-10 15:15:40 | J70: 0 | K70: 6.5 | L70: GRS_配送_其它费 | M70: 燃油附加费 | N70: 0 | O70: EUR | P70: 0.04 | Q70: 0 | R70: 0.04 | S70: 0 | T70: 0.04 | Z70: 德国法兰克福2仓 | AA70: v6 | AC70: 00340434648320317127 | AD70: DE | AE70: 66564 | AF70: 55459 | AN70: 【燃油率:0.0125】 | AO70: Smart Air Filtration PRO T4 Kit 4" | AP70: AeroZesh T4 金属底座风机 4寸 + GrowHub E42A+控制器+黑色滤芯4寸+黑色风管4寸8ft 欧版
B71: 606799738562 | C71: 167856961849739622-4 | D71: 947270 | E71: 304113-P336-EU | F71: 1 | G71: FB4 | H71: DE_DHL_RETURN_L | I71: 2026-04-10 15:15:40 | J71: 14.5 | K71: 14.5 | L71: FB4尾程 | M71: 高速公路费 | N71: 0 | O71: EUR | P71: 0.19 | Q71: 0 | R71: 0.19 | S71: 0 | T71: 0.19 | X71: 千克 | Y71: 14.5 | Z71: 德国法兰克福2仓 | AA71: PQ_F1127_20260101 | AC71: 00340434648320317110 | AD71: DE | AE71: 66564 | AF71: 55459 | AO71: P336 36"×36"×72" PRO Grow Tent | AP71: P336 Pro款33帐篷-36"x36"x72"/90*90*180cm 22mm管径
B72: 606799738562 | C72: 167856961849739622-4 | D72: 947270 | E72: 304113-P336-EU | F72: 1 | G72: FB4 | H72: DE_DHL_RETURN_L | I72: 2026-04-10 15:15:40 | J72: 14.5 | K72: 14.5 | L72: FB4尾程 | M72: 回邮运费 | N72: 0 | O72: EUR | P72: 4.11 | Q72: 0 | R72: 3.37 | S72: 0 | T72: 3.37 | X72: 千克 | Y72: 14.5 | Z72: 德国法兰克福2仓 | AA72: PQ_F1127_20260101 | AC72: 00340434648320317110 | AD72: DE | AE72: 66564 | AF72: 55459 | AG72: PZ_DE_DHL_Paket_Domestic_DE_德国仓 | AH72: OZ_DE_法兰2仓 | AO72: P336 36"×36"×72" PRO Grow Tent | AP72: P336 Pro款33帐篷-36"x36"x72"/90*90*180cm 22mm管径
B73: 606799738562 | C73: 167856961849739622-4 | D73: 947270 | E73: 304113-P336-EU | F73: 1 | G73: FB4 | H73: DE_DHL_RETURN_L | I73: 2026-04-10 15:15:40 | J73: 0 | K73: 14.5 | L73: GRS_配送_其它费 | M73: 燃油附加费 | N73: 0 | O73: EUR | P73: 0.04 | Q73: 0 | R73: 0.04 | S73: 0 | T73: 0.04 | Z73: 德国法兰克福2仓 | AA73: v6 | AC73: 00340434648320317110 | AD73: DE | AE73: 66564 | AF73: 55459 | AN73: 【燃油率:0.0125】 | AO73: P336 36"×36"×72" PRO Grow Tent | AP73: P336 Pro款33帐篷-36"x36"x72"/90*90*180cm 22mm管径
B74: 606799833062 | C74: 168063554608859000-1 | D74: 947270 | E74: SST-1-0001-EU | F74: 1 | G74: FB4 | H74: DE_DHL_RETURN_L | I74: 2026-04-10 16:23:44 | J74: 1.2 | K74: 1.13 | L74: FB4尾程 | M74: 高速公路费 | N74: 0 | O74: EUR | P74: 0.19 | Q74: 0 | R74: 0.19 | S74: 0 | T74: 0.19 | X74: 千克 | Y74: 1.13 | Z74: 德国法兰克福2仓 | AA74: PQ_F1127_20260101 | AC74: 00340434648320317196 | AD74: DE | AE74: 58511 | AF74: 55459 | AO74: 1-Pack 40-Cell Seed Starter Trays with 1 Set of LED Lights and 10"x20.75" Seedling Heat Mat | AP74: 欧规 40孔育苗盘1套装+LED灯条1套+加热垫1套
B75: 606799833062 | C75: 168063554608859000-1 | D75: 947270 | E75: SST-1-0001-EU | F75: 1 | G75: FB4 | H75: DE_DHL_RETURN_L | I75: 2026-04-10 16:23:44 | J75: 1.2 | K75: 1.13 | L75: FB4尾程 | M75: 回邮运费 | N75: 0 | O75: EUR | P75: 4.11 | Q75: 0 | R75: 3.37 | S75: 0 | T75: 3.37 | X75: 千克 | Y75: 1.13 | Z75: 德国法兰克福2仓 | AA75: PQ_F1127_20260101 | AC75: 00340434648320317196 | AD75: DE | AE75: 58511 | AF75: 55459 | AG75: PZ_DE_DHL_Paket_Domestic_DE_德国仓 | AH75: OZ_DE_法兰2仓 | AO75: 1-Pack 40-Cell Seed Starter Trays with 1 Set of LED Lights and 10"x20.75" Seedling Heat Mat | AP75: 欧规 40孔育苗盘1套装+LED灯条1套+加热垫1套
B76: 606799833062 | C76: 168063554608859000-1 | D76: 947270 | E76: SST-1-0001-EU | F76: 1 | G76: FB4 | H76: DE_DHL_RETURN_L | I76: 2026-04-10 16:23:44 | J76: 0 | K76: 1.13 | L76: GRS_配送_其它费 | M76: 燃油附加费 | N76: 0 | O76: EUR | P76: 0.04 | Q76: 0 | R76: 0.04 | S76: 0 | T76: 0.04 | Z76: 德国法兰克福2仓 | AA76: v6 | AC76: 00340434648320317196 | AD76: DE | AE76: 58511 | AF76: 55459 | AN76: 【燃油率:0.0125】 | AO76: 1-Pack 40-Cell Seed Starter Trays with 1 Set of LED Lights and 10"x20.75" Seedling Heat Mat | AP76: 欧规 40孔育苗盘1套装+LED灯条1套+加热垫1套
B77: 606800016813 | C77: 168094472467845381-1 | D77: 947270 | E77: VST-SP2-GL-US | F77: 1 | G77: FB4 | H77: DE_DHL_RETURN_L | I77: 2026-04-10 18:23:38 | J77: 2 | K77: 1.98 | L77: FB4尾程 | M77: 高速公路费 | N77: 0 | O77: EUR | P77: 0.19 | Q77: 0 | R77: 0.19 | S77: 0 | T77: 0.19 | X77: 千克 | Y77: 1.98 | Z77: 德国法兰克福2仓 | AA77: PQ_F1127_20260101 | AC77: 00340434648320318780 | AD77: DE | AE77: 91207 | AF77: 55459
B78: 606800016813 | C78: 168094472467845381-1 | D78: 947270 | E78: VST-SP2-GL-US | F78: 1 | G78: FB4 | H78: DE_DHL_RETURN_L | I78: 2026-04-10 18:23:38 | J78: 2 | K78: 1.98 | L78: FB4尾程 | M78: 回邮运费 | N78: 0 | O78: EUR | P78: 4.11 | Q78: 0 | R78: 3.37 | S78: 0 | T78: 3.37 | X78: 千克 | Y78: 1.98 | Z78: 德国法兰克福2仓 | AA78: PQ_F1127_20260101 | AC78: 00340434648320318780 | AD78: DE | AE78: 91207 | AF78: 55459 | AG78: PZ_DE_DHL_Paket_Domestic_DE_德国仓 | AH78: OZ_DE_法兰2仓
B79: 606800016813 | C79: 168094472467845381-1 | D79: 947270 | E79: VST-SP2-GL-US | F79: 1 | G79: FB4 | H79: DE_DHL_RETURN_L | I79: 2026-04-10 18:23:38 | J79: 0 | K79: 1.98 | L79: GRS_配送_其它费 | M79: 燃油附加费 | N79: 0 | O79: EUR | P79: 0.04 | Q79: 0 | R79: 0.04 | S79: 0 | T79: 0.04 | Z79: 德国法兰克福2仓 | AA79: v6 | AC79: 00340434648320318780 | AD79: DE | AE79: 91207 | AF79: 55459 | AN79: 【燃油率:0.0125】
B80: 606801037259 | C80: 167666224499283213-1 | D80: 947270 | E80: GH-E42AP-EU | F80: 1 | G80: FB4 | H80: DE_DHL_RETURN_L | I80: 2026-04-11 16:25:59 | J80: 0.8 | K80: 0.719 | L80: FB4尾程 | M80: 高速公路费 | N80: 0 | O80: EUR | P80: 0.19 | Q80: 0 | R80: 0.19 | S80: 0 | T80: 0.19 | X80: 千克 | Y80: 0.719 | Z80: 德国法兰克福2仓 | AA80: PQ_F1127_20260101 | AC80: 00340434648320319800 | AD80: DE | AE80: 30982 | AF80: 55459 | AO80: GrowHub E42A+ Controller for Grow Tent | AP80: GrowHub E42A+ Controller 欧版
B81: 606801037259 | C81: 167666224499283213-1 | D81: 947270 | E81: GH-E42AP-EU | F81: 1 | G81: FB4 | H81: DE_DHL_RETURN_L | I81: 2026-04-11 16:25:59 | J81: 0.8 | K81: 0.719 | L81: FB4尾程 | M81: 回邮运费 | N81: 0 | O81: EUR | P81: 4.11 | Q81: 0 | R81: 3.37 | S81: 0 | T81: 3.37 | X81: 千克 | Y81: 0.719 | Z81: 德国法兰克福2仓 | AA81: PQ_F1127_20260101 | AC81: 00340434648320319800 | AD81: DE | AE81: 30982 | AF81: 55459 | AG81: PZ_DE_DHL_Paket_Domestic_DE_德国仓 | AH81: OZ_DE_法兰2仓 | AO81: GrowHub E42A+ Controller for Grow Tent | AP81: GrowHub E42A+ Controller 欧版
B82: 606801037259 | C82: 167666224499283213-1 | D82: 947270 | E82: GH-E42AP-EU | F82: 1 | G82: FB4 | H82: DE_DHL_RETURN_L | I82: 2026-04-11 16:25:59 | J82: 0 | K82: 0.719 | L82: GRS_配送_其它费 | M82: 燃油附加费 | N82: 0 | O82: EUR | P82: 0.04 | Q82: 0 | R82: 0.04 | S82: 0 | T82: 0.04 | Z82: 德国法兰克福2仓 | AA82: v6 | AC82: 00340434648320319800 | AD82: DE | AE82: 30982 | AF82: 55459 | AN82: 【燃油率:0.0125】 | AO82: GrowHub E42A+ Controller for Grow Tent | AP82: GrowHub E42A+ Controller 欧版
B83: 606801049537 | C83: 168063562930358714 | D83: 947270 | E83: VSE-ASH05-EU | F83: 1 | G83: FB4 | H83: DE_DHL_RETURN_L | I83: 2026-04-11 16:47:00 | J83: 1.8 | K83: 1.8 | L83: FB4尾程 | M83: 高速公路费 | N83: 0 | O83: EUR | P83: 0.19 | Q83: 0 | R83: 0.19 | S83: 0 | T83: 0.19 | X83: 千克 | Y83: 1.8 | Z83: 德国法兰克福2仓 | AA83: PQ_F1127_20260101 | AC83: 00340434648320319817 | AD83: DE | AE83: 63916 | AF83: 55459 | AO83: AeroStream Humidificateur pour plantes 5 l | AP83: AeroStream 5L智能Wi-Fi加湿器（SGS，单核雾化片）-欧版
B84: 606801049537 | C84: 168063562930358714 | D84: 947270 | E84: VSE-ASH05-EU | F84: 1 | G84: FB4 | H84: DE_DHL_RETURN_L | I84: 2026-04-11 16:47:00 | J84: 1.8 | K84: 1.8 | L84: FB4尾程 | M84: 回邮运费 | N84: 0 | O84: EUR | P84: 4.11 | Q84: 0 | R84: 3.37 | S84: 0 | T84: 3.37 | X84: 千克 | Y84: 1.8 | Z84: 德国法兰克福2仓 | AA84: PQ_F1127_20260101 | AC84: 00340434648320319817 | AD84: DE | AE84: 63916 | AF84: 55459 | AG84: PZ_DE_DHL_Paket_Domestic_DE_德国仓 | AH84: OZ_DE_法兰2仓 | AO84: AeroStream Humidificateur pour plantes 5 l | AP84: AeroStream 5L智能Wi-Fi加湿器（SGS，单核雾化片）-欧版
B85: 606801049537 | C85: 168063562930358714 | D85: 947270 | E85: VSE-ASH05-EU | F85: 1 | G85: FB4 | H85: DE_DHL_RETURN_L | I85: 2026-04-11 16:47:00 | J85: 0 | K85: 1.8 | L85: GRS_配送_其它费 | M85: 燃油附加费 | N85: 0 | O85: EUR | P85: 0.04 | Q85: 0 | R85: 0.04 | S85: 0 | T85: 0.04 | Z85: 德国法兰克福2仓 | AA85: v6 | AC85: 00340434648320319817 | AD85: DE | AE85: 63916 | AF85: 55459 | AN85: 【燃油率:0.0125】 | AO85: AeroStream Humidificateur pour plantes 5 l | AP85: AeroStream 5L智能Wi-Fi加湿器（SGS，单核雾化片）-欧版
B86: 606801076115 | C86: 03-14482-21234 | D86: 947270 | E86: VSVC-AZT6-EU | F86: 1 | G86: FB4 | H86: DE_DHL_RETURN_L | I86: 2026-04-11 17:28:29 | J86: 9 | K86: 9 | L86: FB4尾程 | M86: 高速公路费 | N86: 0 | O86: EUR | P86: 0.19 | Q86: 0 | R86: 0.19 | S86: 0 | T86: 0.19 | X86: 千克 | Y86: 9 | Z86: 德国法兰克福2仓 | AA86: PQ_F1127_20260101 | AC86: 00340434648320319831 | AD86: DE | AE86: 42329 | AF86: 55459 | AO86: Smart Air Filtration T6 Kit 6", AeroZesh T6 Inline Duct Fan with E12 Speed Controller
B87: 606801076115 | C87: 03-14482-21234 | D87: 947270 | E87: VSVC-AZT6-EU | F87: 1 | G87: FB4 | H87: DE_DHL_RETURN_L | I87: 2026-04-11 17:28:29 | J87: 9 | K87: 9 | L87: FB4尾程 | M87: 回邮运费 | N87: 0 | O87: EUR | P87: 4.11 | Q87: 0 | R87: 3.37 | S87: 0 | T87: 3.37 | X87: 千克 | Y87: 9 | Z87: 德国法兰克福2仓 | AA87: PQ_F1127_20260101 | AC87: 00340434648320319831 | AD87: DE | AE87: 42329 | AF87: 55459 | AG87: PZ_DE_DHL_Paket_Domestic_DE_德国仓 | AH87: OZ_DE_法兰2仓 | AO87: Smart Air Filtration T6 Kit 6", AeroZesh T6 Inline Duct Fan with E12 Speed Controller
B88: 606801076115 | C88: 03-14482-21234 | D88: 947270 | E88: VSVC-AZT6-EU | F88: 1 | G88: FB4 | H88: DE_DHL_RETURN_L | I88: 2026-04-11 17:28:29 | J88: 0 | K88: 9 | L88: GRS_配送_其它费 | M88: 燃油附加费 | N88: 0 | O88: EUR | P88: 0.04 | Q88: 0 | R88: 0.04 | S88: 0 | T88: 0.04 | Z88: 德国法兰克福2仓 | AA88: v6 | AC88: 00340434648320319831 | AD88: DE | AE88: 42329 | AF88: 55459 | AN88: 【燃油率:0.0125】 | AO88: Smart Air Filtration T6 Kit 6", AeroZesh T6 Inline Duct Fan with E12 Speed Controller
B89: 606801665439 | C89: 167713500546586903 | D89: 947270 | E89: VST-SP2-GL-EU | F89: 1 | G89: FB4 | H89: DE_DHL_RETURN_L | I89: 2026-04-12 11:37:02 | J89: 2.1 | K89: 2.014 | L89: FB4尾程 | M89: 高速公路费 | N89: 0 | O89: EUR | P89: 0.19 | Q89: 0 | R89: 0.19 | S89: 0 | T89: 0.19 | X89: 千克 | Y89: 2.014 | Z89: 德国法兰克福1仓 | AA89: PQ_F1127_20260101 | AC89: 00340434648320319855 | AD89: DE | AE89: 54578 | AF89: 55459 | AO89: Grow Tent High CFM Kit 100-150cm | AP89: 帐篷伸缩支撑杆100-150cm
B90: 606801665439 | C90: 167713500546586903 | D90: 947270 | E90: VST-SP2-GL-EU | F90: 1 | G90: FB4 | H90: DE_DHL_RETURN_L | I90: 2026-04-12 11:37:02 | J90: 2.1 | K90: 2.014 | L90: FB4尾程 | M90: 回邮运费 | N90: 0 | O90: EUR | P90: 4.11 | Q90: 0 | R90: 3.37 | S90: 0 | T90: 3.37 | X90: 千克 | Y90: 2.014 | Z90: 德国法兰克福1仓 | AA90: PQ_F1127_20260101 | AC90: 00340434648320319855 | AD90: DE | AE90: 54578 | AF90: 55459 | AG90: PZ_DE_DHL_Paket_Domestic_DE_德国仓 | AH90: OZ_DE_法兰2仓 | AO90: Grow Tent High CFM Kit 100-150cm | AP90: 帐篷伸缩支撑杆100-150cm
B91: 606801665439 | C91: 167713500546586903 | D91: 947270 | E91: VST-SP2-GL-EU | F91: 1 | G91: FB4 | H91: DE_DHL_RETURN_L | I91: 2026-04-12 11:37:02 | J91: 0 | K91: 2.014 | L91: GRS_配送_其它费 | M91: 燃油附加费 | N91: 0 | O91: EUR | P91: 0.04 | Q91: 0 | R91: 0.04 | S91: 0 | T91: 0.04 | Z91: 德国法兰克福1仓 | AA91: v6 | AC91: 00340434648320319855 | AD91: DE | AE91: 54578 | AF91: 55459 | AN91: 【燃油率:0.0125】 | AO91: Grow Tent High CFM Kit 100-150cm | AP91: 帐篷伸缩支撑杆100-150cm
B92: 606803401324 | C92: 167666197655731804-5 | D92: 947270 | E92: VSE-ASH09-EU | F92: 1 | G92: FB4 | H92: DE_DHL_RETURN_L | I92: 2026-04-13 10:38:51 | J92: 3.4 | K92: 3.35 | L92: FB4尾程 | M92: 高速公路费 | N92: 0 | O92: EUR | P92: 0.19 | Q92: 0 | R92: 0.19 | S92: 0 | T92: 0.19 | X92: 千克 | Y92: 3.35 | Z92: 德国法兰克福2仓 | AA92: PQ_F1127_20260101 | AC92: 00340434648320320615 | AD92: DE | AE92: 44789 | AF92: 55459 | AO92: AeroStream - Humidificador para plantas (9 L) | AP92: AeroStream 9L智能Wi-Fi加湿器（SGS，单核雾化片）-欧版
B93: 606803401324 | C93: 167666197655731804-5 | D93: 947270 | E93: VSE-ASH09-EU | F93: 1 | G93: FB4 | H93: DE_DHL_RETURN_L | I93: 2026-04-13 10:38:51 | J93: 3.4 | K93: 3.35 | L93: FB4尾程 | M93: 回邮运费 | N93: 0 | O93: EUR | P93: 4.11 | Q93: 0 | R93: 3.37 | S93: 0 | T93: 3.37 | X93: 千克 | Y93: 3.35 | Z93: 德国法兰克福2仓 | AA93: PQ_F1127_20260101 | AC93: 00340434648320320615 | AD93: DE | AE93: 44789 | AF93: 55459 | AG93: PZ_DE_DHL_Paket_Domestic_DE_德国仓 | AH93: OZ_DE_法兰2仓 | AO93: AeroStream - Humidificador para plantas (9 L) | AP93: AeroStream 9L智能Wi-Fi加湿器（SGS，单核雾化片）-欧版
B94: 606803401324 | C94: 167666197655731804-5 | D94: 947270 | E94: VSE-ASH09-EU | F94: 1 | G94: FB4 | H94: DE_DHL_RETURN_L | I94: 2026-04-13 10:38:51 | J94: 0 | K94: 3.35 | L94: GRS_配送_其它费 | M94: 燃油附加费 | N94: 0 | O94: EUR | P94: 0.04 | Q94: 0 | R94: 0.04 | S94: 0 | T94: 0.04 | Z94: 德国法兰克福2仓 | AA94: v6 | AC94: 00340434648320320615 | AD94: DE | AE94: 44789 | AF94: 55459 | AN94: 【燃油率:0.0125】 | AO94: AeroStream - Humidificador para plantas (9 L) | AP94: AeroStream 9L智能Wi-Fi加湿器（SGS，单核雾化片）-欧版
B95: 606804439210 | C95: 404-1611652-5576303 | D95: 947270 | E95: VSE-ASH09-EU | F95: 1 | G95: FB4 | H95: DE_DHL_RETURN_L | I95: 2026-04-13 17:16:54 | J95: 3.4 | K95: 3.346 | L95: FB4尾程 | M95: 高速公路费 | N95: 0 | O95: EUR | P95: 0.19 | Q95: 0 | R95: 0.19 | S95: 0 | T95: 0.19 | X95: 千克 | Y95: 3.346 | Z95: 德国法兰克福2仓 | AA95: PQ_F1127_20260101 | AC95: 00340434648320324378 | AD95: DE | AE95: 20149 | AF95: 55459 | AO95: AeroStream - Humidificador para plantas (9 L) | AP95: AeroStream 9L智能Wi-Fi加湿器（SGS，单核雾化片）-欧版
B96: 606804439210 | C96: 404-1611652-5576303 | D96: 947270 | E96: VSE-ASH09-EU | F96: 1 | G96: FB4 | H96: DE_DHL_RETURN_L | I96: 2026-04-13 17:16:54 | J96: 3.4 | K96: 3.346 | L96: FB4尾程 | M96: 回邮运费 | N96: 0 | O96: EUR | P96: 4.11 | Q96: 0 | R96: 3.37 | S96: 0 | T96: 3.37 | X96: 千克 | Y96: 3.346 | Z96: 德国法兰克福2仓 | AA96: PQ_F1127_20260101 | AC96: 00340434648320324378 | AD96: DE | AE96: 20149 | AF96: 55459 | AG96: PZ_DE_DHL_Paket_Domestic_DE_德国仓 | AH96: OZ_DE_法兰2仓 | AO96: AeroStream - Humidificador para plantas (9 L) | AP96: AeroStream 9L智能Wi-Fi加湿器（SGS，单核雾化片）-欧版
B97: 606804439210 | C97: 404-1611652-5576303 | D97: 947270 | E97: VSE-ASH09-EU | F97: 1 | G97: FB4 | H97: DE_DHL_RETURN_L | I97: 2026-04-13 17:16:54 | J97: 0 | K97: 3.346 | L97: GRS_配送_其它费 | M97: 燃油附加费 | N97: 0 | O97: EUR | P97: 0.04 | Q97: 0 | R97: 0.04 | S97: 0 | T97: 0.04 | Z97: 德国法兰克福2仓 | AA97: v6 | AC97: 00340434648320324378 | AD97: DE | AE97: 20149 | AF97: 55459 | AN97: 【燃油率:0.0125】 | AO97: AeroStream - Humidificador para plantas (9 L) | AP97: AeroStream 9L智能Wi-Fi加湿器（SGS，单核雾化片）-欧版
B98: 606804687228 | C98: 168063593800435797-1 | D98: 947270 | E98: VSL-LRSF50-4 | F98: 1 | G98: FB4 | H98: DE_DHL_RETURN_L | I98: 2026-04-13 19:11:44 | J98: 1.4 | K98: 1.361 | L98: FB4尾程 | M98: 高速公路费 | N98: 0 | O98: EUR | P98: 0.19 | Q98: 0 | R98: 0.19 | S98: 0 | T98: 0.19 | X98: 千克 | Y98: 1.361 | Z98: 德国法兰克福2仓 | AA98: PQ_F1127_20260101 | AC98: 00340434648320329229 | AD98: DE | AE98: 46562 | AF98: 55459
B99: 606804687228 | C99: 168063593800435797-1 | D99: 947270 | E99: VSL-LRSF50-4 | F99: 1 | G99: FB4 | H99: DE_DHL_RETURN_L | I99: 2026-04-13 19:11:44 | J99: 1.4 | K99: 1.361 | L99: FB4尾程 | M99: 回邮运费 | N99: 0 | O99: EUR | P99: 4.11 | Q99: 0 | R99: 3.37 | S99: 0 | T99: 3.37 | X99: 千克 | Y99: 1.361 | Z99: 德国法兰克福2仓 | AA99: PQ_F1127_20260101 | AC99: 00340434648320329229 | AD99: DE | AE99: 46562 | AF99: 55459 | AG99: PZ_DE_DHL_Paket_Domestic_DE_德国仓 | AH99: OZ_DE_法兰2仓
B100: 606804687228 | C100: 168063593800435797-1 | D100: 947270 | E100: VSL-LRSF50-4 | F100: 1 | G100: FB4 | H100: DE_DHL_RETURN_L | I100: 2026-04-13 19:11:44 | J100: 0 | K100: 1.361 | L100: GRS_配送_其它费 | M100: 燃油附加费 | N100: 0 | O100: EUR | P100: 0.04 | Q100: 0 | R100: 0.04 | S100: 0 | T100: 0.04 | Z100: 德国法兰克福2仓 | AA100: v6 | AC100: 00340434648320329229 | AD100: DE | AE100: 46562 | AF100: 55459 | AN100: 【燃油率:0.0125】
...

Sheet 出库订单 (2)
A1: 出库时间 | B1: 业务单号 | C1: 客户单号 | D1: 下单子账号 | E1: SKU | F1: SKU数量 | G1: 服务类别 | H1: 服务产品 | I1: 计费时间 | J1: 计费重 | K1: 实重 | L1: 费用类型 | M1: 费用名称 | N1: 库龄 | O1: 币种 | P1: 计费金额 | Q1: 优惠金额 | R1: 应收金额 | S1: 含代收代付税费 | T1: 可开票金额 | U1: 计算公式 | V1: 数字公式 | W1: 产品类型 | X1: 计费单位 | Y1: 计费数量 | Z1: 计费地点 | AA1: 报价单编号 | AB1: 优惠券信息 | AC1: 服务商单号 | AD1: 目的地国家 | AE1: 起运地邮编 | AF1: 目的地邮编 | AG1: 起运分区 | AH1: 目的分区 | AI1: 分区名称 | AJ1: 业务单状态 | AK1: 有红冲单 | AL1: 划拨单号 | AM1: 是否跨月重计 | AN1: 备注 | AO1: SKU英文 | AP1: SKU中文 | AQ1: 平台
B2: 606761975658 | C2: 05-14373-05460 | D2: 947270 | E2: 304113-52-EU | F2: 1 | G2: FB4 | H2: DE_DHL_RETURN_L | I2: 2026-03-19 11:25:53 | J2: 0 | K2: 11.821 | L2: FB4尾程 | M2: 超长超重附加费 | N2: 0 | O2: EUR | P2: 14 | Q2: 0 | R2: 14 | S2: 0 | T2: 14 | X2: 千克 | Y2: 0 | Z2: 德国法兰克福2仓 | AC2: 00340434648320258819 | AD2: DE | AE2: 71726 | AF2: 55459 | AM2: 是 | AN2: 【杂费加收备注:超长超重附加费】 | AO2: 52帐篷-60"x32"x80"/150*80*200cm 16mm管径 | AP2: 52帐篷-60"x32"x80"/150*80*200cm 16mm管径 | AQ2: vs-ebay-de
B3: 606783542625 | C3: 09-14388-03807 | D3: 947270 | E3: 304114-43TENTKIT-EU | F3: 1 | G3: FB4 | H3: DE_DHL_RETURN_L | I3: 2026-03-31 13:45:56 | J3: 0 | K3: 31.5 | L3: FB4尾程 | M3: 超长超重附加费 | N3: 0 | O3: EUR | P3: 14 | Q3: 0 | R3: 14 | S3: 0 | T3: 14 | X3: 千克 | Y3: 0 | Z3: 德国法兰克福2仓 | AC3: 00340434648320290680 | AD3: DE | AE3: 37154 | AF3: 55459 | AM3: 是 | AN3: 【杂费加收备注:超长超重附加费】 | AO3: 2-in-1 Grow Tent Kit | AP3: 2合一 帐篷 套装 | AQ3: vs-ebay-de
B4: 606785493240 | C4: 167739312226332841-1 | D4: 947270 | E4: VSE-ADD12-EU | F4: 1 | G4: FB4 | H4: DE_DHL_RETURN_L | I4: 2026-04-01 14:50:27 | J4: 12.5 | K4: 12.5 | L4: FB4尾程 | M4: 高速公路费 | N4: 0 | O4: EUR | P4: 0.19 | Q4: 0 | R4: 0.19 | S4: 0 | T4: 0.19 | X4: 千克 | Y4: 12.5 | Z4: 德国法兰克福2仓 | AA4: PQ_F1127_20260101 | AC4: 00340434648320294268 | AD4: DE | AE4: 99974 | AF4: 55459 | AO4: Desumidificador AeroDrain D12 | AP4: AeroDrain WiFi除湿机_12L_欧版 | AQ4: vs-官网-de
B5: 606785493240 | C5: 167739312226332841-1 | D5: 947270 | E5: VSE-ADD12-EU | F5: 1 | G5: FB4 | H5: DE_DHL_RETURN_L | I5: 2026-04-01 14:50:27 | J5: 12.5 | K5: 12.5 | L5: FB4尾程 | M5: 回邮运费 | N5: 0 | O5: EUR | P5: 4.11 | Q5: 0 | R5: 3.37 | S5: 0 | T5: 3.37 | X5: 千克 | Y5: 12.5 | Z5: 德国法兰克福2仓 | AA5: PQ_F1127_20260101 | AC5: 00340434648320294268 | AD5: DE | AE5: 99974 | AF5: 55459 | AG5: PZ_DE_DHL_Paket_Domestic_DE_德国仓 | AH5: OZ_DE_法兰2仓 | AO5: Desumidificador AeroDrain D12 | AP5: AeroDrain WiFi除湿机_12L_欧版 | AQ5: vs-官网-de
B6: 606785493240 | C6: 167739312226332841-1 | D6: 947270 | E6: VSE-ADD12-EU | F6: 1 | G6: FB4 | H6: DE_DHL_RETURN_L | I6: 2026-04-01 14:50:27 | J6: 0 | K6: 12.5 | L6: GRS_配送_其它费 | M6: 燃油附加费 | N6: 0 | O6: EUR | P6: 0.04 | Q6: 0 | R6: 0.04 | S6: 0 | T6: 0.04 | Z6: 德国法兰克福2仓 | AA6: v6 | AC6: 00340434648320294268 | AD6: DE | AE6: 99974 | AF6: 55459 | AN6: 【燃油率:0.0125】 | AO6: Desumidificador AeroDrain D12 | AP6: AeroDrain WiFi除湿机_12L_欧版 | AQ6: vs-官网-de
B7: 606785550265 | C7: 167831206272971807-1 | D7: 947270 | E7: VSFD6500-EU | F7: 1 | G7: FB4 | H7: DE_DHL_RETURN_L | I7: 2026-04-01 15:19:37 | J7: 11 | K7: 11 | L7: FB4尾程 | M7: 高速公路费 | N7: 0 | O7: EUR | P7: 0.19 | Q7: 0 | R7: 0.19 | S7: 0 | T7: 0.19 | X7: 千克 | Y7: 11 | Z7: 德国法兰克福2仓 | AA7: PQ_F1127_20260101 | AC7: 00340434648320294275 | AD7: DE | AE7: 39179 | AF7: 55459 | AO7: VSFD6500 630W | AP7: 欧规 VSFD6500可拆卸630W LED灯(加远红,紫外,串联) | AQ7: vs-官网-de
B8: 606785550265 | C8: 167831206272971807-1 | D8: 947270 | E8: VSFD6500-EU | F8: 1 | G8: FB4 | H8: DE_DHL_RETURN_L | I8: 2026-04-01 15:19:37 | J8: 11 | K8: 11 | L8: FB4尾程 | M8: 回邮运费 | N8: 0 | O8: EUR | P8: 4.11 | Q8: 0 | R8: 3.37 | S8: 0 | T8: 3.37 | X8: 千克 | Y8: 11 | Z8: 德国法兰克福2仓 | AA8: PQ_F1127_20260101 | AC8: 00340434648320294275 | AD8: DE | AE8: 39179 | AF8: 55459 | AG8: PZ_DE_DHL_Paket_Domestic_DE_德国仓 | AH8: OZ_DE_法兰2仓 | AO8: VSFD6500 630W | AP8: 欧规 VSFD6500可拆卸630W LED灯(加远红,紫外,串联) | AQ8: vs-官网-de
B9: 606785550265 | C9: 167831206272971807-1 | D9: 947270 | E9: VSFD6500-EU | F9: 1 | G9: FB4 | H9: DE_DHL_RETURN_L | I9: 2026-04-01 15:19:37 | J9: 0 | K9: 11 | L9: GRS_配送_其它费 | M9: 燃油附加费 | N9: 0 | O9: EUR | P9: 0.04 | Q9: 0 | R9: 0.04 | S9: 0 | T9: 0.04 | Z9: 德国法兰克福2仓 | AA9: v6 | AC9: 00340434648320294275 | AD9: DE | AE9: 39179 | AF9: 55459 | AN9: 【燃油率:0.0125】 | AO9: VSFD6500 630W | AP9: 欧规 VSFD6500可拆卸630W LED灯(加远红,紫外,串联) | AQ9: vs-官网-de
B10: 606786902873 | C10: 01-14446-00032 | D10: 947270 | E10: VSA150SE-E25-EU | F10: 1 | G10: FB4 | H10: DE_DHL_RETURN_L | I10: 2026-04-02 10:54:07 | J10: 3.2 | K10: 3.17 | L10: FB4尾程 | M10: 高速公路费 | N10: 0 | O10: EUR | P10: 0.19 | Q10: 0 | R10: 0.19 | S10: 0 | T10: 0.19 | X10: 千克 | Y10: 3.17 | Z10: 德国法兰克福2仓 | AA10: PQ_F1127_20260101 | AC10: 00340434648320296804 | AD10: DE | AE10: 32423 | AF10: 55459 | AO10: AeroLight A150SE, LED Grow Light 150W with Integrated Circulation Fan & GrowHub Controller E25 | AQ10: vs-ebay-de
B11: 606786902873 | C11: 01-14446-00032 | D11: 947270 | E11: VSA150SE-E25-EU | F11: 1 | G11: FB4 | H11: DE_DHL_RETURN_L | I11: 2026-04-02 10:54:07 | J11: 3.2 | K11: 3.17 | L11: FB4尾程 | M11: 回邮运费 | N11: 0 | O11: EUR | P11: 4.11 | Q11: 0 | R11: 3.37 | S11: 0 | T11: 3.37 | X11: 千克 | Y11: 3.17 | Z11: 德国法兰克福2仓 | AA11: PQ_F1127_20260101 | AC11: 00340434648320296804 | AD11: DE | AE11: 32423 | AF11: 55459 | AG11: PZ_DE_DHL_Paket_Domestic_DE_德国仓 | AH11: OZ_DE_法兰2仓 | AO11: AeroLight A150SE, LED Grow Light 150W with Integrated Circulation Fan & GrowHub Controller E25 | AQ11: vs-ebay-de
B12: 606786902873 | C12: 01-14446-00032 | D12: 947270 | E12: VSA150SE-E25-EU | F12: 1 | G12: FB4 | H12: DE_DHL_RETURN_L | I12: 2026-04-02 10:54:07 | J12: 0 | K12: 3.17 | L12: GRS_配送_其它费 | M12: 燃油附加费 | N12: 0 | O12: EUR | P12: 0.04 | Q12: 0 | R12: 0.04 | S12: 0 | T12: 0.04 | Z12: 德国法兰克福2仓 | AA12: v6 | AC12: 00340434648320296804 | AD12: DE | AE12: 32423 | AF12: 55459 | AN12: 【燃油率:0.0125】 | AO12: AeroLight A150SE, LED Grow Light 150W with Integrated Circulation Fan & GrowHub Controller E25 | AQ12: vs-ebay-de
B13: 606788393243 | C13: 09-14428-79871 | D13: 947270 | E13: 330301-EU | F13: 2 | G13: FB4 | H13: DE_DHL_RETURN_L | I13: 2026-04-03 10:22:50 | J13: 1 | K13: 0.91 | L13: FB4尾程 | M13: 高速公路费 | N13: 0 | O13: EUR | P13: 0.19 | Q13: 0 | R13: 0.19 | S13: 0 | T13: 0.19 | X13: 千克 | Y13: 0.91 | Z13: 德国法兰克福2仓 | AA13: PQ_F1127_20260101 | AC13: 00340434648320298990 | AD13: DE | AE13: 15517 | AF13: 55459 | AO13: Dual digital display heating pad 10" x 20.75" | AQ13: vs-ebay-de
B14: 606788393243 | C14: 09-14428-79871 | D14: 947270 | E14: 330301-EU | F14: 2 | G14: FB4 | H14: DE_DHL_RETURN_L | I14: 2026-04-03 10:22:50 | J14: 1 | K14: 0.91 | L14: FB4尾程 | M14: 回邮运费 | N14: 0 | O14: EUR | P14: 4.11 | Q14: 0 | R14: 3.37 | S14: 0 | T14: 3.37 | X14: 千克 | Y14: 0.91 | Z14: 德国法兰克福2仓 | AA14: PQ_F1127_20260101 | AC14: 00340434648320298990 | AD14: DE | AE14: 15517 | AF14: 55459 | AG14: PZ_DE_DHL_Paket_Domestic_DE_德国仓 | AH14: OZ_DE_法兰2仓 | AO14: Dual digital display heating pad 10" x 20.75" | AQ14: vs-ebay-de
B15: 606788393243 | C15: 09-14428-79871 | D15: 947270 | E15: 330301-EU | F15: 2 | G15: FB4 | H15: DE_DHL_RETURN_L | I15: 2026-04-03 10:22:50 | J15: 0 | K15: 0.91 | L15: GRS_配送_其它费 | M15: 燃油附加费 | N15: 0 | O15: EUR | P15: 0.04 | Q15: 0 | R15: 0.04 | S15: 0 | T15: 0.04 | Z15: 德国法兰克福2仓 | AA15: v6 | AC15: 00340434648320298990 | AD15: DE | AE15: 15517 | AF15: 55459 | AN15: 【燃油率:0.0125】 | AO15: Dual digital display heating pad 10" x 20.75" | AQ15: vs-ebay-de
B16: 606788555781 | C16: 302-0146966-3921961(606788555781) | D16: 947270 | E16: VSF-AWD4X2-EU | F16: 1 | G16: FB4 | H16: DE_DHL_RETURN_L | I16: 2026-04-03 11:37:09 | J16: 0 | K16: 0.61 | L16: FB4尾程 | M16: 高速公路费 | N16: 0 | O16: EUR | P16: 0 | Q16: 0 | R16: 0 | S16: 0 | T16: 0 | X16: 千克 | Y16: 0 | Z16: 德国法兰克福2仓 | AA16: PQ_F1127_20260101 | AD16: DE | AE16: 42369 | AF16: 55459 | AK16: 是 | AO16: AeroWave D4, 4” Grow Tent Clip Fan with Detachable Hook | AQ16: vs-Amazon-de
B17: 606788555781 | C17: 302-0146966-3921961(606788555781) | D17: 947270 | E17: VSF-AWD4X2-EU | F17: 1 | G17: FB4 | H17: DE_DHL_RETURN_L | I17: 2026-04-03 11:37:09 | J17: 0 | K17: 0.61 | L17: FB4尾程 | M17: 回邮运费 | N17: 0 | O17: EUR | P17: 0 | Q17: 0 | R17: 0 | S17: 0 | T17: 0 | X17: 千克 | Y17: 0 | Z17: 德国法兰克福2仓 | AA17: PQ_F1127_20260101 | AD17: DE | AE17: 42369 | AF17: 55459 | AK17: 是 | AO17: AeroWave D4, 4” Grow Tent Clip Fan with Detachable Hook | AQ17: vs-Amazon-de
B18: 606788555781 | C18: 302-0146966-3921961(606788555781) | D18: 947270 | E18: VSF-AWD4X2-EU | F18: 1 | G18: FB4 | H18: DE_DHL_RETURN_L | I18: 2026-04-03 11:37:09 | J18: 0 | K18: 0.61 | L18: GRS_配送_其它费 | M18: 燃油附加费 | N18: 0 | O18: EUR | P18: 0 | Q18: 0 | R18: 0 | S18: 0 | T18: 0 | Z18: 德国法兰克福2仓 | AA18: v6 | AD18: DE | AE18: 42369 | AF18: 55459 | AK18: 是 | AN18: 【燃油率:0.0125】 | AO18: AeroWave D4, 4” Grow Tent Clip Fan with Detachable Hook | AQ18: vs-Amazon-de
B19: 606788565041 | C19: 302-0146966-3921961 | D19: 947270 | E19: VSF-AWD4X2-EU | F19: 1 | G19: FB4 | H19: DE_DHL_RETURN_L | I19: 2026-04-03 11:42:25 | J19: 0.7 | K19: 0.61 | L19: FB4尾程 | M19: 高速公路费 | N19: 0 | O19: EUR | P19: 0.19 | Q19: 0 | R19: 0.19 | S19: 0 | T19: 0.19 | X19: 千克 | Y19: 0.61 | Z19: 德国法兰克福2仓 | AA19: PQ_F1127_20260101 | AC19: 00340434648320299072 | AD19: DE | AE19: 42369 | AF19: 55459 | AO19: AeroWave D4, 4” Grow Tent Clip Fan with Detachable Hook | AQ19: vs-Amazon-de
B20: 606788565041 | C20: 302-0146966-3921961 | D20: 947270 | E20: VSF-AWD4X2-EU | F20: 1 | G20: FB4 | H20: DE_DHL_RETURN_L | I20: 2026-04-03 11:42:25 | J20: 0.7 | K20: 0.61 | L20: FB4尾程 | M20: 回邮运费 | N20: 0 | O20: EUR | P20: 4.11 | Q20: 0 | R20: 3.37 | S20: 0 | T20: 3.37 | X20: 千克 | Y20: 0.61 | Z20: 德国法兰克福2仓 | AA20: PQ_F1127_20260101 | AC20: 00340434648320299072 | AD20: DE | AE20: 42369 | AF20: 55459 | AG20: PZ_DE_DHL_Paket_Domestic_DE_德国仓 | AH20: OZ_DE_法兰2仓 | AO20: AeroWave D4, 4” Grow Tent Clip Fan with Detachable Hook | AQ20: vs-Amazon-de
B21: 606788565041 | C21: 302-0146966-3921961 | D21: 947270 | E21: VSF-AWD4X2-EU | F21: 1 | G21: FB4 | H21: DE_DHL_RETURN_L | I21: 2026-04-03 11:42:25 | J21: 0 | K21: 0.61 | L21: GRS_配送_其它费 | M21: 燃油附加费 | N21: 0 | O21: EUR | P21: 0.04 | Q21: 0 | R21: 0.04 | S21: 0 | T21: 0.04 | Z21: 德国法兰克福2仓 | AA21: v6 | AC21: 00340434648320299072 | AD21: DE | AE21: 42369 | AF21: 55459 | AN21: 【燃油率:0.0125】 | AO21: AeroWave D4, 4” Grow Tent Clip Fan with Detachable Hook | AQ21: vs-Amazon-de
B22: 606789082979 | C22: 167666197655731804-1 | D22: 947270 | E22: VSL-LL100 | F22: 1 | G22: FB4 | H22: DE_DHL_RETURN_L | I22: 2026-04-03 18:07:13 | J22: 3 | K22: 3 | L22: FB4尾程 | M22: 高速公路费 | N22: 0 | O22: EUR | P22: 0.19 | Q22: 0 | R22: 0.19 | S22: 0 | T22: 0.19 | X22: 千克 | Y22: 3 | Z22: 德国法兰克福2仓 | AA22: PQ_F1127_20260101 | AC22: 00340434648320300815 | AD22: DE | AE22: 44789 | AF22: 55459 | AQ22: vs-官网-de
B23: 606789082979 | C23: 167666197655731804-1 | D23: 947270 | E23: VSL-LL100 | F23: 1 | G23: FB4 | H23: DE_DHL_RETURN_L | I23: 2026-04-03 18:07:13 | J23: 3 | K23: 3 | L23: FB4尾程 | M23: 回邮运费 | N23: 0 | O23: EUR | P23: 4.11 | Q23: 0 | R23: 3.37 | S23: 0 | T23: 3.37 | X23: 千克 | Y23: 3 | Z23: 德国法兰克福2仓 | AA23: PQ_F1127_20260101 | AC23: 00340434648320300815 | AD23: DE | AE23: 44789 | AF23: 55459 | AG23: PZ_DE_DHL_Paket_Domestic_DE_德国仓 | AH23: OZ_DE_法兰2仓 | AQ23: vs-官网-de
B24: 606789082979 | C24: 167666197655731804-1 | D24: 947270 | E24: VSL-LL100 | F24: 1 | G24: FB4 | H24: DE_DHL_RETURN_L | I24: 2026-04-03 18:07:13 | J24: 0 | K24: 3 | L24: GRS_配送_其它费 | M24: 燃油附加费 | N24: 0 | O24: EUR | P24: 0.04 | Q24: 0 | R24: 0.04 | S24: 0 | T24: 0.04 | Z24: 德国法兰克福2仓 | AA24: v6 | AC24: 00340434648320300815 | AD24: DE | AE24: 44789 | AF24: 55459 | AN24: 【燃油率:0.0125】 | AQ24: vs-官网-de
B25: 606790618821 | C25: 19-14421-20177 | D25: 947270 | E25: VSF-AWE6-G2-EU | F25: 1 | G25: FB4 | H25: DE_DHL_RETURN_L | I25: 2026-04-05 11:19:28 | J25: 1.1 | K25: 1.1 | L25: FB4尾程 | M25: 高速公路费 | N25: 0 | O25: EUR | P25: 0.19 | Q25: 0 | R25: 0.19 | S25: 0 | T25: 0.19 | X25: 千克 | Y25: 1.1 | Z25: 德国法兰克福2仓 | AA25: PQ_F1127_20260101 | AC25: 00340434648320301911 | AD25: DE | AE25: 37154 | AF25: 55459 | AO25: AeroWave E6 Grow Tent Fan 6” | AQ25: vs-ebay-de
B26: 606790618821 | C26: 19-14421-20177 | D26: 947270 | E26: VSF-AWE6-G2-EU | F26: 1 | G26: FB4 | H26: DE_DHL_RETURN_L | I26: 2026-04-05 11:19:28 | J26: 1.1 | K26: 1.1 | L26: FB4尾程 | M26: 回邮运费 | N26: 0 | O26: EUR | P26: 4.11 | Q26: 0 | R26: 3.37 | S26: 0 | T26: 3.37 | X26: 千克 | Y26: 1.1 | Z26: 德国法兰克福2仓 | AA26: PQ_F1127_20260101 | AC26: 00340434648320301911 | AD26: DE | AE26: 37154 | AF26: 55459 | AG26: PZ_DE_DHL_Paket_Domestic_DE_德国仓 | AH26: OZ_DE_法兰2仓 | AO26: AeroWave E6 Grow Tent Fan 6” | AQ26: vs-ebay-de
B27: 606790618821 | C27: 19-14421-20177 | D27: 947270 | E27: VSF-AWE6-G2-EU | F27: 1 | G27: FB4 | H27: DE_DHL_RETURN_L | I27: 2026-04-05 11:19:28 | J27: 0 | K27: 1.1 | L27: GRS_配送_其它费 | M27: 燃油附加费 | N27: 0 | O27: EUR | P27: 0.04 | Q27: 0 | R27: 0.04 | S27: 0 | T27: 0.04 | Z27: 德国法兰克福2仓 | AA27: v6 | AC27: 00340434648320301911 | AD27: DE | AE27: 37154 | AF27: 55459 | AN27: 【燃油率:0.0125】 | AO27: AeroWave E6 Grow Tent Fan 6” | AQ27: vs-ebay-de
B28: 606793790813 | C28: 167739320279396597-1 | D28: 947270 | E28: TN-22-EU;VC-0001-EU;VSE-ASU075-EU;VSF-AWD4-EU | F28: 2;1;1;2 | G28: FB4 | H28: DE_DHL_RETURN_L | I28: 2026-04-07 09:56:18 | J28: 1.2 | K28: 1.2 | L28: FB4尾程 | M28: 高速公路费 | N28: 0 | O28: EUR | P28: 0.19 | Q28: 0 | R28: 0.19 | S28: 0 | T28: 0.19 | X28: 千克 | Y28: 1.2 | Z28: 德国法兰克福2仓 | AA28: PQ_F1127_20260101 | AC28: 00340434648320302604 | AD28: DE | AE28: 38268 | AF28: 55459 | AO28: 2 x 2Ft. Elastic Trellis Netting;2-Pcs. Grow Tent Vent Cover 4inch;AeroStream U075 USB Humidifier;黑色4寸夹扇 | AP28: 弹力爬藤网 2*2FT(网格尺寸：10*10cm);防尘罩-4-Inch两个装;;黑色4寸夹扇 | AQ28: vs-官网-de
B29: 606793790813 | C29: 167739320279396597-1 | D29: 947270 | E29: TN-22-EU;VC-0001-EU;VSE-ASU075-EU;VSF-AWD4-EU | F29: 2;1;1;2 | G29: FB4 | H29: DE_DHL_RETURN_L | I29: 2026-04-07 09:56:18 | J29: 1.2 | K29: 1.2 | L29: FB4尾程 | M29: 回邮运费 | N29: 0 | O29: EUR | P29: 4.11 | Q29: 0 | R29: 3.37 | S29: 0 | T29: 3.37 | X29: 千克 | Y29: 1.2 | Z29: 德国法兰克福2仓 | AA29: PQ_F1127_20260101 | AC29: 00340434648320302604 | AD29: DE | AE29: 38268 | AF29: 55459 | AG29: PZ_DE_DHL_Paket_Domestic_DE_德国仓 | AH29: OZ_DE_法兰2仓 | AO29: 2 x 2Ft. Elastic Trellis Netting;2-Pcs. Grow Tent Vent Cover 4inch;AeroStream U075 USB Humidifier;黑色4寸夹扇 | AP29: 弹力爬藤网 2*2FT(网格尺寸：10*10cm);防尘罩-4-Inch两个装;;黑色4寸夹扇 | AQ29: vs-官网-de
B30: 606793790813 | C30: 167739320279396597-1 | D30: 947270 | E30: TN-22-EU;VC-0001-EU;VSE-ASU075-EU;VSF-AWD4-EU | F30: 2;1;1;2 | G30: FB4 | H30: DE_DHL_RETURN_L | I30: 2026-04-07 09:56:18 | J30: 0 | K30: 1.2 | L30: GRS_配送_其它费 | M30: 燃油附加费 | N30: 0 | O30: EUR | P30: 0.04 | Q30: 0 | R30: 0.04 | S30: 0 | T30: 0.04 | Z30: 德国法兰克福2仓 | AA30: v6 | AC30: 00340434648320302604 | AD30: DE | AE30: 38268 | AF30: 55459 | AN30: 【燃油率:0.0125】 | AO30: 2 x 2Ft. Elastic Trellis Netting;2-Pcs. Grow Tent Vent Cover 4inch;AeroStream U075 USB Humidifier;黑色4寸夹扇 | AP30: 弹力爬藤网 2*2FT(网格尺寸：10*10cm);防尘罩-4-Inch两个装;;黑色4寸夹扇 | AQ30: vs-官网-de
B31: 606794821152 | C31: 167553788697789080-1 | D31: 947270 | E31: 306146-0820-EU;VSV-AZG8-EU | F31: 1;1 | G31: FB4 | H31: DE_DHL_RETURN_L | I31: 2026-04-07 16:37:52 | J31: 12.7 | K31: 12.7 | L31: FB4尾程 | M31: 高速公路费 | N31: 0 | O31: EUR | P31: 0.19 | Q31: 0 | R31: 0.19 | S31: 0 | T31: 0.19 | X31: 千克 | Y31: 12.7 | Z31: 德国法兰克福2仓 | AA31: PQ_F1127_20260101 | AC31: 00340434648320304189 | AD31: DE | AE31: 33165 | AF31: 55459 | AO31: 8-Inch Air Carbon Filter for Odor Control, black;AeroZesh G8 8-inch Inline Duct Fan with E12 Speed Controller | AP31: VIVOSUN钢印滤芯 黑色8寸;欧版 低端8寸金属底座风机G8+E12线控 | AQ31: vs-官网-de
B32: 606794821152 | C32: 167553788697789080-1 | D32: 947270 | E32: 306146-0820-EU;VSV-AZG8-EU | F32: 1;1 | G32: FB4 | H32: DE_DHL_RETURN_L | I32: 2026-04-07 16:37:52 | J32: 12.7 | K32: 12.7 | L32: FB4尾程 | M32: 回邮运费 | N32: 0 | O32: EUR | P32: 4.11 | Q32: 0 | R32: 3.37 | S32: 0 | T32: 3.37 | X32: 千克 | Y32: 12.7 | Z32: 德国法兰克福2仓 | AA32: PQ_F1127_20260101 | AC32: 00340434648320304189 | AD32: DE | AE32: 33165 | AF32: 55459 | AG32: PZ_DE_DHL_Paket_Domestic_DE_德国仓 | AH32: OZ_DE_法兰2仓 | AO32: 8-Inch Air Carbon Filter for Odor Control, black;AeroZesh G8 8-inch Inline Duct Fan with E12 Speed Controller | AP32: VIVOSUN钢印滤芯 黑色8寸;欧版 低端8寸金属底座风机G8+E12线控 | AQ32: vs-官网-de
B33: 606794821152 | C33: 167553788697789080-1 | D33: 947270 | E33: 306146-0820-EU;VSV-AZG8-EU | F33: 1;1 | G33: FB4 | H33: DE_DHL_RETURN_L | I33: 2026-04-07 16:37:52 | J33: 0 | K33: 12.7 | L33: GRS_配送_其它费 | M33: 燃油附加费 | N33: 0 | O33: EUR | P33: 0.04 | Q33: 0 | R33: 0.04 | S33: 0 | T33: 0.04 | Z33: 德国法兰克福2仓 | AA33: v6 | AC33: 00340434648320304189 | AD33: DE | AE33: 33165 | AF33: 55459 | AN33: 【燃油率:0.0125】 | AO33: 8-Inch Air Carbon Filter for Odor Control, black;AeroZesh G8 8-inch Inline Duct Fan with E12 Speed Controller | AP33: VIVOSUN钢印滤芯 黑色8寸;欧版 低端8寸金属底座风机G8+E12线控 | AQ33: vs-官网-de
B34: 606795959273 | C34: 167739219616094550-1 | D34: 947270 | E34: VSF-AWE6-G2X2-EU | F34: 1 | G34: FB4 | H34: DE_DHL_RETURN_L | I34: 2026-04-08 10:01:39 | J34: 2.2 | K34: 2.13 | L34: FB4尾程 | M34: 高速公路费 | N34: 0 | O34: EUR | P34: 0.19 | Q34: 0 | R34: 0.19 | S34: 0 | T34: 0.19 | X34: 千克 | Y34: 2.13 | Z34: 德国法兰克福2仓 | AA34: PQ_F1127_20260101 | AC34: 00340434648320309597 | AD34: DE | AE34: 48599 | AF34: 55459 | AO34: Aerowave E6 Gen 2 black clip fan 2-pack | AQ34: vs-官网-de
B35: 606795959273 | C35: 167739219616094550-1 | D35: 947270 | E35: VSF-AWE6-G2X2-EU | F35: 1 | G35: FB4 | H35: DE_DHL_RETURN_L | I35: 2026-04-08 10:01:39 | J35: 2.2 | K35: 2.13 | L35: FB4尾程 | M35: 回邮运费 | N35: 0 | O35: EUR | P35: 4.11 | Q35: 0 | R35: 3.37 | S35: 0 | T35: 3.37 | X35: 千克 | Y35: 2.13 | Z35: 德国法兰克福2仓 | AA35: PQ_F1127_20260101 | AC35: 00340434648320309597 | AD35: DE | AE35: 48599 | AF35: 55459 | AG35: PZ_DE_DHL_Paket_Domestic_DE_德国仓 | AH35: OZ_DE_法兰2仓 | AO35: Aerowave E6 Gen 2 black clip fan 2-pack | AQ35: vs-官网-de
B36: 606795959273 | C36: 167739219616094550-1 | D36: 947270 | E36: VSF-AWE6-G2X2-EU | F36: 1 | G36: FB4 | H36: DE_DHL_RETURN_L | I36: 2026-04-08 10:01:39 | J36: 0 | K36: 2.13 | L36: GRS_配送_其它费 | M36: 燃油附加费 | N36: 0 | O36: EUR | P36: 0.04 | Q36: 0 | R36: 0.04 | S36: 0 | T36: 0.04 | Z36: 德国法兰克福2仓 | AA36: v6 | AC36: 00340434648320309597 | AD36: DE | AE36: 48599 | AF36: 55459 | AN36: 【燃油率:0.0125】 | AO36: Aerowave E6 Gen 2 black clip fan 2-pack | AQ36: vs-官网-de
B37: 606795959285 | C37: 167739219616094550-2 | D37: 947270 | E37: VSVC-AZT6E42AP-EU | F37: 1 | G37: FB4 | H37: DE_DHL_RETURN_L | I37: 2026-04-08 10:01:39 | J37: 10 | K37: 10 | L37: FB4尾程 | M37: 高速公路费 | N37: 0 | O37: EUR | P37: 0.19 | Q37: 0 | R37: 0.19 | S37: 0 | T37: 0.19 | X37: 千克 | Y37: 10 | Z37: 德国法兰克福2仓 | AA37: PQ_F1127_20260101 | AC37: 00340434648320309580 | AD37: DE | AE37: 48599 | AF37: 55459 | AO37: Smart Air Filtration Kit Pro 6″ | AP37: AeroZesh T6 金属底座风机 6寸 + GrowHub E42A+控制器+黑色滤芯6寸+黑色风管6寸8ft 欧版 | AQ37: vs-官网-de
B38: 606795959285 | C38: 167739219616094550-2 | D38: 947270 | E38: VSVC-AZT6E42AP-EU | F38: 1 | G38: FB4 | H38: DE_DHL_RETURN_L | I38: 2026-04-08 10:01:39 | J38: 10 | K38: 10 | L38: FB4尾程 | M38: 回邮运费 | N38: 0 | O38: EUR | P38: 4.11 | Q38: 0 | R38: 3.37 | S38: 0 | T38: 3.37 | X38: 千克 | Y38: 10 | Z38: 德国法兰克福2仓 | AA38: PQ_F1127_20260101 | AC38: 00340434648320309580 | AD38: DE | AE38: 48599 | AF38: 55459 | AG38: PZ_DE_DHL_Paket_Domestic_DE_德国仓 | AH38: OZ_DE_法兰2仓 | AO38: Smart Air Filtration Kit Pro 6″ | AP38: AeroZesh T6 金属底座风机 6寸 + GrowHub E42A+控制器+黑色滤芯6寸+黑色风管6寸8ft 欧版 | AQ38: vs-官网-de
B39: 606795959285 | C39: 167739219616094550-2 | D39: 947270 | E39: VSVC-AZT6E42AP-EU | F39: 1 | G39: FB4 | H39: DE_DHL_RETURN_L | I39: 2026-04-08 10:01:39 | J39: 0 | K39: 10 | L39: GRS_配送_其它费 | M39: 燃油附加费 | N39: 0 | O39: EUR | P39: 0.04 | Q39: 0 | R39: 0.04 | S39: 0 | T39: 0.04 | Z39: 德国法兰克福2仓 | AA39: v6 | AC39: 00340434648320309580 | AD39: DE | AE39: 48599 | AF39: 55459 | AN39: 【燃油率:0.0125】 | AO39: Smart Air Filtration Kit Pro 6″ | AP39: AeroZesh T6 金属底座风机 6寸 + GrowHub E42A+控制器+黑色滤芯6寸+黑色风管6寸8ft 欧版 | AQ39: vs-官网-de
B40: 606795959309 | C40: 167739219616094550-3 | D40: 947270 | E40: 304113-P558-EU | F40: 1 | G40: FB4 | H40: DE_DHL_RETURN_L | I40: 2026-04-08 10:01:39 | J40: 24 | K40: 24 | L40: FB4尾程 | M40: 高速公路费 | N40: 0 | O40: EUR | P40: 0.19 | Q40: 0 | R40: 0.19 | S40: 0 | T40: 0.19 | X40: 千克 | Y40: 24 | Z40: 德国法兰克福2仓 | AA40: PQ_F1127_20260101 | AC40: 00340434648320309573 | AD40: DE | AE40: 48599 | AF40: 55459 | AO40: P558 60"×60"×80" PRO Grow Tent | AP40: P558 Pro款55帐篷-60"x60"x80"/150*150*200cm 22mm管径 | AQ40: vs-官网-de
B41: 606795959309 | C41: 167739219616094550-3 | D41: 947270 | E41: 304113-P558-EU | F41: 1 | G41: FB4 | H41: DE_DHL_RETURN_L | I41: 2026-04-08 10:01:39 | J41: 24 | K41: 24 | L41: FB4尾程 | M41: 回邮运费 | N41: 0 | O41: EUR | P41: 4.11 | Q41: 0 | R41: 3.37 | S41: 0 | T41: 3.37 | X41: 千克 | Y41: 24 | Z41: 德国法兰克福2仓 | AA41: PQ_F1127_20260101 | AC41: 00340434648320309573 | AD41: DE | AE41: 48599 | AF41: 55459 | AG41: PZ_DE_DHL_Paket_Domestic_DE_德国仓 | AH41: OZ_DE_法兰2仓 | AO41: P558 60"×60"×80" PRO Grow Tent | AP41: P558 Pro款55帐篷-60"x60"x80"/150*150*200cm 22mm管径 | AQ41: vs-官网-de
B42: 606795959309 | C42: 167739219616094550-3 | D42: 947270 | E42: 304113-P558-EU | F42: 1 | G42: FB4 | H42: DE_DHL_RETURN_L | I42: 2026-04-08 10:01:39 | J42: 0 | K42: 24 | L42: GRS_配送_其它费 | M42: 燃油附加费 | N42: 0 | O42: EUR | P42: 0.04 | Q42: 0 | R42: 0.04 | S42: 0 | T42: 0.04 | Z42: 德国法兰克福2仓 | AA42: v6 | AC42: 00340434648320309573 | AD42: DE | AE42: 48599 | AF42: 55459 | AN42: 【燃油率:0.0125】 | AO42: P558 60"×60"×80" PRO Grow Tent | AP42: P558 Pro款55帐篷-60"x60"x80"/150*150*200cm 22mm管径 | AQ42: vs-官网-de
B43: 606796218295 | C43: 09-14370-80704 | D43: 947270 | E43: 306146-0412-EU | F43: 2 | G43: FB4 | H43: DE_DHL_RETURN_L | I43: 2026-04-08 11:35:44 | J43: 5.9 | K43: 5.9 | L43: FB4尾程 | M43: 高速公路费 | N43: 0 | O43: EUR | P43: 0.19 | Q43: 0 | R43: 0.19 | S43: 0 | T43: 0.19 | X43: 千克 | Y43: 5.9 | Z43: 德国法兰克福2仓 | AA43: PQ_F1127_20260101 | AC43: 00340434648320309719 | AD43: DE | AE43: 01159 | AF43: 55459 | AO43: VIVOSUN钢印滤芯 黑色4" | AP43: VIVOSUN钢印滤芯 黑色4" | AQ43: vs-ebay-de
B44: 606796218295 | C44: 09-14370-80704 | D44: 947270 | E44: 306146-0412-EU | F44: 2 | G44: FB4 | H44: DE_DHL_RETURN_L | I44: 2026-04-08 11:35:44 | J44: 5.9 | K44: 5.9 | L44: FB4尾程 | M44: 回邮运费 | N44: 0 | O44: EUR | P44: 4.11 | Q44: 0 | R44: 3.37 | S44: 0 | T44: 3.37 | X44: 千克 | Y44: 5.9 | Z44: 德国法兰克福2仓 | AA44: PQ_F1127_20260101 | AC44: 00340434648320309719 | AD44: DE | AE44: 01159 | AF44: 55459 | AG44: PZ_DE_DHL_Paket_Domestic_DE_德国仓 | AH44: OZ_DE_法兰2仓 | AO44: VIVOSUN钢印滤芯 黑色4" | AP44: VIVOSUN钢印滤芯 黑色4" | AQ44: vs-ebay-de
B45: 606796218295 | C45: 09-14370-80704 | D45: 947270 | E45: 306146-0412-EU | F45: 2 | G45: FB4 | H45: DE_DHL_RETURN_L | I45: 2026-04-08 11:35:44 | J45: 0 | K45: 5.9 | L45: GRS_配送_其它费 | M45: 燃油附加费 | N45: 0 | O45: EUR | P45: 0.04 | Q45: 0 | R45: 0.04 | S45: 0 | T45: 0.04 | Z45: 德国法兰克福2仓 | AA45: v6 | AC45: 00340434648320309719 | AD45: DE | AE45: 01159 | AF45: 55459 | AN45: 【燃油率:0.0125】 | AO45: VIVOSUN钢印滤芯 黑色4" | AP45: VIVOSUN钢印滤芯 黑色4" | AQ45: vs-ebay-de
B46: 606796389101 | C46: 167902835321790128 | D46: 947270 | E46: VSE-ALC08-EU | F46: 1 | G46: FB4 | H46: DE_DHL_RETURN_L | I46: 2026-04-08 14:20:43 | J46: 25.8 | K46: 25.778 | L46: FB4尾程 | M46: 高速公路费 | N46: 0 | O46: EUR | P46: 0.19 | Q46: 0 | R46: 0.19 | S46: 0 | T46: 0.19 | X46: 千克 | Y46: 25.778 | Z46: 德国法兰克福1仓 | AA46: PQ_F1127_20260101 | AC46: 00340434648320310173 | AD46: DE | AE46: 84337 | AF46: 55459 | AO46: AeroLush Air Conditioner - 8000 BTU - European Standard | AP46: AeroLush 空调_8000BTU_欧规 | AQ46: vs-官网-de
B47: 606796389101 | C47: 167902835321790128 | D47: 947270 | E47: VSE-ALC08-EU | F47: 1 | G47: FB4 | H47: DE_DHL_RETURN_L | I47: 2026-04-08 14:20:43 | J47: 25.8 | K47: 25.778 | L47: FB4尾程 | M47: 回邮运费 | N47: 0 | O47: EUR | P47: 4.11 | Q47: 0 | R47: 3.37 | S47: 0 | T47: 3.37 | X47: 千克 | Y47: 25.778 | Z47: 德国法兰克福1仓 | AA47: PQ_F1127_20260101 | AC47: 00340434648320310173 | AD47: DE | AE47: 84337 | AF47: 55459 | AG47: PZ_DE_DHL_Paket_Domestic_DE_德国仓 | AH47: OZ_DE_法兰2仓 | AO47: AeroLush Air Conditioner - 8000 BTU - European Standard | AP47: AeroLush 空调_8000BTU_欧规 | AQ47: vs-官网-de
B48: 606796389101 | C48: 167902835321790128 | D48: 947270 | E48: VSE-ALC08-EU | F48: 1 | G48: FB4 | H48: DE_DHL_RETURN_L | I48: 2026-04-08 14:20:43 | J48: 0 | K48: 25.778 | L48: GRS_配送_其它费 | M48: 燃油附加费 | N48: 0 | O48: EUR | P48: 0.04 | Q48: 0 | R48: 0.04 | S48: 0 | T48: 0.04 | Z48: 德国法兰克福1仓 | AA48: v6 | AC48: 00340434648320310173 | AD48: DE | AE48: 84337 | AF48: 55459 | AN48: 【燃油率:0.0125】 | AO48: AeroLush Air Conditioner - 8000 BTU - European Standard | AP48: AeroLush 空调_8000BTU_欧规 | AQ48: vs-官网-de
B49: 606796674103 | C49: 168019031635567590-1 | D49: 947270 | E49: VSF-AWD4-EU | F49: 1 | G49: FB4 | H49: DE_DHL_RETURN_L | I49: 2026-04-08 17:11:31 | J49: 0.4 | K49: 0.31 | L49: FB4尾程 | M49: 高速公路费 | N49: 0 | O49: EUR | P49: 0.19 | Q49: 0 | R49: 0.19 | S49: 0 | T49: 0.19 | X49: 千克 | Y49: 0.31 | Z49: 德国法兰克福2仓 | AA49: PQ_F1127_20260101 | AC49: 00340434648320311163 | AD49: DE | AE49: 14109 | AF49: 55459 | AO49: 黑色4寸夹扇 | AP49: 黑色4寸夹扇 | AQ49: vs-官网-de
B50: 606796674103 | C50: 168019031635567590-1 | D50: 947270 | E50: VSF-AWD4-EU | F50: 1 | G50: FB4 | H50: DE_DHL_RETURN_L | I50: 2026-04-08 17:11:31 | J50: 0.4 | K50: 0.31 | L50: FB4尾程 | M50: 回邮运费 | N50: 0 | O50: EUR | P50: 4.11 | Q50: 0 | R50: 3.37 | S50: 0 | T50: 3.37 | X50: 千克 | Y50: 0.31 | Z50: 德国法兰克福2仓 | AA50: PQ_F1127_20260101 | AC50: 00340434648320311163 | AD50: DE | AE50: 14109 | AF50: 55459 | AG50: PZ_DE_DHL_Paket_Domestic_DE_德国仓 | AH50: OZ_DE_法兰2仓 | AO50: 黑色4寸夹扇 | AP50: 黑色4寸夹扇 | AQ50: vs-官网-de
B51: 606796674103 | C51: 168019031635567590-1 | D51: 947270 | E51: VSF-AWD4-EU | F51: 1 | G51: FB4 | H51: DE_DHL_RETURN_L | I51: 2026-04-08 17:11:31 | J51: 0 | K51: 0.31 | L51: GRS_配送_其它费 | M51: 燃油附加费 | N51: 0 | O51: EUR | P51: 0.04 | Q51: 0 | R51: 0.04 | S51: 0 | T51: 0.04 | Z51: 德国法兰克福2仓 | AA51: v6 | AC51: 00340434648320311163 | AD51: DE | AE51: 14109 | AF51: 55459 | AN51: 【燃油率:0.0125】 | AO51: 黑色4寸夹扇 | AP51: 黑色4寸夹扇 | AQ51: vs-官网-de
B52: 606796679240 | C52: 168019031635567590-2 | D52: 947270 | E52: VSE-ASU075-EU | F52: 1 | G52: FB4 | H52: DE_DHL_RETURN_L | I52: 2026-04-08 17:15:25 | J52: 0.4 | K52: 0.4 | L52: FB4尾程 | M52: 超长超重附加费 | N52: 0 | O52: EUR | P52: 14 | Q52: 0 | R52: 14 | S52: 0 | T52: 14 | X52: 千克 | Y52: 0.4 | Z52: 德国法兰克福2仓 | AA52: PQ_F1127_20260101 | AC52: 00340434648320311736 | AD52: DE | AE52: 14109 | AF52: 55459 | AO52: AeroStream U075 USB Humidifier | AQ52: vs-官网-de
B53: 606796679240 | C53: 168019031635567590-2 | D53: 947270 | E53: VSE-ASU075-EU | F53: 1 | G53: FB4 | H53: DE_DHL_RETURN_L | I53: 2026-04-08 17:15:25 | J53: 0.4 | K53: 0.4 | L53: FB4尾程 | M53: 高速公路费 | N53: 0 | O53: EUR | P53: 0.19 | Q53: 0 | R53: 0.19 | S53: 0 | T53: 0.19 | X53: 千克 | Y53: 0.4 | Z53: 德国法兰克福2仓 | AA53: PQ_F1127_20260101 | AC53: 00340434648320311736 | AD53: DE | AE53: 14109 | AF53: 55459 | AO53: AeroStream U075 USB Humidifier | AQ53: vs-官网-de
B54: 606796679240 | C54: 168019031635567590-2 | D54: 947270 | E54: VSE-ASU075-EU | F54: 1 | G54: FB4 | H54: DE_DHL_RETURN_L | I54: 2026-04-08 17:15:25 | J54: 0.4 | K54: 0.4 | L54: FB4尾程 | M54: 回邮运费 | N54: 0 | O54: EUR | P54: 4.11 | Q54: 0 | R54: 3.37 | S54: 0 | T54: 3.37 | X54: 千克 | Y54: 0.4 | Z54: 德国法兰克福2仓 | AA54: PQ_F1127_20260101 | AC54: 00340434648320311736 | AD54: DE | AE54: 14109 | AF54: 55459 | AG54: PZ_DE_DHL_Paket_Domestic_DE_德国仓 | AH54: OZ_DE_法兰2仓 | AO54: AeroStream U075 USB Humidifier | AQ54: vs-官网-de
B55: 606796679240 | C55: 168019031635567590-2 | D55: 947270 | E55: VSE-ASU075-EU | F55: 1 | G55: FB4 | H55: DE_DHL_RETURN_L | I55: 2026-04-08 17:15:25 | J55: 0 | K55: 0.4 | L55: GRS_配送_其它费 | M55: 燃油附加费 | N55: 0 | O55: EUR | P55: 0.04 | Q55: 0 | R55: 0.04 | S55: 0 | T55: 0.04 | Z55: 德国法兰克福2仓 | AA55: v6 | AC55: 00340434648320311736 | AD55: DE | AE55: 14109 | AF55: 55459 | AN55: 【燃油率:0.0125】 | AO55: AeroStream U075 USB Humidifier | AQ55: vs-官网-de
B56: 606797394937 | C56: 167831208152020348-1 | D56: 947270 | E56: VSC-GCC4-EU | F56: 1 | G56: FB4 | H56: DE_DHL_RETURN_L | I56: 2026-04-09 09:12:52 | J56: 0.3 | K56: 0.262 | L56: FB4尾程 | M56: 高速公路费 | N56: 0 | O56: EUR | P56: 0.19 | Q56: 0 | R56: 0.19 | S56: 0 | T56: 0.19 | X56: 千克 | Y56: 0.262 | Z56: 德国法兰克福2仓 | AA56: PQ_F1127_20260101 | AC56: 00340434648320313136 | AD56: DE | AE56: 59427 | AF56: 55459 | AO56: GrowCam C4 | AP56: GrowCam 摄像头 400W 2K-欧版 | AQ56: vs-官网-de
B57: 606797394937 | C57: 167831208152020348-1 | D57: 947270 | E57: VSC-GCC4-EU | F57: 1 | G57: FB4 | H57: DE_DHL_RETURN_L | I57: 2026-04-09 09:12:52 | J57: 0.3 | K57: 0.262 | L57: FB4尾程 | M57: 回邮运费 | N57: 0 | O57: EUR | P57: 4.11 | Q57: 0 | R57: 3.37 | S57: 0 | T57: 3.37 | X57: 千克 | Y57: 0.262 | Z57: 德国法兰克福2仓 | AA57: PQ_F1127_20260101 | AC57: 00340434648320313136 | AD57: DE | AE57: 59427 | AF57: 55459 | AG57: PZ_DE_DHL_Paket_Domestic_DE_德国仓 | AH57: OZ_DE_法兰2仓 | AO57: GrowCam C4 | AP57: GrowCam 摄像头 400W 2K-欧版 | AQ57: vs-官网-de
B58: 606797394937 | C58: 167831208152020348-1 | D58: 947270 | E58: VSC-GCC4-EU | F58: 1 | G58: FB4 | H58: DE_DHL_RETURN_L | I58: 2026-04-09 09:12:52 | J58: 0 | K58: 0.262 | L58: GRS_配送_其它费 | M58: 燃油附加费 | N58: 0 | O58: EUR | P58: 0.04 | Q58: 0 | R58: 0.04 | S58: 0 | T58: 0.04 | Z58: 德国法兰克福2仓 | AA58: v6 | AC58: 00340434648320313136 | AD58: DE | AE58: 59427 | AF58: 55459 | AN58: 【燃油率:0.0125】 | AO58: GrowCam C4 | AP58: GrowCam 摄像头 400W 2K-欧版 | AQ58: vs-官网-de
B59: 606799574290 | C59: 01-14453-34916 | D59: 947270 | E59: VSE-ATW70-EU | F59: 1 | G59: FB4 | H59: DE_DHL_RETURN_L | I59: 2026-04-10 13:42:51 | J59: 3.3 | K59: 3.216 | L59: FB4尾程 | M59: 高速公路费 | N59: 0 | O59: EUR | P59: 0.19 | Q59: 0 | R59: 0.19 | S59: 0 | T59: 0.19 | X59: 千克 | Y59: 3.216 | Z59: 德国法兰克福2仓 | AA59: PQ_F1127_20260101 | AC59: 00340434648320317080 | AD59: DE | AE59: 65187 | AF59: 55459 | AO59: AeroFlux Heater 70w | AP59: AeroFlux Heater 70w | AQ59: vs-ebay-de
B60: 606799574290 | C60: 01-14453-34916 | D60: 947270 | E60: VSE-ATW70-EU | F60: 1 | G60: FB4 | H60: DE_DHL_RETURN_L | I60: 2026-04-10 13:42:51 | J60: 3.3 | K60: 3.216 | L60: FB4尾程 | M60: 回邮运费 | N60: 0 | O60: EUR | P60: 4.11 | Q60: 0 | R60: 3.37 | S60: 0 | T60: 3.37 | X60: 千克 | Y60: 3.216 | Z60: 德国法兰克福2仓 | AA60: PQ_F1127_20260101 | AC60: 00340434648320317080 | AD60: DE | AE60: 65187 | AF60: 55459 | AG60: PZ_DE_DHL_Paket_Domestic_DE_德国仓 | AH60: OZ_DE_法兰2仓 | AO60: AeroFlux Heater 70w | AP60: AeroFlux Heater 70w | AQ60: vs-ebay-de
B61: 606799574290 | C61: 01-14453-34916 | D61: 947270 | E61: VSE-ATW70-EU | F61: 1 | G61: FB4 | H61: DE_DHL_RETURN_L | I61: 2026-04-10 13:42:51 | J61: 0 | K61: 3.216 | L61: GRS_配送_其它费 | M61: 燃油附加费 | N61: 0 | O61: EUR | P61: 0.04 | Q61: 0 | R61: 0.04 | S61: 0 | T61: 0.04 | Z61: 德国法兰克福2仓 | AA61: v6 | AC61: 00340434648320317080 | AD61: DE | AE61: 65187 | AF61: 55459 | AN61: 【燃油率:0.0125】 | AO61: AeroFlux Heater 70w | AP61: AeroFlux Heater 70w | AQ61: vs-ebay-de
B62: 606799738537 | C62: 167856961849739622-1 | D62: 947270 | E62: VSAW200-EU | F62: 1 | G62: FB4 | H62: DE_DHL_RETURN_L | I62: 2026-04-10 15:15:40 | J62: 10.5 | K62: 10.5 | L62: FB4尾程 | M62: 高速公路费 | N62: 0 | O62: EUR | P62: 0.19 | Q62: 0 | R62: 0.19 | S62: 0 | T62: 0.19 | X62: 千克 | Y62: 10.5 | Z62: 德国法兰克福2仓 | AA62: PQ_F1127_20260101 | AC62: 00340434648320317141 | AD62: DE | AE62: 66564 | AF62: 55459 | AO62: AeroLight Wing AW200 | AP62: 压铸款200W生长灯 | AQ62: vs-官网-de
B63: 606799738537 | C63: 167856961849739622-1 | D63: 947270 | E63: VSAW200-EU | F63: 1 | G63: FB4 | H63: DE_DHL_RETURN_L | I63: 2026-04-10 15:15:40 | J63: 10.5 | K63: 10.5 | L63: FB4尾程 | M63: 回邮运费 | N63: 0 | O63: EUR | P63: 4.11 | Q63: 0 | R63: 3.37 | S63: 0 | T63: 3.37 | X63: 千克 | Y63: 10.5 | Z63: 德国法兰克福2仓 | AA63: PQ_F1127_20260101 | AC63: 00340434648320317141 | AD63: DE | AE63: 66564 | AF63: 55459 | AG63: PZ_DE_DHL_Paket_Domestic_DE_德国仓 | AH63: OZ_DE_法兰2仓 | AO63: AeroLight Wing AW200 | AP63: 压铸款200W生长灯 | AQ63: vs-官网-de
B64: 606799738537 | C64: 167856961849739622-1 | D64: 947270 | E64: VSAW200-EU | F64: 1 | G64: FB4 | H64: DE_DHL_RETURN_L | I64: 2026-04-10 15:15:40 | J64: 0 | K64: 10.5 | L64: GRS_配送_其它费 | M64: 燃油附加费 | N64: 0 | O64: EUR | P64: 0.04 | Q64: 0 | R64: 0.04 | S64: 0 | T64: 0.04 | Z64: 德国法兰克福2仓 | AA64: v6 | AC64: 00340434648320317141 | AD64: DE | AE64: 66564 | AF64: 55459 | AN64: 【燃油率:0.0125】 | AO64: AeroLight Wing AW200 | AP64: 压铸款200W生长灯 | AQ64: vs-官网-de
B65: 606799738549 | C65: 167856961849739622-2 | D65: 947270 | E65: PS-002-EU;332823-100J-EU;TN-33-EU;VC-0001-EU;311001-5x5-EU;VSF-AWE6-G2-EU | F65: 1;1;1;1;1;1 | G65: FB4 | H65: DE_DHL_RETURN_L | I65: 2026-04-10 15:15:40 | J65: 5.5 | K65: 5.5 | L65: FB4尾程 | M65: 高速公路费 | N65: 0 | O65: EUR | P65: 0.19 | Q65: 0 | R65: 0.19 | S65: 0 | T65: 0.19 | X65: 千克 | Y65: 5.5 | Z65: 德国法兰克福2仓 | AA65: PQ_F1127_20260101 | AC65: 00340434648320317134 | AD65: DE | AE65: 66564 | AF65: 55459 | AO65: 黑绿配色花枝剪1个装;328 Feet (100m) PE-Coated Twist Ties;3 x 3Ft. Elastic Trellis Netting;2-Pcs. Grow Tent Vent Cover 4inch;AeroWave E6 Grow Tent Fan 6” | AP65: 黑绿配色花枝剪1个装;园林扎线-100米;弹力爬藤网 3*3FT(网格尺寸：10*10cm);防尘罩-4-Inch两个装; | AQ65: vs-官网-de
B66: 606799738549 | C66: 167856961849739622-2 | D66: 947270 | E66: PS-002-EU;332823-100J-EU;TN-33-EU;VC-0001-EU;311001-5x5-EU;VSF-AWE6-G2-EU | F66: 1;1;1;1;1;1 | G66: FB4 | H66: DE_DHL_RETURN_L | I66: 2026-04-10 15:15:40 | J66: 5.5 | K66: 5.5 | L66: FB4尾程 | M66: 回邮运费 | N66: 0 | O66: EUR | P66: 4.11 | Q66: 0 | R66: 3.37 | S66: 0 | T66: 3.37 | X66: 千克 | Y66: 5.5 | Z66: 德国法兰克福2仓 | AA66: PQ_F1127_20260101 | AC66: 00340434648320317134 | AD66: DE | AE66: 66564 | AF66: 55459 | AG66: PZ_DE_DHL_Paket_Domestic_DE_德国仓 | AH66: OZ_DE_法兰2仓 | AO66: 黑绿配色花枝剪1个装;328 Feet (100m) PE-Coated Twist Ties;3 x 3Ft. Elastic Trellis Netting;2-Pcs. Grow Tent Vent Cover 4inch;AeroWave E6 Grow Tent Fan 6” | AP66: 黑绿配色花枝剪1个装;园林扎线-100米;弹力爬藤网 3*3FT(网格尺寸：10*10cm);防尘罩-4-Inch两个装; | AQ66: vs-官网-de
B67: 606799738549 | C67: 167856961849739622-2 | D67: 947270 | E67: PS-002-EU;332823-100J-EU;TN-33-EU;VC-0001-EU;311001-5x5-EU;VSF-AWE6-G2-EU | F67: 1;1;1;1;1;1 | G67: FB4 | H67: DE_DHL_RETURN_L | I67: 2026-04-10 15:15:40 | J67: 0 | K67: 5.5 | L67: GRS_配送_其它费 | M67: 燃油附加费 | N67: 0 | O67: EUR | P67: 0.04 | Q67: 0 | R67: 0.04 | S67: 0 | T67: 0.04 | Z67: 德国法兰克福2仓 | AA67: v6 | AC67: 00340434648320317134 | AD67: DE | AE67: 66564 | AF67: 55459 | AN67: 【燃油率:0.0125】 | AO67: 黑绿配色花枝剪1个装;328 Feet (100m) PE-Coated Twist Ties;3 x 3Ft. Elastic Trellis Netting;2-Pcs. Grow Tent Vent Cover 4inch;AeroWave E6 Grow Tent Fan 6” | AP67: 黑绿配色花枝剪1个装;园林扎线-100米;弹力爬藤网 3*3FT(网格尺寸：10*10cm);防尘罩-4-Inch两个装; | AQ67: vs-官网-de
B68: 606799738550 | C68: 167856961849739622-3 | D68: 947270 | E68: VSVC-AZT4E42AP-EU | F68: 1 | G68: FB4 | H68: DE_DHL_RETURN_L | I68: 2026-04-10 15:15:40 | J68: 6.5 | K68: 6.5 | L68: FB4尾程 | M68: 高速公路费 | N68: 0 | O68: EUR | P68: 0.19 | Q68: 0 | R68: 0.19 | S68: 0 | T68: 0.19 | X68: 千克 | Y68: 6.5 | Z68: 德国法兰克福2仓 | AA68: PQ_F1127_20260101 | AC68: 00340434648320317127 | AD68: DE | AE68: 66564 | AF68: 55459 | AO68: Smart Air Filtration PRO T4 Kit 4" | AP68: AeroZesh T4 金属底座风机 4寸 + GrowHub E42A+控制器+黑色滤芯4寸+黑色风管4寸8ft 欧版 | AQ68: vs-官网-de
